Workbook

Sheet デイ
A1: コード | B1: 銘柄名（RSS） | C1: 現在値 | D1: 前日比率 | E1: 前日比率2 | F1: VWAP | G1: 当日出来高（RSS） | H1: 20日平均出来高 | I1: RVOL | J1: 補正RVOL | K1: 判定2 | L1: 信用倍率 | M1: PER | N1: PBR | O1: 配当 | P1: 配当率 | Q1: メモ | R1: 0.37847222 | S1: 60 | T1: しきい値 | U1: 1.5
A2: 4014 | B2: =IFERROR(_xll.RssMarket($A2,"銘柄名称"),"") -> カラダノート | C2: =IFERROR(_xll.RssMarket($A2,"現在値"),"") -> 449 | D2: =IFERROR(_xll.RssMarket($A2,"前日比"),"") -> -6 | E2: =IFERROR(_xll.RssMarket($A2,"前日比率"),"") -> -1.32 | F2: =IFERROR(_xll.RssMarket($A2,"出来高加重平均"),"") -> 450.6944 | G2: =IFERROR(_xll.RssMarket($A2,"出来高"),"") -> 7200 | H2: 105375 | I2: =IFERROR(G2/H2,"") -> 0.068327402 | J2: =T20D3[[#This Row],[RVOL]]*$U$2 -> 0.068327402 | K2: =IFERROR(IF(J2>=デイ!$U$1,"〇",""),"") | L2: =IFERROR(_xll.RssMarket($A2,"信用倍率"),"") -> 0 | M2: =IFERROR(_xll.RssMarket($A2,"PER"),"") -> 12.5 | N2: =IFERROR(_xll.RssMarket($A2,"PBR"),"") -> 6.24 | O2: =IFERROR(_xll.RssMarket($A2,"配当"),"") -> 0 | P2: =T20D3[[#This Row],[配当]]/T20D3[[#This Row],[現在値]] -> 0 | R2: 0.38194444 | S2: 30 | T2: 補正係数 300/経過時間（分） | U2: 1
A3: 5596 | B3: =IFERROR(_xll.RssMarket($A3,"銘柄名称"),"") -> アウトルックコンサルティング | C3: =IFERROR(_xll.RssMarket($A3,"現在値"),"") -> 1788 | D3: =IFERROR(_xll.RssMarket($A3,"前日比"),"") -> 1 | E3: =IFERROR(_xll.RssMarket($A3,"前日比率"),"") -> 0.06 | F3: =IFERROR(_xll.RssMarket($A3,"出来高加重平均"),"") -> 1787.5 | G3: =IFERROR(_xll.RssMarket($A3,"出来高"),"") -> 2400 | H3: 12905 | I3: =IFERROR(G3/H3,"") -> 0.18597443 | J3: =T20D3[[#This Row],[RVOL]]*$U$2 -> 0.18597443 | K3: =IFERROR(IF(J3>=デイ!$U$1,"〇",""),"") | L3: =IFERROR(_xll.RssMarket($A3,"信用倍率"),"") -> 0 | M3: =IFERROR(_xll.RssMarket($A3,"PER"),"") -> 14.11 | N3: =IFERROR(_xll.RssMarket($A3,"PBR"),"") -> 4.99 | O3: =IFERROR(_xll.RssMarket($A3,"配当"),"") -> 17 | P3: =T20D3[[#This Row],[配当]]/T20D3[[#This Row],[現在値]] -> 0.00950783 | R3: 0.38541667 | S3: 20
A4: 8136 | B4: =IFERROR(_xll.RssMarket($A4,"銘柄名称"),"") -> サンリオ | C4: =IFERROR(_xll.RssMarket($A4,"現在値"),"") -> 5464 | D4: =IFERROR(_xll.RssMarket($A4,"前日比"),"") -> 700 | E4: =IFERROR(_xll.RssMarket($A4,"前日比率"),"") -> 14.69 | F4: =IFERROR(_xll.RssMarket($A4,"出来高加重平均"),"") -> 5464 | G4: =IFERROR(_xll.RssMarket($A4,"出来高"),"") -> 2381700 | H4: 8534270 | I4: =IFERROR(G4/H4,"") -> 0.27907484 | J4: =T20D3[[#This Row],[RVOL]]*$U$2 -> 0.27907484 | K4: =IFERROR(IF(J4>=デイ!$U$1,"〇",""),"") | L4: =IFERROR(_xll.RssMarket($A4,"信用倍率"),"") -> 31.82 | M4: =IFERROR(_xll.RssMarket($A4,"PER"),"") -> 26.82 | N4: =IFERROR(_xll.RssMarket($A4,"PBR"),"") -> 9.31 | O4: =IFERROR(_xll.RssMarket($A4,"配当"),"") -> 62 | P4: =T20D3[[#This Row],[配当]]/T20D3[[#This Row],[現在値]] -> 0.011346999 | R4: 0.39583333 | S4: 10
A5: 6574 | B5: =IFERROR(_xll.RssMarket($A5,"銘柄名称"),"") -> コンヴァノ | C5: =IFERROR(_xll.RssMarket($A5,"現在値"),"") -> 130 | D5: =IFERROR(_xll.RssMarket($A5,"前日比"),"") -> 3 | E5: =IFERROR(_xll.RssMarket($A5,"前日比率"),"") -> 2.36 | F5: =IFERROR(_xll.RssMarket($A5,"出来高加重平均"),"") -> 127.9115 | G5: =IFERROR(_xll.RssMarket($A5,"出来高"),"") -> 2070000 | H5: 6767215 | I5: =IFERROR(G5/H5,"") -> 0.30588654 | J5: =T20D3[[#This Row],[RVOL]]*$U$2 -> 0.30588654 | K5: =IFERROR(IF(J5>=デイ!$U$1,"〇",""),"") | L5: =IFERROR(_xll.RssMarket($A5,"信用倍率"),"") -> 0 | M5: =IFERROR(_xll.RssMarket($A5,"PER"),"") -> 16.88 | N5: =IFERROR(_xll.RssMarket($A5,"PBR"),"") -> 4.99 | O5: =IFERROR(_xll.RssMarket($A5,"配当"),"") -> 0 | P5: =T20D3[[#This Row],[配当]]/T20D3[[#This Row],[現在値]] -> 0 | R5: 0.41666667 | S5: 5
A6: 5248 | B6: =IFERROR(_xll.RssMarket($A6,"銘柄名称"),"") -> テクノロジーズ | C6: =IFERROR(_xll.RssMarket($A6,"現在値"),"") -> 523 | D6: =IFERROR(_xll.RssMarket($A6,"前日比"),"") -> -15 | E6: =IFERROR(_xll.RssMarket($A6,"前日比率"),"") -> -2.79 | F6: =IFERROR(_xll.RssMarket($A6,"出来高加重平均"),"") -> 521.4175 | G6: =IFERROR(_xll.RssMarket($A6,"出来高"),"") -> 64900 | H6: 168265 | I6: =IFERROR(G6/H6,"") -> 0.38570113 | J6: =T20D3[[#This Row],[RVOL]]*$U$2 -> 0.38570113 | K6: =IFERROR(IF(J6>=デイ!$U$1,"〇",""),"") | L6: =IFERROR(_xll.RssMarket($A6,"信用倍率"),"") -> 0 | M6: =IFERROR(_xll.RssMarket($A6,"PER"),"") -> 17.72 | N6: =IFERROR(_xll.RssMarket($A6,"PBR"),"") -> 6.33 | O6: =IFERROR(_xll.RssMarket($A6,"配当"),"") -> 0 | P6: =T20D3[[#This Row],[配当]]/T20D3[[#This Row],[現在値]] -> 0 | R6: 0.45833333 | S6: 2.5
A7: 3912 | B7: =IFERROR(_xll.RssMarket($A7,"銘柄名称"),"") -> モバイルファクトリー | C7: =IFERROR(_xll.RssMarket($A7,"現在値"),"") -> 1140 | D7: =IFERROR(_xll.RssMarket($A7,"前日比"),"") -> -24 | E7: =IFERROR(_xll.RssMarket($A7,"前日比率"),"") -> -2.06 | F7: =IFERROR(_xll.RssMarket($A7,"出来高加重平均"),"") -> 1154.7619 | G7: =IFERROR(_xll.RssMarket($A7,"出来高"),"") -> 14700 | H7: 35845 | I7: =IFERROR(G7/H7,"") -> 0.41009904 | J7: =T20D3[[#This Row],[RVOL]]*$U$2 -> 0.41009904 | K7: =IFERROR(IF(J7>=デイ!$U$1,"〇",""),"") | L7: =IFERROR(_xll.RssMarket($A7,"信用倍率"),"") -> 26.11 | M7: =IFERROR(_xll.RssMarket($A7,"PER"),"") -> 9.04 | N7: =IFERROR(_xll.RssMarket($A7,"PBR"),"") -> 2.63 | O7: =IFERROR(_xll.RssMarket($A7,"配当"),"") -> 51 | P7: =T20D3[[#This Row],[配当]]/T20D3[[#This Row],[現在値]] -> 0.044736842 | R7: 0.47916667 | S7: 2
A8: 7049 | B8: =IFERROR(_xll.RssMarket($A8,"銘柄名称"),"") -> 識学 | C8: =IFERROR(_xll.RssMarket($A8,"現在値"),"") -> 925 | D8: =IFERROR(_xll.RssMarket($A8,"前日比"),"") -> -1 | E8: =IFERROR(_xll.RssMarket($A8,"前日比率"),"") -> -0.11 | F8: =IFERROR(_xll.RssMarket($A8,"出来高加重平均"),"") -> 926.1445 | G8: =IFERROR(_xll.RssMarket($A8,"出来高"),"") -> 16600 | H8: 29885 | I8: =IFERROR(G8/H8,"") -> 0.55546261 | J8: =T20D3[[#This Row],[RVOL]]*$U$2 -> 0.55546261 | K8: =IFERROR(IF(J8>=デイ!$U$1,"〇",""),"") | L8: =IFERROR(_xll.RssMarket($A8,"信用倍率"),"") -> 0.51 | M8: =IFERROR(_xll.RssMarket($A8,"PER"),"") -> 21.61 | N8: =IFERROR(_xll.RssMarket($A8,"PBR"),"") -> 2.67 | O8: =IFERROR(_xll.RssMarket($A8,"配当"),"") -> 0 | P8: =T20D3[[#This Row],[配当]]/T20D3[[#This Row],[現在値]] -> 0 | R8: 0.54166667 | S8: 1.7
A9: 3825 | B9: =IFERROR(_xll.RssMarket($A9,"銘柄名称"),"") -> リミックスポイント | C9: =IFERROR(_xll.RssMarket($A9,"現在値"),"") -> 233 | D9: =IFERROR(_xll.RssMarket($A9,"前日比"),"") -> -14 | E9: =IFERROR(_xll.RssMarket($A9,"前日比率"),"") -> -5.67 | F9: =IFERROR(_xll.RssMarket($A9,"出来高加重平均"),"") -> 236.7158 | G9: =IFERROR(_xll.RssMarket($A9,"出来高"),"") -> 2127200 | H9: 3573785 | I9: =IFERROR(G9/H9,"") -> 0.59522327 | J9: =T20D3[[#This Row],[RVOL]]*$U$2 -> 0.59522327 | K9: =IFERROR(IF(J9>=デイ!$U$1,"〇",""),"") | L9: =IFERROR(_xll.RssMarket($A9,"信用倍率"),"") -> 0 | M9: =IFERROR(_xll.RssMarket($A9,"PER"),"") -> 16.29 | N9: =IFERROR(_xll.RssMarket($A9,"PBR"),"") -> 1.04 | O9: =IFERROR(_xll.RssMarket($A9,"配当"),"") -> 5 | P9: =T20D3[[#This Row],[配当]]/T20D3[[#This Row],[現在値]] -> 0.021459227
A10: 215A | B10: =IFERROR(_xll.RssMarket($A10,"銘柄名称"),"") -> タイミー | C10: =IFERROR(_xll.RssMarket($A10,"現在値"),"") -> 1191 | D10: =IFERROR(_xll.RssMarket($A10,"前日比"),"") -> -107 | E10: =IFERROR(_xll.RssMarket($A10,"前日比率"),"") -> -8.24 | F10: =IFERROR(_xll.RssMarket($A10,"出来高加重平均"),"") -> 1218.9932 | G10: =IFERROR(_xll.RssMarket($A10,"出来高"),"") -> 3873000 | H10: 5191325 | I10: =IFERROR(G10/H10,"") -> 0.74605231 | J10: =T20D3[[#This Row],[RVOL]]*$U$2 -> 0.74605231 | K10: =IFERROR(IF(J10>=デイ!$U$1,"〇",""),"") | L10: =IFERROR(_xll.RssMarket($A10,"信用倍率"),"") -> 2.69 | M10: =IFERROR(_xll.RssMarket($A10,"PER"),"") -> 50.04 | N10: =IFERROR(_xll.RssMarket($A10,"PBR"),"") -> 8.22 | O10: =IFERROR(_xll.RssMarket($A10,"配当"),"") -> 0 | P10: =T20D3[[#This Row],[配当]]/T20D3[[#This Row],[現在値]] -> 0
A11: 9552 | B11: =IFERROR(_xll.RssMarket($A11,"銘柄名称"),"") -> クオンツ総研ホールディンク | C11: =IFERROR(_xll.RssMarket($A11,"現在値"),"") -> 1048 | D11: =IFERROR(_xll.RssMarket($A11,"前日比"),"") -> -32 | E11: =IFERROR(_xll.RssMarket($A11,"前日比率"),"") -> -2.96 | F11: =IFERROR(_xll.RssMarket($A11,"出来高加重平均"),"") -> 1049.5779 | G11: =IFERROR(_xll.RssMarket($A11,"出来高"),"") -> 428900 | H11: 537790 | I11: =IFERROR(G11/H11,"") -> 0.7975232 | J11: =T20D3[[#This Row],[RVOL]]*$U$2 -> 0.7975232 | K11: =IFERROR(IF(J11>=デイ!$U$1,"〇",""),"") | L11: =IFERROR(_xll.RssMarket($A11,"信用倍率"),"") -> 9.56 | M11: =IFERROR(_xll.RssMarket($A11,"PER"),"") -> 16.04 | N11: =IFERROR(_xll.RssMarket($A11,"PBR"),"") -> 10.75 | O11: =IFERROR(_xll.RssMarket($A11,"配当"),"") -> 6 | P11: =T20D3[[#This Row],[配当]]/T20D3[[#This Row],[現在値]] -> 0.0057251908
A12: 4222 | B12: =IFERROR(_xll.RssMarket($A12,"銘柄名称"),"") -> 児玉化学 | C12: =IFERROR(_xll.RssMarket($A12,"現在値"),"") -> 892 | D12: =IFERROR(_xll.RssMarket($A12,"前日比"),"") -> -60 | E12: =IFERROR(_xll.RssMarket($A12,"前日比率"),"") -> -6.3 | F12: =IFERROR(_xll.RssMarket($A12,"出来高加重平均"),"") -> 909.6489 | G12: =IFERROR(_xll.RssMarket($A12,"出来高"),"") -> 558400 | H12: 679610 | I12: =IFERROR(G12/H12,"") -> 0.82164771 | J12: =T20D3[[#This Row],[RVOL]]*$U$2 -> 0.82164771 | K12: =IFERROR(IF(J12>=デイ!$U$1,"〇",""),"") | L12: =IFERROR(_xll.RssMarket($A12,"信用倍率"),"") -> 0 | M12: =IFERROR(_xll.RssMarket($A12,"PER"),"") -> 0.69 | N12: =IFERROR(_xll.RssMarket($A12,"PBR"),"") -> 0.52 | O12: =IFERROR(_xll.RssMarket($A12,"配当"),"") -> 0 | P12: =T20D3[[#This Row],[配当]]/T20D3[[#This Row],[現在値]] -> 0
A13: 3939 | B13: =IFERROR(_xll.RssMarket($A13,"銘柄名称"),"") -> カナミックネットワーク | C13: =IFERROR(_xll.RssMarket($A13,"現在値"),"") -> 518 | D13: =IFERROR(_xll.RssMarket($A13,"前日比"),"") -> -25 | E13: =IFERROR(_xll.RssMarket($A13,"前日比率"),"") -> -4.6 | F13: =IFERROR(_xll.RssMarket($A13,"出来高加重平均"),"") -> 523.4664 | G13: =IFERROR(_xll.RssMarket($A13,"出来高"),"") -> 202800 | H13: 224360 | I13: =IFERROR(G13/H13,"") -> 0.90390444 | J13: =T20D3[[#This Row],[RVOL]]*$U$2 -> 0.90390444 | K13: =IFERROR(IF(J13>=デイ!$U$1,"〇",""),"") | L13: =IFERROR(_xll.RssMarket($A13,"信用倍率"),"") -> 2.03 | M13: =IFERROR(_xll.RssMarket($A13,"PER"),"") -> 17.92 | N13: =IFERROR(_xll.RssMarket($A13,"PBR"),"") -> 5.28 | O13: =IFERROR(_xll.RssMarket($A13,"配当"),"") -> 9 | P13: =T20D3[[#This Row],[配当]]/T20D3[[#This Row],[現在値]] -> 0.017374517
A14: 339A | B14: =IFERROR(_xll.RssMarket($A14,"銘柄名称"),"") -> プログレス・テクノロジース | C14: =IFERROR(_xll.RssMarket($A14,"現在値"),"") -> 1487 | D14: =IFERROR(_xll.RssMarket($A14,"前日比"),"") -> -55 | E14: =IFERROR(_xll.RssMarket($A14,"前日比率"),"") -> -3.57 | F14: =IFERROR(_xll.RssMarket($A14,"出来高加重平均"),"") -> 1485.9187 | G14: =IFERROR(_xll.RssMarket($A14,"出来高"),"") -> 51700 | H14: 54645 | I14: =IFERROR(G14/H14,"") -> 0.94610669 | J14: =T20D3[[#This Row],[RVOL]]*$U$2 -> 0.94610669 | K14: =IFERROR(IF(J14>=デイ!$U$1,"〇",""),"") | L14: =IFERROR(_xll.RssMarket($A14,"信用倍率"),"") -> 0 | M14: =IFERROR(_xll.RssMarket($A14,"PER"),"") -> 10.51 | N14: =IFERROR(_xll.RssMarket($A14,"PBR"),"") -> 2.12 | O14: =IFERROR(_xll.RssMarket($A14,"配当"),"") -> 30 | P14: =T20D3[[#This Row],[配当]]/T20D3[[#This Row],[現在値]] -> 0.020174849
A15: 9416 | B15: =IFERROR(_xll.RssMarket($A15,"銘柄名称"),"") -> ビジョン | C15: =IFERROR(_xll.RssMarket($A15,"現在値"),"") -> 1293 | D15: =IFERROR(_xll.RssMarket($A15,"前日比"),"") -> -18 | E15: =IFERROR(_xll.RssMarket($A15,"前日比率"),"") -> -1.37 | F15: =IFERROR(_xll.RssMarket($A15,"出来高加重平均"),"") -> 1298.4047 | G15: =IFERROR(_xll.RssMarket($A15,"出来高"),"") -> 422500 | H15: 363260 | I15: =IFERROR(G15/H15,"") -> 1.1630788 | J15: =T20D3[[#This Row],[RVOL]]*$U$2 -> 1.1630788 | K15: =IFERROR(IF(J15>=デイ!$U$1,"〇",""),"") | L15: =IFERROR(_xll.RssMarket($A15,"信用倍率"),"") -> 60.43 | M15: =IFERROR(_xll.RssMarket($A15,"PER"),"") -> 14.87 | N15: =IFERROR(_xll.RssMarket($A15,"PBR"),"") -> 3.32 | O15: =IFERROR(_xll.RssMarket($A15,"配当"),"") -> 50 | P15: =T20D3[[#This Row],[配当]]/T20D3[[#This Row],[現在値]] -> 0.03866976
A16: 9984 | B16: =IFERROR(_xll.RssMarket($A16,"銘柄名称"),"") -> ソフトバンクグループ | C16: =IFERROR(_xll.RssMarket($A16,"現在値"),"") -> 4390 | D16: =IFERROR(_xll.RssMarket($A16,"前日比"),"") -> -427 | E16: =IFERROR(_xll.RssMarket($A16,"前日比率"),"") -> -8.86 | F16: =IFERROR(_xll.RssMarket($A16,"出来高加重平均"),"") -> 4550.2294 | G16: =IFERROR(_xll.RssMarket($A16,"出来高"),"") -> 75769800 | H16: 61468480 | I16: =IFERROR(G16/H16,"") -> 1.232661 | J16: =T20D3[[#This Row],[RVOL]]*$U$2 -> 1.232661 | K16: =IFERROR(IF(J16>=デイ!$U$1,"〇",""),"") | L16: =IFERROR(_xll.RssMarket($A16,"信用倍率"),"") -> 11.82 | M16: =IFERROR(_xll.RssMarket($A16,"PER"),"") -> 7.58 | N16: =IFERROR(_xll.RssMarket($A16,"PBR"),"") -> 1.77 | O16: =IFERROR(_xll.RssMarket($A16,"配当"),"") -> 11 | P16: =T20D3[[#This Row],[配当]]/T20D3[[#This Row],[現在値]] -> 0.0025056948
A17: 6080 | B17: =IFERROR(_xll.RssMarket($A17,"銘柄名称"),"") -> Ｍ＆Ａキャピタルパートナー | C17: =IFERROR(_xll.RssMarket($A17,"現在値"),"") -> 3380 | D17: =IFERROR(_xll.RssMarket($A17,"前日比"),"") -> -135 | E17: =IFERROR(_xll.RssMarket($A17,"前日比率"),"") -> -3.84 | F17: =IFERROR(_xll.RssMarket($A17,"出来高加重平均"),"") -> 3414.007 | G17: =IFERROR(_xll.RssMarket($A17,"出来高"),"") -> 113300 | H17: 90265 | I17: =IFERROR(G17/H17,"") -> 1.255193 | J17: =T20D3[[#This Row],[RVOL]]*$U$2 -> 1.255193 | K17: =IFERROR(IF(J17>=デイ!$U$1,"〇",""),"") | L17: =IFERROR(_xll.RssMarket($A17,"信用倍率"),"") -> 2.78 | M17: =IFERROR(_xll.RssMarket($A17,"PER"),"") -> 14.84 | N17: =IFERROR(_xll.RssMarket($A17,"PBR"),"") -> 2.47 | O17: =IFERROR(_xll.RssMarket($A17,"配当"),"") -> 68.34 | P17: =T20D3[[#This Row],[配当]]/T20D3[[#This Row],[現在値]] -> 0.020218935
A18: 8920 | B18: =IFERROR(_xll.RssMarket($A18,"銘柄名称"),"") -> 東祥 | C18: =IFERROR(_xll.RssMarket($A18,"現在値"),"") -> 929 | D18: =IFERROR(_xll.RssMarket($A18,"前日比"),"") -> 11 | E18: =IFERROR(_xll.RssMarket($A18,"前日比率"),"") -> 1.2 | F18: =IFERROR(_xll.RssMarket($A18,"出来高加重平均"),"") -> 926.1408 | G18: =IFERROR(_xll.RssMarket($A18,"出来高"),"") -> 166100 | H18: 121930 | I18: =IFERROR(G18/H18,"") -> 1.362257 | J18: =T20D3[[#This Row],[RVOL]]*$U$2 -> 1.362257 | K18: =IFERROR(IF(J18>=デイ!$U$1,"〇",""),"") | L18: =IFERROR(_xll.RssMarket($A18,"信用倍率"),"") -> 8.21 | M18: =IFERROR(_xll.RssMarket($A18,"PER"),"") -> 9.79 | N18: =IFERROR(_xll.RssMarket($A18,"PBR"),"") -> 0.93 | O18: =IFERROR(_xll.RssMarket($A18,"配当"),"") -> 10 | P18: =T20D3[[#This Row],[配当]]/T20D3[[#This Row],[現在値]] -> 0.010764263
A19: 6071 | B19: =IFERROR(_xll.RssMarket($A19,"銘柄名称"),"") -> ＩＢＪ | C19: =IFERROR(_xll.RssMarket($A19,"現在値"),"") -> 717 | D19: =IFERROR(_xll.RssMarket($A19,"前日比"),"") -> -14 | E19: =IFERROR(_xll.RssMarket($A19,"前日比率"),"") -> -1.92 | F19: =IFERROR(_xll.RssMarket($A19,"出来高加重平均"),"") -> 721.8145 | G19: =IFERROR(_xll.RssMarket($A19,"出来高"),"") -> 296500 | H19: 208280 | I19: =IFERROR(G19/H19,"") -> 1.4235644 | J19: =T20D3[[#This Row],[RVOL]]*$U$2 -> 1.4235644 | K19: =IFERROR(IF(J19>=デイ!$U$1,"〇",""),"") | L19: =IFERROR(_xll.RssMarket($A19,"信用倍率"),"") -> 16.82 | M19: =IFERROR(_xll.RssMarket($A19,"PER"),"") -> 17.4 | N19: =IFERROR(_xll.RssMarket($A19,"PBR"),"") -> 2.93 | O19: =IFERROR(_xll.RssMarket($A19,"配当"),"") -> 10 | P19: =T20D3[[#This Row],[配当]]/T20D3[[#This Row],[現在値]] -> 0.013947001
A20: 421A | B20: =IFERROR(_xll.RssMarket($A20,"銘柄名称"),"") -> ムービン・ストラテジック・キ | C20: =IFERROR(_xll.RssMarket($A20,"現在値"),"") -> 2519 | D20: =IFERROR(_xll.RssMarket($A20,"前日比"),"") -> -89 | E20: =IFERROR(_xll.RssMarket($A20,"前日比率"),"") -> -3.41 | F20: =IFERROR(_xll.RssMarket($A20,"出来高加重平均"),"") -> 2588.796 | G20: =IFERROR(_xll.RssMarket($A20,"出来高"),"") -> 111300 | H20: 66260 | I20: =IFERROR(G20/H20,"") -> 1.6797465 | J20: =T20D3[[#This Row],[RVOL]]*$U$2 -> 1.6797465 | K20: =IFERROR(IF(J20>=デイ!$U$1,"〇",""),"") -> 〇 | L20: =IFERROR(_xll.RssMarket($A20,"信用倍率"),"") -> 0 | M20: =IFERROR(_xll.RssMarket($A20,"PER"),"") -> 19.33 | N20: =IFERROR(_xll.RssMarket($A20,"PBR"),"") -> 8.07 | O20: =IFERROR(_xll.RssMarket($A20,"配当"),"") -> 0 | P20: =T20D3[[#This Row],[配当]]/T20D3[[#This Row],[現在値]] -> 0
A21: 4389 | B21: =IFERROR(_xll.RssMarket($A21,"銘柄名称"),"") -> プロパティデータバンク | C21: =IFERROR(_xll.RssMarket($A21,"現在値"),"") -> 788 | D21: =IFERROR(_xll.RssMarket($A21,"前日比"),"") -> -56 | E21: =IFERROR(_xll.RssMarket($A21,"前日比率"),"") -> -6.64 | F21: =IFERROR(_xll.RssMarket($A21,"出来高加重平均"),"") -> 808.5185 | G21: =IFERROR(_xll.RssMarket($A21,"出来高"),"") -> 16200 | H21: 8615 | I21: =IFERROR(G21/H21,"") -> 1.8804411 | J21: =T20D3[[#This Row],[RVOL]]*$U$2 -> 1.8804411 | K21: =IFERROR(IF(J21>=デイ!$U$1,"〇",""),"") -> 〇 | L21: =IFERROR(_xll.RssMarket($A21,"信用倍率"),"") -> 0 | M21: =IFERROR(_xll.RssMarket($A21,"PER"),"") -> 12.42 | N21: =IFERROR(_xll.RssMarket($A21,"PBR"),"") -> 2.3 | O21: =IFERROR(_xll.RssMarket($A21,"配当"),"") -> 12 | P21: =T20D3[[#This Row],[配当]]/T20D3[[#This Row],[現在値]] -> 0.015228426
A22: 3661 | B22: =IFERROR(_xll.RssMarket($A22,"銘柄名称"),"") -> エムアップホールディングス | C22: =IFERROR(_xll.RssMarket($A22,"現在値"),"") -> 787 | D22: =IFERROR(_xll.RssMarket($A22,"前日比"),"") -> -13 | E22: =IFERROR(_xll.RssMarket($A22,"前日比率"),"") -> -1.63 | F22: =IFERROR(_xll.RssMarket($A22,"出来高加重平均"),"") -> 793.497 | G22: =IFERROR(_xll.RssMarket($A22,"出来高"),"") -> 973100 | H22: 497645 | I22: =IFERROR(G22/H22,"") -> 1.95541 | J22: =T20D3[[#This Row],[RVOL]]*$U$2 -> 1.95541 | K22: =IFERROR(IF(J22>=デイ!$U$1,"〇",""),"") -> 〇 | L22: =IFERROR(_xll.RssMarket($A22,"信用倍率"),"") -> 22.95 | M22: =IFERROR(_xll.RssMarket($A22,"PER"),"") -> 18 | N22: =IFERROR(_xll.RssMarket($A22,"PBR"),"") -> 6.67 | O22: =IFERROR(_xll.RssMarket($A22,"配当"),"") -> 12.5 | P22: =T20D3[[#This Row],[配当]]/T20D3[[#This Row],[現在値]] -> 0.0158831
A23: 2410 | B23: =IFERROR(_xll.RssMarket($A23,"銘柄名称"),"") -> キャリアデザインセンター | C23: =IFERROR(_xll.RssMarket($A23,"現在値"),"") -> 2445 | D23: =IFERROR(_xll.RssMarket($A23,"前日比"),"") -> -12 | E23: =IFERROR(_xll.RssMarket($A23,"前日比率"),"") -> -0.49 | F23: =IFERROR(_xll.RssMarket($A23,"出来高加重平均"),"") -> 2465.9855 | G23: =IFERROR(_xll.RssMarket($A23,"出来高"),"") -> 55300 | H23: 23690 | I23: =IFERROR(G23/H23,"") -> 2.3343183 | J23: =T20D3[[#This Row],[RVOL]]*$U$2 -> 2.3343183 | K23: =IFERROR(IF(J23>=デイ!$U$1,"〇",""),"") -> 〇 | L23: =IFERROR(_xll.RssMarket($A23,"信用倍率"),"") -> 32.83 | M23: =IFERROR(_xll.RssMarket($A23,"PER"),"") -> 10.09 | N23: =IFERROR(_xll.RssMarket($A23,"PBR"),"") -> 2.77 | O23: =IFERROR(_xll.RssMarket($A23,"配当"),"") -> 125 | P23: =T20D3[[#This Row],[配当]]/T20D3[[#This Row],[現在値]] -> 0.051124744
A24: 4495 | B24: =IFERROR(_xll.RssMarket($A24,"銘柄名称"),"") -> アイキューブドシステムズ | C24: =IFERROR(_xll.RssMarket($A24,"現在値"),"") -> 2408 | D24: =IFERROR(_xll.RssMarket($A24,"前日比"),"") -> -20 | E24: =IFERROR(_xll.RssMarket($A24,"前日比率"),"") -> -0.82 | F24: =IFERROR(_xll.RssMarket($A24,"出来高加重平均"),"") -> 2506.8266 | G24: =IFERROR(_xll.RssMarket($A24,"出来高"),"") -> 37500 | H24: 15795 | I24: =IFERROR(G24/H24,"") -> 2.374169 | J24: =T20D3[[#This Row],[RVOL]]*$U$2 -> 2.374169 | K24: =IFERROR(IF(J24>=デイ!$U$1,"〇",""),"") -> 〇 | L24: =IFERROR(_xll.RssMarket($A24,"信用倍率"),"") -> 0 | M24: =IFERROR(_xll.RssMarket($A24,"PER"),"") -> 16.58 | N24: =IFERROR(_xll.RssMarket($A24,"PBR"),"") -> 4.59 | O24: =IFERROR(_xll.RssMarket($A24,"配当"),"") -> 36 | P24: =T20D3[[#This Row],[配当]]/T20D3[[#This Row],[現在値]] -> 0.014950166
A25: 8789 | B25: =IFERROR(_xll.RssMarket($A25,"銘柄名称"),"") -> フィンテックグローバル | C25: =IFERROR(_xll.RssMarket($A25,"現在値"),"") -> 149 | D25: =IFERROR(_xll.RssMarket($A25,"前日比"),"") -> -9 | E25: =IFERROR(_xll.RssMarket($A25,"前日比率"),"") -> -5.7 | F25: =IFERROR(_xll.RssMarket($A25,"出来高加重平均"),"") -> 147.6061 | G25: =IFERROR(_xll.RssMarket($A25,"出来高"),"") -> 3593000 | H25: 1496970 | I25: =IFERROR(G25/H25,"") -> 2.4001817 | J25: =T20D3[[#This Row],[RVOL]]*$U$2 -> 2.4001817 | K25: =IFERROR(IF(J25>=デイ!$U$1,"〇",""),"") -> 〇 | L25: =IFERROR(_xll.RssMarket($A25,"信用倍率"),"") -> 20.12 | M25: =IFERROR(_xll.RssMarket($A25,"PER"),"") -> 10.64 | N25: =IFERROR(_xll.RssMarket($A25,"PBR"),"") -> 2.63 | O25: =IFERROR(_xll.RssMarket($A25,"配当"),"") -> 5 | P25: =T20D3[[#This Row],[配当]]/T20D3[[#This Row],[現在値]] -> 0.033557047
A26: 3923 | B26: =IFERROR(_xll.RssMarket($A26,"銘柄名称"),"") -> ラクス | C26: =IFERROR(_xll.RssMarket($A26,"現在値"),"") -> 765 | D26: =IFERROR(_xll.RssMarket($A26,"前日比"),"") -> -55 | E26: =IFERROR(_xll.RssMarket($A26,"前日比率"),"") -> -6.71 | F26: =IFERROR(_xll.RssMarket($A26,"出来高加重平均"),"") -> 775.5598 | G26: =IFERROR(_xll.RssMarket($A26,"出来高"),"") -> 6060600 | H26: 2474825 | I26: =IFERROR(G26/H26,"") -> 2.4489004 | J26: =T20D3[[#This Row],[RVOL]]*$U$2 -> 2.4489004 | K26: =IFERROR(IF(J26>=デイ!$U$1,"〇",""),"") -> 〇 | L26: =IFERROR(_xll.RssMarket($A26,"信用倍率"),"") -> 6.73 | M26: =IFERROR(_xll.RssMarket($A26,"PER"),"") -> 22.76 | N26: =IFERROR(_xll.RssMarket($A26,"PBR"),"") -> 11.29 | O26: =IFERROR(_xll.RssMarket($A26,"配当"),"") -> 3.4 | P26: =T20D3[[#This Row],[配当]]/T20D3[[#This Row],[現在値]] -> 0.0044444444
A27: 4496 | B27: =IFERROR(_xll.RssMarket($A27,"銘柄名称"),"") -> コマースＯＮＥＨＬＤＧＳ | C27: =IFERROR(_xll.RssMarket($A27,"現在値"),"") -> 773 | D27: =IFERROR(_xll.RssMarket($A27,"前日比"),"") -> -14 | E27: =IFERROR(_xll.RssMarket($A27,"前日比率"),"") -> -1.78 | F27: =IFERROR(_xll.RssMarket($A27,"出来高加重平均"),"") -> 799.3258 | G27: =IFERROR(_xll.RssMarket($A27,"出来高"),"") -> 8900 | H27: 3375 | I27: =IFERROR(G27/H27,"") -> 2.637037 | J27: =T20D3[[#This Row],[RVOL]]*$U$2 -> 2.637037 | K27: =IFERROR(IF(J27>=デイ!$U$1,"〇",""),"") -> 〇 | L27: =IFERROR(_xll.RssMarket($A27,"信用倍率"),"") -> 0 | M27: =IFERROR(_xll.RssMarket($A27,"PER"),"") -> 11.31 | N27: =IFERROR(_xll.RssMarket($A27,"PBR"),"") -> 2.05 | O27: =IFERROR(_xll.RssMarket($A27,"配当"),"") -> 21 | P27: =T20D3[[#This Row],[配当]]/T20D3[[#This Row],[現在値]] -> 0.027166882
A28: 3696 | B28: =IFERROR(_xll.RssMarket($A28,"銘柄名称"),"") -> セレス | C28: =IFERROR(_xll.RssMarket($A28,"現在値"),"") -> 1617 | D28: =IFERROR(_xll.RssMarket($A28,"前日比"),"") -> -189 | E28: =IFERROR(_xll.RssMarket($A28,"前日比率"),"") -> -10.47 | F28: =IFERROR(_xll.RssMarket($A28,"出来高加重平均"),"") -> 1683.2807 | G28: =IFERROR(_xll.RssMarket($A28,"出来高"),"") -> 557500 | H28: 162100 | I28: =IFERROR(G28/H28,"") -> 3.439235 | J28: =T20D3[[#This Row],[RVOL]]*$U$2 -> 3.439235 | K28: =IFERROR(IF(J28>=デイ!$U$1,"〇",""),"") -> 〇 | L28: =IFERROR(_xll.RssMarket($A28,"信用倍率"),"") -> 26.6 | M28: =IFERROR(_xll.RssMarket($A28,"PER"),"") -> 5.57 | N28: =IFERROR(_xll.RssMarket($A28,"PBR"),"") -> 1.54 | O28: =IFERROR(_xll.RssMarket($A28,"配当"),"") -> 80 | P28: =T20D3[[#This Row],[配当]]/T20D3[[#This Row],[現在値]] -> 0.049474335
A29: 4040 | B29: =IFERROR(_xll.RssMarket($A29,"銘柄名称"),"") -> 南海化学 | C29: =IFERROR(_xll.RssMarket($A29,"現在値"),"") -> 3415 | D29: =IFERROR(_xll.RssMarket($A29,"前日比"),"") -> 30 | E29: =IFERROR(_xll.RssMarket($A29,"前日比率"),"") -> 0.89 | F29: =IFERROR(_xll.RssMarket($A29,"出来高加重平均"),"") -> 3478.173 | G29: =IFERROR(_xll.RssMarket($A29,"出来高"),"") -> 41600 | H29: 11355 | I29: =IFERROR(G29/H29,"") -> 3.6635843 | J29: =T20D3[[#This Row],[RVOL]]*$U$2 -> 3.6635843 | K29: =IFERROR(IF(J29>=デイ!$U$1,"〇",""),"") -> 〇 | L29: =IFERROR(_xll.RssMarket($A29,"信用倍率"),"") -> 0 | M29: =IFERROR(_xll.RssMarket($A29,"PER"),"") -> 3.54 | N29: =IFERROR(_xll.RssMarket($A29,"PBR"),"") -> 0.79 | O29: =IFERROR(_xll.RssMarket($A29,"配当"),"") -> 60 | P29: =T20D3[[#This Row],[配当]]/T20D3[[#This Row],[現在値]] -> 0.017569546
A30: 7089 | B30: =IFERROR(_xll.RssMarket($A30,"銘柄名称"),"") -> フォースタートアップス | C30: =IFERROR(_xll.RssMarket($A30,"現在値"),"") -> 1180 | D30: =IFERROR(_xll.RssMarket($A30,"前日比"),"") -> -41 | E30: =IFERROR(_xll.RssMarket($A30,"前日比率"),"") -> -3.36 | F30: =IFERROR(_xll.RssMarket($A30,"出来高加重平均"),"") -> 1195.4867 | G30: =IFERROR(_xll.RssMarket($A30,"出来高"),"") -> 101700 | H30: 24095 | I30: =IFERROR(G30/H30,"") -> 4.2207927 | J30: =T20D3[[#This Row],[RVOL]]*$U$2 -> 4.2207927 | K30: =IFERROR(IF(J30>=デイ!$U$1,"〇",""),"") -> 〇 | L30: =IFERROR(_xll.RssMarket($A30,"信用倍率"),"") -> 0 | M30: =IFERROR(_xll.RssMarket($A30,"PER"),"") -> 12.77 | N30: =IFERROR(_xll.RssMarket($A30,"PBR"),"") -> 3.22 | O30: =IFERROR(_xll.RssMarket($A30,"配当"),"") -> 0 | P30: =T20D3[[#This Row],[配当]]/T20D3[[#This Row],[現在値]] -> 0
A33: コード | B33: 銘柄名（RSS） | C33: 現在値 | D33: 前日比 | E33: 前日比率 | F33: VWAP | G33: 当日出来高（RSS） | H33: 20日平均出来高 | I33: RVOL | J33: 補正RVOL | K33: 判定2 | L33: 信用倍率 | M33: PER | N33: PBR | O33: 配当 | P33: 配当率 | Q33: メモ
R40: 0.54166667 | S40: 1.7

Sheet 割安チェック 
A1: コード(手入力） | B1: 銘柄名（RSS） | C1: 市場部 | D1: 現在値 | E1: 前日比 | F1: 時価総額 | G1: 株式数 （百万） | H1: PER | I1: EPS | J1: PBR | K1: BPS | L1: ROE | M1: 配当 | N1: 配当率 | O1: スコア③ | P1: スコア⑤ | Q1: Gap比 | R1: 営業利益 率（予） | S1: 成長率 | T1: 現金及び預金（億） | U1: 負債（億） | V1: 総資産 | W1: ネットキャッシュ比率 | X1: 列1
A2: 9104 | B2: =IFERROR(_xll.RssMarket($A2,"銘柄名称"),"") -> 商船三井 | C2: =IFERROR(_xll.RssMarket($A2,"市場部略称"),"") -> 東Ｐ | D2: =IFERROR(_xll.RssMarket($A2,"現在値"),"") -> 5140 | E2: =IFERROR(_xll.RssMarket($A2,"前日比"),"") -> -71 | F2: =IFERROR(_xll.RssMarket($A2,"時価総額"),"") -> 1865169 | G2: =T20D35746[[#This Row],[時価総額]]/T20D35746[[#This Row],[現在値]] -> 362.87335 | H2: =IFERROR(_xll.RssMarket($A2,"PER"),"") -> 8.82 | I2: =T20D35746[[#This Row],[現在値]] / IFERROR(IF(T20D35746[[#This Row],[PER]] > 0, T20D35746[[#This Row],[PER]], 15), 15) -> 582.76644 | J2: =IFERROR(_xll.RssMarket($A2,"PBR"),"") -> 0.68 | K2: =T20D35746[[#This Row],[現在値]]/T20D35746[[#This Row],[PBR]] -> 7558.8235 | L2: =T20D35746[[#This Row],[EPS]]/T20D35746[[#This Row],[BPS]]*100 -> 7.7097506 | M2: =IFERROR(_xll.RssMarket($A2,"配当"),"") -> 200 | N2: =T20D35746[[#This Row],[配当]]/T20D35746[[#This Row],[現在値]] -> 0.038910506 | O2: =ROUND( ((IF(OR(R2="",R2<=0),20,R2)/20) *(L2/15)) /(IFERROR(IF(H2>0,H2,15),15)/15) *100,0) -> 26 | P2: =ROUND( ((IF(OR(R2="",R2<=0),20,R2)/20) *(L2/15) *((MIN(MAX(S2,0),50)/15)+1) *(1+MIN(MAX(IFERROR(IF(W2="",0,W2),0),-30),50)/200)) /(IFERROR(IF(H2>0,H2,15),15)/15) *100,0) -> 22 | Q2: =T20D35746[[#This Row],[スコア⑤]]/T20D35746[[#This Row],[スコア③]] -> 0.84615385 | R2: 5.94 | T2: 1560 | U2: 16900 | V2: 49800 | W2: =(T20D35746[[#This Row],[現金及び預金（億）]]-T20D35746[[#This Row],[負債（億）]])/T20D35746[[#This Row],[総資産]]*100 -> -30.803213 | X2: 優良銘柄
A3: 1724 | B3: =IFERROR(_xll.RssMarket($A3,"銘柄名称"),"") -> シンクレイヤ | C3: =IFERROR(_xll.RssMarket($A3,"市場部略称"),"") -> 東Ｓ | D3: =IFERROR(_xll.RssMarket($A3,"現在値"),"") -> 703 | E3: =IFERROR(_xll.RssMarket($A3,"前日比"),"") -> -30 | F3: =IFERROR(_xll.RssMarket($A3,"時価総額"),"") -> 3475 | G3: =T20D35746[[#This Row],[時価総額]]/T20D35746[[#This Row],[現在値]] -> 4.943101 | H3: =IFERROR(_xll.RssMarket($A3,"PER"),"") -> 6.28 | I3: =T20D35746[[#This Row],[現在値]] / IFERROR(IF(T20D35746[[#This Row],[PER]] > 0, T20D35746[[#This Row],[PER]], 15), 15) -> 111.94268 | J3: =IFERROR(_xll.RssMarket($A3,"PBR"),"") -> 0.53 | K3: =T20D35746[[#This Row],[現在値]]/T20D35746[[#This Row],[PBR]] -> 1326.4151 | L3: =T20D35746[[#This Row],[EPS]]/T20D35746[[#This Row],[BPS]]*100 -> 8.4394904 | M3: =IFERROR(_xll.RssMarket($A3,"配当"),"") -> 28 | N3: =T20D35746[[#This Row],[配当]]/T20D35746[[#This Row],[現在値]] -> 0.039829303 | O3: =ROUND( ((IF(OR(R3="",R3<=0),20,R3)/20) *(L3/15)) /(IFERROR(IF(H3>0,H3,15),15)/15) *100,0) -> 40 | P3: =ROUND( ((IF(OR(R3="",R3<=0),20,R3)/20) *(L3/15) *((MIN(MAX(S3,0),50)/15)+1) *(1+MIN(MAX(IFERROR(IF(W3="",0,W3),0),-30),50)/200)) /(IFERROR(IF(H3>0,H3,15),15)/15) *100,0) -> 37 | Q3: =T20D35746[[#This Row],[スコア⑤]]/T20D35746[[#This Row],[スコア③]] -> 0.925 | R3: 6 | T3: 9.48 | U3: 26.2 | V3: 114 | W3: =(T20D35746[[#This Row],[現金及び預金（億）]]-T20D35746[[#This Row],[負債（億）]])/T20D35746[[#This Row],[総資産]]*100 -> -14.666667
A4: 1605 | B4: =IFERROR(_xll.RssMarket($A4,"銘柄名称"),"") -> ＩＮＰＥＸ | C4: =IFERROR(_xll.RssMarket($A4,"市場部略称"),"") -> 東Ｐ | D4: =IFERROR(_xll.RssMarket($A4,"現在値"),"") -> 3473 | E4: =IFERROR(_xll.RssMarket($A4,"前日比"),"") -> -525 | F4: =IFERROR(_xll.RssMarket($A4,"時価総額"),"") -> 4372979 | G4: =T20D35746[[#This Row],[時価総額]]/T20D35746[[#This Row],[現在値]] -> 1259.1359 | H4: =IFERROR(_xll.RssMarket($A4,"PER"),"") -> 10.37 | I4: =T20D35746[[#This Row],[現在値]] / IFERROR(IF(T20D35746[[#This Row],[PER]] > 0, T20D35746[[#This Row],[PER]], 15), 15) -> 334.90839 | J4: =IFERROR(_xll.RssMarket($A4,"PBR"),"") -> 0.9 | K4: =T20D35746[[#This Row],[現在値]]/T20D35746[[#This Row],[PBR]] -> 3858.8889 | L4: =T20D35746[[#This Row],[EPS]]/T20D35746[[#This Row],[BPS]]*100 -> 8.6788814 | M4: =IFERROR(_xll.RssMarket($A4,"配当"),"") -> 100 | N4: =T20D35746[[#This Row],[配当]]/T20D35746[[#This Row],[現在値]] -> 0.02879355 | O4: =ROUND( ((IF(OR(R4="",R4<=0),20,R4)/20) *(L4/15)) /(IFERROR(IF(H4>0,H4,15),15)/15) *100,0) -> 234 | P4: =ROUND( ((IF(OR(R4="",R4<=0),20,R4)/20) *(L4/15) *((MIN(MAX(S4,0),50)/15)+1) *(1+MIN(MAX(IFERROR(IF(W4="",0,W4),0),-30),50)/200)) /(IFERROR(IF(H4>0,H4,15),15)/15) *100,0) -> 221 | Q4: =T20D35746[[#This Row],[スコア⑤]]/T20D35746[[#This Row],[スコア③]] -> 0.94444444 | R4: 56 | T4: 2417 | U4: 10600 | V4: 73800 | W4: =(T20D35746[[#This Row],[現金及び預金（億）]]-T20D35746[[#This Row],[負債（億）]])/T20D35746[[#This Row],[総資産]]*100 -> -11.088076 | X4: 優良銘柄
A5: 9101 | B5: =IFERROR(_xll.RssMarket($A5,"銘柄名称"),"") -> 日本郵船 | C5: =IFERROR(_xll.RssMarket($A5,"市場部略称"),"") -> 東Ｐ | D5: =IFERROR(_xll.RssMarket($A5,"現在値"),"") -> 5049 | E5: =IFERROR(_xll.RssMarket($A5,"前日比"),"") -> -61 | F5: =IFERROR(_xll.RssMarket($A5,"時価総額"),"") -> 2191778 | G5: =T20D35746[[#This Row],[時価総額]]/T20D35746[[#This Row],[現在値]] -> 434.10141 | H5: =IFERROR(_xll.RssMarket($A5,"PER"),"") -> 9.83 | I5: =T20D35746[[#This Row],[現在値]] / IFERROR(IF(T20D35746[[#This Row],[PER]] > 0, T20D35746[[#This Row],[PER]], 15), 15) -> 513.63174 | J5: =IFERROR(_xll.RssMarket($A5,"PBR"),"") -> 0.74 | K5: =T20D35746[[#This Row],[現在値]]/T20D35746[[#This Row],[PBR]] -> 6822.973 | L5: =T20D35746[[#This Row],[EPS]]/T20D35746[[#This Row],[BPS]]*100 -> 7.5279756 | M5: =IFERROR(_xll.RssMarket($A5,"配当"),"") -> 225 | N5: =T20D35746[[#This Row],[配当]]/T20D35746[[#This Row],[現在値]] -> 0.04456328 | O5: =ROUND( ((IF(OR(R5="",R5<=0),20,R5)/20) *(L5/15)) /(IFERROR(IF(H5>0,H5,15),15)/15) *100,0) -> 20 | P5: =ROUND( ((IF(OR(R5="",R5<=0),20,R5)/20) *(L5/15) *((MIN(MAX(S5,0),50)/15)+1) *(1+MIN(MAX(IFERROR(IF(W5="",0,W5),0),-30),50)/200)) /(IFERROR(IF(H5>0,H5,15),15)/15) *100,0) -> 19 | Q5: =T20D35746[[#This Row],[スコア⑤]]/T20D35746[[#This Row],[スコア③]] -> 0.95 | R5: 5.11 | T5: 1499 | U5: 6200 | V5: 43200 | W5: =(T20D35746[[#This Row],[現金及び預金（億）]]-T20D35746[[#This Row],[負債（億）]])/T20D35746[[#This Row],[総資産]]*100 -> -10.881944 | X5: 優良銘柄
A6: 2931 | B6: =IFERROR(_xll.RssMarket($A6,"銘柄名称"),"") -> ユーグレナ | C6: =IFERROR(_xll.RssMarket($A6,"市場部略称"),"") -> 東Ｐ | D6: =IFERROR(_xll.RssMarket($A6,"現在値"),"") -> 405 | E6: =IFERROR(_xll.RssMarket($A6,"前日比"),"") -> -10 | F6: =IFERROR(_xll.RssMarket($A6,"時価総額"),"") -> 55322 | G6: =T20D35746[[#This Row],[時価総額]]/T20D35746[[#This Row],[現在値]] -> 136.59753 | H6: =IFERROR(_xll.RssMarket($A6,"PER"),"") -> 0 | I6: =T20D35746[[#This Row],[現在値]] / IFERROR(IF(T20D35746[[#This Row],[PER]] > 0, T20D35746[[#This Row],[PER]], 15), 15) -> 27 | J6: =IFERROR(_xll.RssMarket($A6,"PBR"),"") -> 1.8 | K6: =T20D35746[[#This Row],[現在値]]/T20D35746[[#This Row],[PBR]] -> 225 | L6: =T20D35746[[#This Row],[EPS]]/T20D35746[[#This Row],[BPS]]*100 -> 12 | M6: =IFERROR(_xll.RssMarket($A6,"配当"),"") -> 0 | N6: =T20D35746[[#This Row],[配当]]/T20D35746[[#This Row],[現在値]] -> 0 | O6: =ROUND( ((IF(OR(R6="",R6<=0),20,R6)/20) *(L6/15)) /(IFERROR(IF(H6>0,H6,15),15)/15) *100,0) -> 80 | P6: =ROUND( ((IF(OR(R6="",R6<=0),20,R6)/20) *(L6/15) *((MIN(MAX(S6,0),50)/15)+1) *(1+MIN(MAX(IFERROR(IF(W6="",0,W6),0),-30),50)/200)) /(IFERROR(IF(H6>0,H6,15),15)/15) *100,0) -> 80 | Q6: =T20D35746[[#This Row],[スコア⑤]]/T20D35746[[#This Row],[スコア③]] -> 1 | W6: =(T20D35746[[#This Row],[現金及び預金（億）]]-T20D35746[[#This Row],[負債（億）]])/T20D35746[[#This Row],[総資産]]*100 -> #DIV/0!
A7: 3134 | B7: =IFERROR(_xll.RssMarket($A7,"銘柄名称"),"") -> Ｈａｍｅｅ | C7: =IFERROR(_xll.RssMarket($A7,"市場部略称"),"") -> 東Ｓ | D7: =IFERROR(_xll.RssMarket($A7,"現在値"),"") -> 481 | E7: =IFERROR(_xll.RssMarket($A7,"前日比"),"") -> -7 | F7: =IFERROR(_xll.RssMarket($A7,"時価総額"),"") -> 7853 | G7: =T20D35746[[#This Row],[時価総額]]/T20D35746[[#This Row],[現在値]] -> 16.326403 | H7: =IFERROR(_xll.RssMarket($A7,"PER"),"") -> 51.17 | I7: =T20D35746[[#This Row],[現在値]] / IFERROR(IF(T20D35746[[#This Row],[PER]] > 0, T20D35746[[#This Row],[PER]], 15), 15) -> 9.4000391 | J7: =IFERROR(_xll.RssMarket($A7,"PBR"),"") -> 1.57 | K7: =T20D35746[[#This Row],[現在値]]/T20D35746[[#This Row],[PBR]] -> 306.36943 | L7: =T20D35746[[#This Row],[EPS]]/T20D35746[[#This Row],[BPS]]*100 -> 3.068204 | M7: =IFERROR(_xll.RssMarket($A7,"配当"),"") -> 22.5 | N7: =T20D35746[[#This Row],[配当]]/T20D35746[[#This Row],[現在値]] -> 0.046777547 | O7: =ROUND( ((IF(OR(R7="",R7<=0),20,R7)/20) *(L7/15)) /(IFERROR(IF(H7>0,H7,15),15)/15) *100,0) -> 2 | P7: =ROUND( ((IF(OR(R7="",R7<=0),20,R7)/20) *(L7/15) *((MIN(MAX(S7,0),50)/15)+1) *(1+MIN(MAX(IFERROR(IF(W7="",0,W7),0),-30),50)/200)) /(IFERROR(IF(H7>0,H7,15),15)/15) *100,0) -> 2 | Q7: =T20D35746[[#This Row],[スコア⑤]]/T20D35746[[#This Row],[スコア③]] -> 1 | R7: 6.27 | T7: 49.9 | U7: 38.5 | V7: 170 | W7: =(T20D35746[[#This Row],[現金及び預金（億）]]-T20D35746[[#This Row],[負債（億）]])/T20D35746[[#This Row],[総資産]]*100 -> 6.7058824
A8: 3350 | B8: =IFERROR(_xll.RssMarket($A8,"銘柄名称"),"") -> メタプラネット | C8: =IFERROR(_xll.RssMarket($A8,"市場部略称"),"") -> 東Ｓ | D8: =IFERROR(_xll.RssMarket($A8,"現在値"),"") -> 325 | E8: =IFERROR(_xll.RssMarket($A8,"前日比"),"") -> -12 | F8: =IFERROR(_xll.RssMarket($A8,"時価総額"),"") -> 379211 | G8: =T20D35746[[#This Row],[時価総額]]/T20D35746[[#This Row],[現在値]] -> 1166.8031 | H8: =IFERROR(_xll.RssMarket($A8,"PER"),"") -> 0 | I8: =T20D35746[[#This Row],[現在値]] / IFERROR(IF(T20D35746[[#This Row],[PER]] > 0, T20D35746[[#This Row],[PER]], 15), 15) -> 21.666667 | J8: =IFERROR(_xll.RssMarket($A8,"PBR"),"") -> 1.06 | K8: =T20D35746[[#This Row],[現在値]]/T20D35746[[#This Row],[PBR]] -> 306.60377 | L8: =T20D35746[[#This Row],[EPS]]/T20D35746[[#This Row],[BPS]]*100 -> 7.0666667 | M8: =IFERROR(_xll.RssMarket($A8,"配当"),"") -> 0 | N8: =T20D35746[[#This Row],[配当]]/T20D35746[[#This Row],[現在値]] -> 0 | O8: =ROUND( ((IF(OR(R8="",R8<=0),20,R8)/20) *(L8/15)) /(IFERROR(IF(H8>0,H8,15),15)/15) *100,0) -> 163 | P8: =ROUND( ((IF(OR(R8="",R8<=0),20,R8)/20) *(L8/15) *((MIN(MAX(S8,0),50)/15)+1) *(1+MIN(MAX(IFERROR(IF(W8="",0,W8),0),-30),50)/200)) /(IFERROR(IF(H8>0,H8,15),15)/15) *100,0) -> 163 | Q8: =T20D35746[[#This Row],[スコア⑤]]/T20D35746[[#This Row],[スコア③]] -> 1 | R8: 69.12 | T8: 27.7 | U8: 45 | V8: 5507 | W8: =(T20D35746[[#This Row],[現金及び預金（億）]]-T20D35746[[#This Row],[負債（億）]])/T20D35746[[#This Row],[総資産]]*100 -> -0.31414563
A9: 3496 | B9: =IFERROR(_xll.RssMarket($A9,"銘柄名称"),"") -> アズーム | C9: =IFERROR(_xll.RssMarket($A9,"市場部略称"),"") -> 東Ｐ | D9: =IFERROR(_xll.RssMarket($A9,"現在値"),"") -> 4325 | E9: =IFERROR(_xll.RssMarket($A9,"前日比"),"") -> -155 | F9: =IFERROR(_xll.RssMarket($A9,"時価総額"),"") -> 53078 | G9: =T20D35746[[#This Row],[時価総額]]/T20D35746[[#This Row],[現在値]] -> 12.27237 | H9: =IFERROR(_xll.RssMarket($A9,"PER"),"") -> 24.12 | I9: =T20D35746[[#This Row],[現在値]] / IFERROR(IF(T20D35746[[#This Row],[PER]] > 0, T20D35746[[#This Row],[PER]], 15), 15) -> 179.31177 | J9: =IFERROR(_xll.RssMarket($A9,"PBR"),"") -> 7.78 | K9: =T20D35746[[#This Row],[現在値]]/T20D35746[[#This Row],[PBR]] -> 555.9126 | L9: =T20D35746[[#This Row],[EPS]]/T20D35746[[#This Row],[BPS]]*100 -> 32.25539 | M9: =IFERROR(_xll.RssMarket($A9,"配当"),"") -> 126 | N9: =T20D35746[[#This Row],[配当]]/T20D35746[[#This Row],[現在値]] -> 0.029132948 | O9: =ROUND( ((IF(OR(R9="",R9<=0),20,R9)/20) *(L9/15)) /(IFERROR(IF(H9>0,H9,15),15)/15) *100,0) -> 134 | P9: =ROUND( ((IF(OR(R9="",R9<=0),20,R9)/20) *(L9/15) *((MIN(MAX(S9,0),50)/15)+1) *(1+MIN(MAX(IFERROR(IF(W9="",0,W9),0),-30),50)/200)) /(IFERROR(IF(H9>0,H9,15),15)/15) *100,0) -> 134 | Q9: =T20D35746[[#This Row],[スコア⑤]]/T20D35746[[#This Row],[スコア③]] -> 1 | W9: =(T20D35746[[#This Row],[現金及び預金（億）]]-T20D35746[[#This Row],[負債（億）]])/T20D35746[[#This Row],[総資産]]*100 -> #DIV/0!
A10: 3660 | B10: =IFERROR(_xll.RssMarket($A10,"銘柄名称"),"") -> アイスタイル | C10: =IFERROR(_xll.RssMarket($A10,"市場部略称"),"") -> 東Ｐ | D10: =IFERROR(_xll.RssMarket($A10,"現在値"),"") -> 448 | E10: =IFERROR(_xll.RssMarket($A10,"前日比"),"") -> -23 | F10: =IFERROR(_xll.RssMarket($A10,"時価総額"),"") -> 45918 | G10: =T20D35746[[#This Row],[時価総額]]/T20D35746[[#This Row],[現在値]] -> 102.49554 | H10: =IFERROR(_xll.RssMarket($A10,"PER"),"") -> 16.05 | I10: =T20D35746[[#This Row],[現在値]] / IFERROR(IF(T20D35746[[#This Row],[PER]] > 0, T20D35746[[#This Row],[PER]], 15), 15) -> 27.912773 | J10: =IFERROR(_xll.RssMarket($A10,"PBR"),"") -> 2.5 | K10: =T20D35746[[#This Row],[現在値]]/T20D35746[[#This Row],[PBR]] -> 179.2 | L10: =T20D35746[[#This Row],[EPS]]/T20D35746[[#This Row],[BPS]]*100 -> 15.576324 | M10: =IFERROR(_xll.RssMarket($A10,"配当"),"") -> 1 | N10: =T20D35746[[#This Row],[配当]]/T20D35746[[#This Row],[現在値]] -> 0.0022321429 | O10: =ROUND( ((IF(OR(R10="",R10<=0),20,R10)/20) *(L10/15)) /(IFERROR(IF(H10>0,H10,15),15)/15) *100,0) -> 97 | P10: =ROUND( ((IF(OR(R10="",R10<=0),20,R10)/20) *(L10/15) *((MIN(MAX(S10,0),50)/15)+1) *(1+MIN(MAX(IFERROR(IF(W10="",0,W10),0),-30),50)/200)) /(IFERROR(IF(H10>0,H10,15),15)/15) *100,0) -> 97 | Q10: =T20D35746[[#This Row],[スコア⑤]]/T20D35746[[#This Row],[スコア③]] -> 1 | W10: =(T20D35746[[#This Row],[現金及び預金（億）]]-T20D35746[[#This Row],[負債（億）]])/T20D35746[[#This Row],[総資産]]*100 -> #DIV/0!
A11: 3687 | B11: =IFERROR(_xll.RssMarket($A11,"銘柄名称"),"") -> フィックスターズ | C11: =IFERROR(_xll.RssMarket($A11,"市場部略称"),"") -> 東Ｐ | D11: =IFERROR(_xll.RssMarket($A11,"現在値"),"") -> 1444 | E11: =IFERROR(_xll.RssMarket($A11,"前日比"),"") -> -38 | F11: =IFERROR(_xll.RssMarket($A11,"時価総額"),"") -> 48568 | G11: =T20D35746[[#This Row],[時価総額]]/T20D35746[[#This Row],[現在値]] -> 33.634349 | H11: =IFERROR(_xll.RssMarket($A11,"PER"),"") -> 29.17 | I11: =T20D35746[[#This Row],[現在値]] / IFERROR(IF(T20D35746[[#This Row],[PER]] > 0, T20D35746[[#This Row],[PER]], 15), 15) -> 49.502914 | J11: =IFERROR(_xll.RssMarket($A11,"PBR"),"") -> 5.64 | K11: =T20D35746[[#This Row],[現在値]]/T20D35746[[#This Row],[PBR]] -> 256.02837 | L11: =T20D35746[[#This Row],[EPS]]/T20D35746[[#This Row],[BPS]]*100 -> 19.334933 | M11: =IFERROR(_xll.RssMarket($A11,"配当"),"") -> 18 | N11: =T20D35746[[#This Row],[配当]]/T20D35746[[#This Row],[現在値]] -> 0.012465374 | O11: =ROUND( ((IF(OR(R11="",R11<=0),20,R11)/20) *(L11/15)) /(IFERROR(IF(H11>0,H11,15),15)/15) *100,0) -> 66 | P11: =ROUND( ((IF(OR(R11="",R11<=0),20,R11)/20) *(L11/15) *((MIN(MAX(S11,0),50)/15)+1) *(1+MIN(MAX(IFERROR(IF(W11="",0,W11),0),-30),50)/200)) /(IFERROR(IF(H11>0,H11,15),15)/15) *100,0) -> 66 | Q11: =T20D35746[[#This Row],[スコア⑤]]/T20D35746[[#This Row],[スコア③]] -> 1 | W11: =(T20D35746[[#This Row],[現金及び預金（億）]]-T20D35746[[#This Row],[負債（億）]])/T20D35746[[#This Row],[総資産]]*100 -> #DIV/0!
A12: 3698 | B12: =IFERROR(_xll.RssMarket($A12,"銘柄名称"),"") -> ＣＲＩ・ミドルウェア | C12: =IFERROR(_xll.RssMarket($A12,"市場部略称"),"") -> 東Ｓ | D12: =IFERROR(_xll.RssMarket($A12,"現在値"),"") -> 982 | E12: =IFERROR(_xll.RssMarket($A12,"前日比"),"") -> -82 | F12: =IFERROR(_xll.RssMarket($A12,"時価総額"),"") -> 5477 | G12: =T20D35746[[#This Row],[時価総額]]/T20D35746[[#This Row],[現在値]] -> 5.5773931 | H12: =IFERROR(_xll.RssMarket($A12,"PER"),"") -> 11.15 | I12: =T20D35746[[#This Row],[現在値]] / IFERROR(IF(T20D35746[[#This Row],[PER]] > 0, T20D35746[[#This Row],[PER]], 15), 15) -> 88.071749 | J12: =IFERROR(_xll.RssMarket($A12,"PBR"),"") -> 1.26 | K12: =T20D35746[[#This Row],[現在値]]/T20D35746[[#This Row],[PBR]] -> 779.36508 | L12: =T20D35746[[#This Row],[EPS]]/T20D35746[[#This Row],[BPS]]*100 -> 11.300448 | M12: =IFERROR(_xll.RssMarket($A12,"配当"),"") -> 27 | N12: =T20D35746[[#This Row],[配当]]/T20D35746[[#This Row],[現在値]] -> 0.027494908 | O12: =ROUND( ((IF(OR(R12="",R12<=0),20,R12)/20) *(L12/15)) /(IFERROR(IF(H12>0,H12,15),15)/15) *100,0) -> 101 | P12: =ROUND( ((IF(OR(R12="",R12<=0),20,R12)/20) *(L12/15) *((MIN(MAX(S12,0),50)/15)+1) *(1+MIN(MAX(IFERROR(IF(W12="",0,W12),0),-30),50)/200)) /(IFERROR(IF(H12>0,H12,15),15)/15) *100,0) -> 101 | Q12: =T20D35746[[#This Row],[スコア⑤]]/T20D35746[[#This Row],[スコア③]] -> 1 | W12: =(T20D35746[[#This Row],[現金及び預金（億）]]-T20D35746[[#This Row],[負債（億）]])/T20D35746[[#This Row],[総資産]]*100 -> #DIV/0!
A13: 3915 | B13: =IFERROR(_xll.RssMarket($A13,"銘柄名称"),"") -> テラスカイ | C13: =IFERROR(_xll.RssMarket($A13,"市場部略称"),"") -> 東Ｐ | D13: =IFERROR(_xll.RssMarket($A13,"現在値"),"") -> 1910 | E13: =IFERROR(_xll.RssMarket($A13,"前日比"),"") -> -78 | F13: =IFERROR(_xll.RssMarket($A13,"時価総額"),"") -> 24674 | G13: =T20D35746[[#This Row],[時価総額]]/T20D35746[[#This Row],[現在値]] -> 12.918325 | H13: =IFERROR(_xll.RssMarket($A13,"PER"),"") -> 18 | I13: =T20D35746[[#This Row],[現在値]] / IFERROR(IF(T20D35746[[#This Row],[PER]] > 0, T20D35746[[#This Row],[PER]], 15), 15) -> 106.11111 | J13: =IFERROR(_xll.RssMarket($A13,"PBR"),"") -> 2.14 | K13: =T20D35746[[#This Row],[現在値]]/T20D35746[[#This Row],[PBR]] -> 892.52336 | L13: =T20D35746[[#This Row],[EPS]]/T20D35746[[#This Row],[BPS]]*100 -> 11.888889 | M13: =IFERROR(_xll.RssMarket($A13,"配当"),"") -> 16 | N13: =T20D35746[[#This Row],[配当]]/T20D35746[[#This Row],[現在値]] -> 0.0083769634 | O13: =ROUND( ((IF(OR(R13="",R13<=0),20,R13)/20) *(L13/15)) /(IFERROR(IF(H13>0,H13,15),15)/15) *100,0) -> 66 | P13: =ROUND( ((IF(OR(R13="",R13<=0),20,R13)/20) *(L13/15) *((MIN(MAX(S13,0),50)/15)+1) *(1+MIN(MAX(IFERROR(IF(W13="",0,W13),0),-30),50)/200)) /(IFERROR(IF(H13>0,H13,15),15)/15) *100,0) -> 66 | Q13: =T20D35746[[#This Row],[スコア⑤]]/T20D35746[[#This Row],[スコア③]] -> 1 | W13: =(T20D35746[[#This Row],[現金及び預金（億）]]-T20D35746[[#This Row],[負債（億）]])/T20D35746[[#This Row],[総資産]]*100 -> #DIV/0!
A14: 4022 | B14: =IFERROR(_xll.RssMarket($A14,"銘柄名称"),"") -> ラサ工業 | C14: =IFERROR(_xll.RssMarket($A14,"市場部略称"),"") -> 東Ｐ | D14: =IFERROR(_xll.RssMarket($A14,"現在値"),"") -> 9260 | E14: =IFERROR(_xll.RssMarket($A14,"前日比"),"") -> 120 | F14: =IFERROR(_xll.RssMarket($A14,"時価総額"),"") -> 73563 | G14: =T20D35746[[#This Row],[時価総額]]/T20D35746[[#This Row],[現在値]] -> 7.9441685 | H14: =IFERROR(_xll.RssMarket($A14,"PER"),"") -> 19.03 | I14: =T20D35746[[#This Row],[現在値]] / IFERROR(IF(T20D35746[[#This Row],[PER]] > 0, T20D35746[[#This Row],[PER]], 15), 15) -> 486.60011 | J14: =IFERROR(_xll.RssMarket($A14,"PBR"),"") -> 2.43 | K14: =T20D35746[[#This Row],[現在値]]/T20D35746[[#This Row],[PBR]] -> 3810.6996 | L14: =T20D35746[[#This Row],[EPS]]/T20D35746[[#This Row],[BPS]]*100 -> 12.769312 | M14: =IFERROR(_xll.RssMarket($A14,"配当"),"") -> 145 | N14: =T20D35746[[#This Row],[配当]]/T20D35746[[#This Row],[現在値]] -> 0.015658747 | O14: =ROUND( ((IF(OR(R14="",R14<=0),20,R14)/20) *(L14/15)) /(IFERROR(IF(H14>0,H14,15),15)/15) *100,0) -> 67 | P14: =ROUND( ((IF(OR(R14="",R14<=0),20,R14)/20) *(L14/15) *((MIN(MAX(S14,0),50)/15)+1) *(1+MIN(MAX(IFERROR(IF(W14="",0,W14),0),-30),50)/200)) /(IFERROR(IF(H14>0,H14,15),15)/15) *100,0) -> 67 | Q14: =T20D35746[[#This Row],[スコア⑤]]/T20D35746[[#This Row],[スコア③]] -> 1 | W14: =(T20D35746[[#This Row],[現金及び預金（億）]]-T20D35746[[#This Row],[負債（億）]])/T20D35746[[#This Row],[総資産]]*100 -> #DIV/0!
A15: 4398 | B15: =IFERROR(_xll.RssMarket($A15,"銘柄名称"),"") -> ブロードバンドセキュリテ | C15: =IFERROR(_xll.RssMarket($A15,"市場部略称"),"") -> 東Ｓ | D15: =IFERROR(_xll.RssMarket($A15,"現在値"),"") -> 1361 | E15: =IFERROR(_xll.RssMarket($A15,"前日比"),"") -> -117 | F15: =IFERROR(_xll.RssMarket($A15,"時価総額"),"") -> 6253 | G15: =T20D35746[[#This Row],[時価総額]]/T20D35746[[#This Row],[現在値]] -> 4.5944159 | H15: =IFERROR(_xll.RssMarket($A15,"PER"),"") -> 12.98 | I15: =T20D35746[[#This Row],[現在値]] / IFERROR(IF(T20D35746[[#This Row],[PER]] > 0, T20D35746[[#This Row],[PER]], 15), 15) -> 104.85362 | J15: =IFERROR(_xll.RssMarket($A15,"PBR"),"") -> 2.82 | K15: =T20D35746[[#This Row],[現在値]]/T20D35746[[#This Row],[PBR]] -> 482.62411 | L15: =T20D35746[[#This Row],[EPS]]/T20D35746[[#This Row],[BPS]]*100 -> 21.725732 | M15: =IFERROR(_xll.RssMarket($A15,"配当"),"") -> 16 | N15: =T20D35746[[#This Row],[配当]]/T20D35746[[#This Row],[現在値]] -> 0.011756062 | O15: =ROUND( ((IF(OR(R15="",R15<=0),20,R15)/20) *(L15/15)) /(IFERROR(IF(H15>0,H15,15),15)/15) *100,0) -> 83 | P15: =ROUND( ((IF(OR(R15="",R15<=0),20,R15)/20) *(L15/15) *((MIN(MAX(S15,0),50)/15)+1) *(1+MIN(MAX(IFERROR(IF(W15="",0,W15),0),-30),50)/200)) /(IFERROR(IF(H15>0,H15,15),15)/15) *100,0) -> 83 | Q15: =T20D35746[[#This Row],[スコア⑤]]/T20D35746[[#This Row],[スコア③]] -> 1 | R15: 9.86 | W15: =(T20D35746[[#This Row],[現金及び預金（億）]]-T20D35746[[#This Row],[負債（億）]])/T20D35746[[#This Row],[総資産]]*100 -> #DIV/0!
A16: 4519 | B16: =IFERROR(_xll.RssMarket($A16,"銘柄名称"),"") -> 中外製薬 | C16: =IFERROR(_xll.RssMarket($A16,"市場部略称"),"") -> 東Ｐ | D16: =IFERROR(_xll.RssMarket($A16,"現在値"),"") -> 9280 | E16: =IFERROR(_xll.RssMarket($A16,"前日比"),"") -> 80 | F16: =IFERROR(_xll.RssMarket($A16,"時価総額"),"") -> 15581655 | G16: =T20D35746[[#This Row],[時価総額]]/T20D35746[[#This Row],[現在値]] -> 1679.0577 | H16: =IFERROR(_xll.RssMarket($A16,"PER"),"") -> 33.94 | I16: =T20D35746[[#This Row],[現在値]] / IFERROR(IF(T20D35746[[#This Row],[PER]] > 0, T20D35746[[#This Row],[PER]], 15), 15) -> 273.42369 | J16: =IFERROR(_xll.RssMarket($A16,"PBR"),"") -> 7.53 | K16: =T20D35746[[#This Row],[現在値]]/T20D35746[[#This Row],[PBR]] -> 1232.4037 | L16: =T20D35746[[#This Row],[EPS]]/T20D35746[[#This Row],[BPS]]*100 -> 22.186211 | M16: =IFERROR(_xll.RssMarket($A16,"配当"),"") -> 132 | N16: =T20D35746[[#This Row],[配当]]/T20D35746[[#This Row],[現在値]] -> 0.014224138 | O16: =ROUND( ((IF(OR(R16="",R16<=0),20,R16)/20) *(L16/15)) /(IFERROR(IF(H16>0,H16,15),15)/15) *100,0) -> 65 | P16: =ROUND( ((IF(OR(R16="",R16<=0),20,R16)/20) *(L16/15) *((MIN(MAX(S16,0),50)/15)+1) *(1+MIN(MAX(IFERROR(IF(W16="",0,W16),0),-30),50)/200)) /(IFERROR(IF(H16>0,H16,15),15)/15) *100,0) -> 65 | Q16: =T20D35746[[#This Row],[スコア⑤]]/T20D35746[[#This Row],[スコア③]] -> 1 | W16: =(T20D35746[[#This Row],[現金及び預金（億）]]-T20D35746[[#This Row],[負債（億）]])/T20D35746[[#This Row],[総資産]]*100 -> #DIV/0! | X16: 優良銘柄
A17: 4568 | B17: =IFERROR(_xll.RssMarket($A17,"銘柄名称"),"") -> 第一三共 | C17: =IFERROR(_xll.RssMarket($A17,"市場部略称"),"") -> 東Ｐ | D17: =IFERROR(_xll.RssMarket($A17,"現在値"),"") -> 2937.5 | E17: =IFERROR(_xll.RssMarket($A17,"前日比"),"") -> 31.5 | F17: =IFERROR(_xll.RssMarket($A17,"時価総額"),"") -> 5564654 | G17: =T20D35746[[#This Row],[時価総額]]/T20D35746[[#This Row],[現在値]] -> 1894.3503 | H17: =IFERROR(_xll.RssMarket($A17,"PER"),"") -> 18.84 | I17: =T20D35746[[#This Row],[現在値]] / IFERROR(IF(T20D35746[[#This Row],[PER]] > 0, T20D35746[[#This Row],[PER]], 15), 15) -> 155.91826 | J17: =IFERROR(_xll.RssMarket($A17,"PBR"),"") -> 3.29 | K17: =T20D35746[[#This Row],[現在値]]/T20D35746[[#This Row],[PBR]] -> 892.85714 | L17: =T20D35746[[#This Row],[EPS]]/T20D35746[[#This Row],[BPS]]*100 -> 17.462845 | M17: =IFERROR(_xll.RssMarket($A17,"配当"),"") -> 78 | N17: =T20D35746[[#This Row],[配当]]/T20D35746[[#This Row],[現在値]] -> 0.026553191 | O17: =ROUND( ((IF(OR(R17="",R17<=0),20,R17)/20) *(L17/15)) /(IFERROR(IF(H17>0,H17,15),15)/15) *100,0) -> 93 | P17: =ROUND( ((IF(OR(R17="",R17<=0),20,R17)/20) *(L17/15) *((MIN(MAX(S17,0),50)/15)+1) *(1+MIN(MAX(IFERROR(IF(W17="",0,W17),0),-30),50)/200)) /(IFERROR(IF(H17>0,H17,15),15)/15) *100,0) -> 93 | Q17: =T20D35746[[#This Row],[スコア⑤]]/T20D35746[[#This Row],[スコア③]] -> 1 | W17: =(T20D35746[[#This Row],[現金及び預金（億）]]-T20D35746[[#This Row],[負債（億）]])/T20D35746[[#This Row],[総資産]]*100 -> #DIV/0! | X17: 優良銘柄
A18: 4661 | B18: =IFERROR(_xll.RssMarket($A18,"銘柄名称"),"") -> オリエンタルランド | C18: =IFERROR(_xll.RssMarket($A18,"市場部略称"),"") -> 東Ｐ | D18: =IFERROR(_xll.RssMarket($A18,"現在値"),"") -> 2819 | E18: =IFERROR(_xll.RssMarket($A18,"前日比"),"") -> 5.5 | F18: =IFERROR(_xll.RssMarket($A18,"時価総額"),"") -> 5075470 | G18: =T20D35746[[#This Row],[時価総額]]/T20D35746[[#This Row],[現在値]] -> 1800.4505 | H18: =IFERROR(_xll.RssMarket($A18,"PER"),"") -> 37.88 | I18: =T20D35746[[#This Row],[現在値]] / IFERROR(IF(T20D35746[[#This Row],[PER]] > 0, T20D35746[[#This Row],[PER]], 15), 15) -> 74.419219 | J18: =IFERROR(_xll.RssMarket($A18,"PBR"),"") -> 4.49 | K18: =T20D35746[[#This Row],[現在値]]/T20D35746[[#This Row],[PBR]] -> 627.83964 | L18: =T20D35746[[#This Row],[EPS]]/T20D35746[[#This Row],[BPS]]*100 -> 11.853221 | M18: =IFERROR(_xll.RssMarket($A18,"配当"),"") -> 14 | N18: =T20D35746[[#This Row],[配当]]/T20D35746[[#This Row],[現在値]] -> 0.0049663001 | O18: =ROUND( ((IF(OR(R18="",R18<=0),20,R18)/20) *(L18/15)) /(IFERROR(IF(H18>0,H18,15),15)/15) *100,0) -> 36 | P18: =ROUND( ((IF(OR(R18="",R18<=0),20,R18)/20) *(L18/15) *((MIN(MAX(S18,0),50)/15)+1) *(1+MIN(MAX(IFERROR(IF(W18="",0,W18),0),-30),50)/200)) /(IFERROR(IF(H18>0,H18,15),15)/15) *100,0) -> 36 | Q18: =T20D35746[[#This Row],[スコア⑤]]/T20D35746[[#This Row],[スコア③]] -> 1 | R18: 23.08 | W18: =(T20D35746[[#This Row],[現金及び預金（億）]]-T20D35746[[#This Row],[負債（億）]])/T20D35746[[#This Row],[総資産]]*100 -> #DIV/0!
A19: 4784 | B19: =IFERROR(_xll.RssMarket($A19,"銘柄名称"),"") -> ＧＭＯインターネット | C19: =IFERROR(_xll.RssMarket($A19,"市場部略称"),"") -> 東Ｐ | D19: =IFERROR(_xll.RssMarket($A19,"現在値"),"") -> 804 | E19: =IFERROR(_xll.RssMarket($A19,"前日比"),"") -> -89 | F19: =IFERROR(_xll.RssMarket($A19,"時価総額"),"") -> 220857 | G19: =T20D35746[[#This Row],[時価総額]]/T20D35746[[#This Row],[現在値]] -> 274.69776 | H19: =IFERROR(_xll.RssMarket($A19,"PER"),"") -> 44.17 | I19: =T20D35746[[#This Row],[現在値]] / IFERROR(IF(T20D35746[[#This Row],[PER]] > 0, T20D35746[[#This Row],[PER]], 15), 15) -> 18.2024 | J19: =IFERROR(_xll.RssMarket($A19,"PBR"),"") -> 16.72 | K19: =T20D35746[[#This Row],[現在値]]/T20D35746[[#This Row],[PBR]] -> 48.086124 | L19: =T20D35746[[#This Row],[EPS]]/T20D35746[[#This Row],[BPS]]*100 -> 37.853747 | M19: =IFERROR(_xll.RssMarket($A19,"配当"),"") -> 18.2 | N19: =T20D35746[[#This Row],[配当]]/T20D35746[[#This Row],[現在値]] -> 0.022636816 | O19: =ROUND( ((IF(OR(R19="",R19<=0),20,R19)/20) *(L19/15)) /(IFERROR(IF(H19>0,H19,15),15)/15) *100,0) -> 86 | P19: =ROUND( ((IF(OR(R19="",R19<=0),20,R19)/20) *(L19/15) *((MIN(MAX(S19,0),50)/15)+1) *(1+MIN(MAX(IFERROR(IF(W19="",0,W19),0),-30),50)/200)) /(IFERROR(IF(H19>0,H19,15),15)/15) *100,0) -> 86 | Q19: =T20D35746[[#This Row],[スコア⑤]]/T20D35746[[#This Row],[スコア③]] -> 1 | W19: =(T20D35746[[#This Row],[現金及び預金（億）]]-T20D35746[[#This Row],[負債（億）]])/T20D35746[[#This Row],[総資産]]*100 -> #DIV/0!
A20: 5121 | B20: =IFERROR(_xll.RssMarket($A20,"銘柄名称"),"") -> 藤倉コンポジット | C20: =IFERROR(_xll.RssMarket($A20,"市場部略称"),"") -> 東Ｐ | D20: =IFERROR(_xll.RssMarket($A20,"現在値"),"") -> 2535 | E20: =IFERROR(_xll.RssMarket($A20,"前日比"),"") -> -47 | F20: =IFERROR(_xll.RssMarket($A20,"時価総額"),"") -> 50890 | G20: =T20D35746[[#This Row],[時価総額]]/T20D35746[[#This Row],[現在値]] -> 20.074951 | H20: =IFERROR(_xll.RssMarket($A20,"PER"),"") -> 13.1 | I20: =T20D35746[[#This Row],[現在値]] / IFERROR(IF(T20D35746[[#This Row],[PER]] > 0, T20D35746[[#This Row],[PER]], 15), 15) -> 193.51145 | J20: =IFERROR(_xll.RssMarket($A20,"PBR"),"") -> 1.35 | K20: =T20D35746[[#This Row],[現在値]]/T20D35746[[#This Row],[PBR]] -> 1877.7778 | L20: =T20D35746[[#This Row],[EPS]]/T20D35746[[#This Row],[BPS]]*100 -> 10.305344 | M20: =IFERROR(_xll.RssMarket($A20,"配当"),"") -> 66 | N20: =T20D35746[[#This Row],[配当]]/T20D35746[[#This Row],[現在値]] -> 0.026035503 | O20: =ROUND( ((IF(OR(R20="",R20<=0),20,R20)/20) *(L20/15)) /(IFERROR(IF(H20>0,H20,15),15)/15) *100,0) -> 48 | P20: =ROUND( ((IF(OR(R20="",R20<=0),20,R20)/20) *(L20/15) *((MIN(MAX(S20,0),50)/15)+1) *(1+MIN(MAX(IFERROR(IF(W20="",0,W20),0),-30),50)/200)) /(IFERROR(IF(H20>0,H20,15),15)/15) *100,0) -> 48 | Q20: =T20D35746[[#This Row],[スコア⑤]]/T20D35746[[#This Row],[スコア③]] -> 1 | R20: 12.29 | W20: =(T20D35746[[#This Row],[現金及び預金（億）]]-T20D35746[[#This Row],[負債（億）]])/T20D35746[[#This Row],[総資産]]*100 -> #DIV/0!
A21: 6013 | B21: =IFERROR(_xll.RssMarket($A21,"銘柄名称"),"") -> タクマ | C21: =IFERROR(_xll.RssMarket($A21,"市場部略称"),"") -> 東Ｐ | D21: =IFERROR(_xll.RssMarket($A21,"現在値"),"") -> 2602 | E21: =IFERROR(_xll.RssMarket($A21,"前日比"),"") -> -79 | F21: =IFERROR(_xll.RssMarket($A21,"時価総額"),"") -> 209556 | G21: =T20D35746[[#This Row],[時価総額]]/T20D35746[[#This Row],[現在値]] -> 80.53651 | H21: =IFERROR(_xll.RssMarket($A21,"PER"),"") -> 15.27 | I21: =T20D35746[[#This Row],[現在値]] / IFERROR(IF(T20D35746[[#This Row],[PER]] > 0, T20D35746[[#This Row],[PER]], 15), 15) -> 170.39948 | J21: =IFERROR(_xll.RssMarket($A21,"PBR"),"") -> 1.8 | K21: =T20D35746[[#This Row],[現在値]]/T20D35746[[#This Row],[PBR]] -> 1445.5556 | L21: =T20D35746[[#This Row],[EPS]]/T20D35746[[#This Row],[BPS]]*100 -> 11.787819 | M21: =IFERROR(_xll.RssMarket($A21,"配当"),"") -> 79 | N21: =T20D35746[[#This Row],[配当]]/T20D35746[[#This Row],[現在値]] -> 0.030361261 | O21: =ROUND( ((IF(OR(R21="",R21<=0),20,R21)/20) *(L21/15)) /(IFERROR(IF(H21>0,H21,15),15)/15) *100,0) -> 77 | P21: =ROUND( ((IF(OR(R21="",R21<=0),20,R21)/20) *(L21/15) *((MIN(MAX(S21,0),50)/15)+1) *(1+MIN(MAX(IFERROR(IF(W21="",0,W21),0),-30),50)/200)) /(IFERROR(IF(H21>0,H21,15),15)/15) *100,0) -> 77 | Q21: =T20D35746[[#This Row],[スコア⑤]]/T20D35746[[#This Row],[スコア③]] -> 1 | W21: =(T20D35746[[#This Row],[現金及び預金（億）]]-T20D35746[[#This Row],[負債（億）]])/T20D35746[[#This Row],[総資産]]*100 -> #DIV/0!
A22: 6039 | B22: =IFERROR(_xll.RssMarket($A22,"銘柄名称"),"") -> 日本動物高度医療 | C22: =IFERROR(_xll.RssMarket($A22,"市場部略称"),"") -> 東Ｇ | D22: =IFERROR(_xll.RssMarket($A22,"現在値"),"") -> 1304 | E22: =IFERROR(_xll.RssMarket($A22,"前日比"),"") -> -21 | F22: =IFERROR(_xll.RssMarket($A22,"時価総額"),"") -> 18765 | G22: =T20D35746[[#This Row],[時価総額]]/T20D35746[[#This Row],[現在値]] -> 14.390337 | H22: =IFERROR(_xll.RssMarket($A22,"PER"),"") -> 23.07 | I22: =T20D35746[[#This Row],[現在値]] / IFERROR(IF(T20D35746[[#This Row],[PER]] > 0, T20D35746[[#This Row],[PER]], 15), 15) -> 56.523624 | J22: =IFERROR(_xll.RssMarket($A22,"PBR"),"") -> 3.77 | K22: =T20D35746[[#This Row],[現在値]]/T20D35746[[#This Row],[PBR]] -> 345.88859 | L22: =T20D35746[[#This Row],[EPS]]/T20D35746[[#This Row],[BPS]]*100 -> 16.341569 | M22: =IFERROR(_xll.RssMarket($A22,"配当"),"") -> 8 | N22: =T20D35746[[#This Row],[配当]]/T20D35746[[#This Row],[現在値]] -> 0.0061349693 | O22: =ROUND( ((IF(OR(R22="",R22<=0),20,R22)/20) *(L22/15)) /(IFERROR(IF(H22>0,H22,15),15)/15) *100,0) -> 71 | P22: =ROUND( ((IF(OR(R22="",R22<=0),20,R22)/20) *(L22/15) *((MIN(MAX(S22,0),50)/15)+1) *(1+MIN(MAX(IFERROR(IF(W22="",0,W22),0),-30),50)/200)) /(IFERROR(IF(H22>0,H22,15),15)/15) *100,0) -> 71 | Q22: =T20D35746[[#This Row],[スコア⑤]]/T20D35746[[#This Row],[スコア③]] -> 1 | W22: =(T20D35746[[#This Row],[現金及び預金（億）]]-T20D35746[[#This Row],[負債（億）]])/T20D35746[[#This Row],[総資産]]*100 -> #DIV/0!
A23: 6653 | B23: =IFERROR(_xll.RssMarket($A23,"銘柄名称"),"") -> 正興電機製作所 | C23: =IFERROR(_xll.RssMarket($A23,"市場部略称"),"") -> 東Ｐ | D23: =IFERROR(_xll.RssMarket($A23,"現在値"),"") -> 2260 | E23: =IFERROR(_xll.RssMarket($A23,"前日比"),"") -> -471 | F23: =IFERROR(_xll.RssMarket($A23,"時価総額"),"") -> 31433 | G23: =T20D35746[[#This Row],[時価総額]]/T20D35746[[#This Row],[現在値]] -> 13.908407 | H23: =IFERROR(_xll.RssMarket($A23,"PER"),"") -> 15.28 | I23: =T20D35746[[#This Row],[現在値]] / IFERROR(IF(T20D35746[[#This Row],[PER]] > 0, T20D35746[[#This Row],[PER]], 15), 15) -> 147.90576 | J23: =IFERROR(_xll.RssMarket($A23,"PBR"),"") -> 1.82 | K23: =T20D35746[[#This Row],[現在値]]/T20D35746[[#This Row],[PBR]] -> 1241.7582 | L23: =T20D35746[[#This Row],[EPS]]/T20D35746[[#This Row],[BPS]]*100 -> 11.910995 | M23: =IFERROR(_xll.RssMarket($A23,"配当"),"") -> 50 | N23: =T20D35746[[#This Row],[配当]]/T20D35746[[#This Row],[現在値]] -> 0.022123894 | O23: =ROUND( ((IF(OR(R23="",R23<=0),20,R23)/20) *(L23/15)) /(IFERROR(IF(H23>0,H23,15),15)/15) *100,0) -> 78 | P23: =ROUND( ((IF(OR(R23="",R23<=0),20,R23)/20) *(L23/15) *((MIN(MAX(S23,0),50)/15)+1) *(1+MIN(MAX(IFERROR(IF(W23="",0,W23),0),-30),50)/200)) /(IFERROR(IF(H23>0,H23,15),15)/15) *100,0) -> 78 | Q23: =T20D35746[[#This Row],[スコア⑤]]/T20D35746[[#This Row],[スコア③]] -> 1 | W23: =(T20D35746[[#This Row],[現金及び預金（億）]]-T20D35746[[#This Row],[負債（億）]])/T20D35746[[#This Row],[総資産]]*100 -> #DIV/0!
A24: 7927 | B24: =IFERROR(_xll.RssMarket($A24,"銘柄名称"),"") -> ムトー精工 | C24: =IFERROR(_xll.RssMarket($A24,"市場部略称"),"") -> 東Ｓ | D24: =IFERROR(_xll.RssMarket($A24,"現在値"),"") -> 2336 | E24: =IFERROR(_xll.RssMarket($A24,"前日比"),"") -> -100 | F24: =IFERROR(_xll.RssMarket($A24,"時価総額"),"") -> 18079 | G24: =T20D35746[[#This Row],[時価総額]]/T20D35746[[#This Row],[現在値]] -> 7.7392979 | H24: =IFERROR(_xll.RssMarket($A24,"PER"),"") -> 9.27 | I24: =T20D35746[[#This Row],[現在値]] / IFERROR(IF(T20D35746[[#This Row],[PER]] > 0, T20D35746[[#This Row],[PER]], 15), 15) -> 251.99569 | J24: =IFERROR(_xll.RssMarket($A24,"PBR"),"") -> 0.86 | K24: =T20D35746[[#This Row],[現在値]]/T20D35746[[#This Row],[PBR]] -> 2716.2791 | L24: =T20D35746[[#This Row],[EPS]]/T20D35746[[#This Row],[BPS]]*100 -> 9.2772384 | M24: =IFERROR(_xll.RssMarket($A24,"配当"),"") -> 101 | N24: =T20D35746[[#This Row],[配当]]/T20D35746[[#This Row],[現在値]] -> 0.043236301 | O24: =ROUND( ((IF(OR(R24="",R24<=0),20,R24)/20) *(L24/15)) /(IFERROR(IF(H24>0,H24,15),15)/15) *100,0) -> 100 | P24: =ROUND( ((IF(OR(R24="",R24<=0),20,R24)/20) *(L24/15) *((MIN(MAX(S24,0),50)/15)+1) *(1+MIN(MAX(IFERROR(IF(W24="",0,W24),0),-30),50)/200)) /(IFERROR(IF(H24>0,H24,15),15)/15) *100,0) -> 100 | Q24: =T20D35746[[#This Row],[スコア⑤]]/T20D35746[[#This Row],[スコア③]] -> 1 | W24: =(T20D35746[[#This Row],[現金及び預金（億）]]-T20D35746[[#This Row],[負債（億）]])/T20D35746[[#This Row],[総資産]]*100 -> #DIV/0!
A25: 9031 | B25: =IFERROR(_xll.RssMarket($A25,"銘柄名称"),"") -> 西日本鉄道 | C25: =IFERROR(_xll.RssMarket($A25,"市場部略称"),"") -> 東Ｐ | D25: =IFERROR(_xll.RssMarket($A25,"現在値"),"") -> 3145 | E25: =IFERROR(_xll.RssMarket($A25,"前日比"),"") -> 108 | F25: =IFERROR(_xll.RssMarket($A25,"時価総額"),"") -> 249587 | G25: =T20D35746[[#This Row],[時価総額]]/T20D35746[[#This Row],[現在値]] -> 79.359936 | H25: =IFERROR(_xll.RssMarket($A25,"PER"),"") -> 9.49 | I25: =T20D35746[[#This Row],[現在値]] / IFERROR(IF(T20D35746[[#This Row],[PER]] > 0, T20D35746[[#This Row],[PER]], 15), 15) -> 331.40148 | J25: =IFERROR(_xll.RssMarket($A25,"PBR"),"") -> 0.92 | K25: =T20D35746[[#This Row],[現在値]]/T20D35746[[#This Row],[PBR]] -> 3418.4783 | L25: =T20D35746[[#This Row],[EPS]]/T20D35746[[#This Row],[BPS]]*100 -> 9.6944152 | M25: =IFERROR(_xll.RssMarket($A25,"配当"),"") -> 50 | N25: =T20D35746[[#This Row],[配当]]/T20D35746[[#This Row],[現在値]] -> 0.015898251 | O25: =ROUND( ((IF(OR(R25="",R25<=0),20,R25)/20) *(L25/15)) /(IFERROR(IF(H25>0,H25,15),15)/15) *100,0) -> 102 | P25: =ROUND( ((IF(OR(R25="",R25<=0),20,R25)/20) *(L25/15) *((MIN(MAX(S25,0),50)/15)+1) *(1+MIN(MAX(IFERROR(IF(W25="",0,W25),0),-30),50)/200)) /(IFERROR(IF(H25>0,H25,15),15)/15) *100,0) -> 102 | Q25: =T20D35746[[#This Row],[スコア⑤]]/T20D35746[[#This Row],[スコア③]] -> 1 | W25: =(T20D35746[[#This Row],[現金及び預金（億）]]-T20D35746[[#This Row],[負債（億）]])/T20D35746[[#This Row],[総資産]]*100 -> #DIV/0!
A26: 9503 | B26: =IFERROR(_xll.RssMarket($A26,"銘柄名称"),"") -> 関西電力 | C26: =IFERROR(_xll.RssMarket($A26,"市場部略称"),"") -> 東Ｐ | D26: =IFERROR(_xll.RssMarket($A26,"現在値"),"") -> 2745.5 | E26: =IFERROR(_xll.RssMarket($A26,"前日比"),"") -> 2 | F26: =IFERROR(_xll.RssMarket($A26,"時価総額"),"") -> 3061033 | G26: =T20D35746[[#This Row],[時価総額]]/T20D35746[[#This Row],[現在値]] -> 1114.9273 | H26: =IFERROR(_xll.RssMarket($A26,"PER"),"") -> 8.49 | I26: =T20D35746[[#This Row],[現在値]] / IFERROR(IF(T20D35746[[#This Row],[PER]] > 0, T20D35746[[#This Row],[PER]], 15), 15) -> 323.38045 | J26: =IFERROR(_xll.RssMarket($A26,"PBR"),"") -> 0.93 | K26: =T20D35746[[#This Row],[現在値]]/T20D35746[[#This Row],[PBR]] -> 2952.1505 | L26: =T20D35746[[#This Row],[EPS]]/T20D35746[[#This Row],[BPS]]*100 -> 10.954064 | M26: =IFERROR(_xll.RssMarket($A26,"配当"),"") -> 75 | N26: =T20D35746[[#This Row],[配当]]/T20D35746[[#This Row],[現在値]] -> 0.027317429 | O26: =ROUND( ((IF(OR(R26="",R26<=0),20,R26)/20) *(L26/15)) /(IFERROR(IF(H26>0,H26,15),15)/15) *100,0) -> 72 | P26: =ROUND( ((IF(OR(R26="",R26<=0),20,R26)/20) *(L26/15) *((MIN(MAX(S26,0),50)/15)+1) *(1+MIN(MAX(IFERROR(IF(W26="",0,W26),0),-30),50)/200)) /(IFERROR(IF(H26>0,H26,15),15)/15) *100,0) -> 72 | Q26: =T20D35746[[#This Row],[スコア⑤]]/T20D35746[[#This Row],[スコア③]] -> 1 | R26: 11.11 | W26: =(T20D35746[[#This Row],[現金及び預金（億）]]-T20D35746[[#This Row],[負債（億）]])/T20D35746[[#This Row],[総資産]]*100 -> #DIV/0!
A27: 9531 | B27: =IFERROR(_xll.RssMarket($A27,"銘柄名称"),"") -> 東京瓦斯 | C27: =IFERROR(_xll.RssMarket($A27,"市場部略称"),"") -> 東Ｐ | D27: =IFERROR(_xll.RssMarket($A27,"現在値"),"") -> 7769 | E27: =IFERROR(_xll.RssMarket($A27,"前日比"),"") -> -11 | F27: =IFERROR(_xll.RssMarket($A27,"時価総額"),"") -> 2883004 | G27: =T20D35746[[#This Row],[時価総額]]/T20D35746[[#This Row],[現在値]] -> 371.09075 | H27: =IFERROR(_xll.RssMarket($A27,"PER"),"") -> 13.48 | I27: =T20D35746[[#This Row],[現在値]] / IFERROR(IF(T20D35746[[#This Row],[PER]] > 0, T20D35746[[#This Row],[PER]], 15), 15) -> 576.33531 | J27: =IFERROR(_xll.RssMarket($A27,"PBR"),"") -> 1.69 | K27: =T20D35746[[#This Row],[現在値]]/T20D35746[[#This Row],[PBR]] -> 4597.0414 | L27: =T20D35746[[#This Row],[EPS]]/T20D35746[[#This Row],[BPS]]*100 -> 12.537092 | M27: =IFERROR(_xll.RssMarket($A27,"配当"),"") -> 100 | N27: =T20D35746[[#This Row],[配当]]/T20D35746[[#This Row],[現在値]] -> 0.012871669 | O27: =ROUND( ((IF(OR(R27="",R27<=0),20,R27)/20) *(L27/15)) /(IFERROR(IF(H27>0,H27,15),15)/15) *100,0) -> 93 | P27: =ROUND( ((IF(OR(R27="",R27<=0),20,R27)/20) *(L27/15) *((MIN(MAX(S27,0),50)/15)+1) *(1+MIN(MAX(IFERROR(IF(W27="",0,W27),0),-30),50)/200)) /(IFERROR(IF(H27>0,H27,15),15)/15) *100,0) -> 93 | Q27: =T20D35746[[#This Row],[スコア⑤]]/T20D35746[[#This Row],[スコア③]] -> 1 | W27: =(T20D35746[[#This Row],[現金及び預金（億）]]-T20D35746[[#This Row],[負債（億）]])/T20D35746[[#This Row],[総資産]]*100 -> #DIV/0! | X27: 優良銘柄
A28: 6266 | B28: =IFERROR(_xll.RssMarket($A28,"銘柄名称"),"") -> タツモ | C28: =IFERROR(_xll.RssMarket($A28,"市場部略称"),"") -> 東Ｐ | D28: =IFERROR(_xll.RssMarket($A28,"現在値"),"") -> 2783 | E28: =IFERROR(_xll.RssMarket($A28,"前日比"),"") -> -30 | F28: =IFERROR(_xll.RssMarket($A28,"時価総額"),"") -> 41306 | G28: =T20D35746[[#This Row],[時価総額]]/T20D35746[[#This Row],[現在値]] -> 14.842257 | H28: =IFERROR(_xll.RssMarket($A28,"PER"),"") -> 11.5 | I28: =T20D35746[[#This Row],[現在値]] / IFERROR(IF(T20D35746[[#This Row],[PER]] > 0, T20D35746[[#This Row],[PER]], 15), 15) -> 242 | J28: =IFERROR(_xll.RssMarket($A28,"PBR"),"") -> 1.66 | K28: =T20D35746[[#This Row],[現在値]]/T20D35746[[#This Row],[PBR]] -> 1676.506 | L28: =T20D35746[[#This Row],[EPS]]/T20D35746[[#This Row],[BPS]]*100 -> 14.434783 | M28: =IFERROR(_xll.RssMarket($A28,"配当"),"") -> 34 | N28: =T20D35746[[#This Row],[配当]]/T20D35746[[#This Row],[現在値]] -> 0.012217032 | O28: =ROUND( ((IF(OR(R28="",R28<=0),20,R28)/20) *(L28/15)) /(IFERROR(IF(H28>0,H28,15),15)/15) *100,0) -> 87 | P28: =ROUND( ((IF(OR(R28="",R28<=0),20,R28)/20) *(L28/15) *((MIN(MAX(S28,0),50)/15)+1) *(1+MIN(MAX(IFERROR(IF(W28="",0,W28),0),-30),50)/200)) /(IFERROR(IF(H28>0,H28,15),15)/15) *100,0) -> 88 | Q28: =T20D35746[[#This Row],[スコア⑤]]/T20D35746[[#This Row],[スコア③]] -> 1.0114943 | R28: 13.89 | T28: 97.3 | U28: 87.9 | V28: 492 | W28: =(T20D35746[[#This Row],[現金及び預金（億）]]-T20D35746[[#This Row],[負債（億）]])/T20D35746[[#This Row],[総資産]]*100 -> 1.9105691
A29: 4980 | B29: =IFERROR(_xll.RssMarket($A29,"銘柄名称"),"") -> デクセリアルズ | C29: =IFERROR(_xll.RssMarket($A29,"市場部略称"),"") -> 東Ｐ | D29: =IFERROR(_xll.RssMarket($A29,"現在値"),"") -> 2236.5 | E29: =IFERROR(_xll.RssMarket($A29,"前日比"),"") -> -182.5 | F29: =IFERROR(_xll.RssMarket($A29,"時価総額"),"") -> 390809 | G29: =T20D35746[[#This Row],[時価総額]]/T20D35746[[#This Row],[現在値]] -> 174.74134 | H29: =IFERROR(_xll.RssMarket($A29,"PER"),"") -> 13.87 | I29: =T20D35746[[#This Row],[現在値]] / IFERROR(IF(T20D35746[[#This Row],[PER]] > 0, T20D35746[[#This Row],[PER]], 15), 15) -> 161.2473 | J29: =IFERROR(_xll.RssMarket($A29,"PBR"),"") -> 3.66 | K29: =T20D35746[[#This Row],[現在値]]/T20D35746[[#This Row],[PBR]] -> 611.06557 | L29: =T20D35746[[#This Row],[EPS]]/T20D35746[[#This Row],[BPS]]*100 -> 26.387888 | M29: =IFERROR(_xll.RssMarket($A29,"配当"),"") -> 58 | N29: =T20D35746[[#This Row],[配当]]/T20D35746[[#This Row],[現在値]] -> 0.025933378 | O29: =ROUND( ((IF(OR(R29="",R29<=0),20,R29)/20) *(L29/15)) /(IFERROR(IF(H29>0,H29,15),15)/15) *100,0) -> 257 | P29: =ROUND( ((IF(OR(R29="",R29<=0),20,R29)/20) *(L29/15) *((MIN(MAX(S29,0),50)/15)+1) *(1+MIN(MAX(IFERROR(IF(W29="",0,W29),0),-30),50)/200)) /(IFERROR(IF(H29>0,H29,15),15)/15) *100,0) -> 269 | Q29: =T20D35746[[#This Row],[スコア⑤]]/T20D35746[[#This Row],[スコア③]] -> 1.0466926 | R29: 27.05 | S29: -24.69 | T29: 350 | U29: 217 | V29: 1518 | W29: =(T20D35746[[#This Row],[現金及び預金（億）]]-T20D35746[[#This Row],[負債（億）]])/T20D35746[[#This Row],[総資産]]*100 -> 8.7615283 | X29: 半導体
A30: 3773 | B30: =IFERROR(_xll.RssMarket($A30,"銘柄名称"),"") -> アドバンスト・メディア | C30: =IFERROR(_xll.RssMarket($A30,"市場部略称"),"") -> 東Ｇ | D30: =IFERROR(_xll.RssMarket($A30,"現在値"),"") -> 1119 | E30: =IFERROR(_xll.RssMarket($A30,"前日比"),"") -> -19 | F30: =IFERROR(_xll.RssMarket($A30,"時価総額"),"") -> 20581 | G30: =T20D35746[[#This Row],[時価総額]]/T20D35746[[#This Row],[現在値]] -> 18.392315 | H30: =IFERROR(_xll.RssMarket($A30,"PER"),"") -> 15.24 | I30: =T20D35746[[#This Row],[現在値]] / IFERROR(IF(T20D35746[[#This Row],[PER]] > 0, T20D35746[[#This Row],[PER]], 15), 15) -> 73.425197 | J30: =IFERROR(_xll.RssMarket($A30,"PBR"),"") -> 1.35 | K30: =T20D35746[[#This Row],[現在値]]/T20D35746[[#This Row],[PBR]] -> 828.88889 | L30: =T20D35746[[#This Row],[EPS]]/T20D35746[[#This Row],[BPS]]*100 -> 8.8582677 | M30: =IFERROR(_xll.RssMarket($A30,"配当"),"") -> 30 | N30: =T20D35746[[#This Row],[配当]]/T20D35746[[#This Row],[現在値]] -> 0.026809651 | O30: =ROUND( ((IF(OR(R30="",R30<=0),20,R30)/20) *(L30/15)) /(IFERROR(IF(H30>0,H30,15),15)/15) *100,0) -> 65 | P30: =ROUND( ((IF(OR(R30="",R30<=0),20,R30)/20) *(L30/15) *((MIN(MAX(S30,0),50)/15)+1) *(1+MIN(MAX(IFERROR(IF(W30="",0,W30),0),-30),50)/200)) /(IFERROR(IF(H30>0,H30,15),15)/15) *100,0) -> 70 | Q30: =T20D35746[[#This Row],[スコア⑤]]/T20D35746[[#This Row],[スコア③]] -> 1.0769231 | R30: 22.5 | S30: -0.73 | T30: 41.1 | U30: 17.7 | V30: 160 | W30: =(T20D35746[[#This Row],[現金及び預金（億）]]-T20D35746[[#This Row],[負債（億）]])/T20D35746[[#This Row],[総資産]]*100 -> 14.625
A31: 3697 | B31: =IFERROR(_xll.RssMarket($A31,"銘柄名称"),"") -> ＳＨＩＦＴ | C31: =IFERROR(_xll.RssMarket($A31,"市場部略称"),"") -> 東Ｐ | D31: =IFERROR(_xll.RssMarket($A31,"現在値"),"") -> 623.6 | E31: =IFERROR(_xll.RssMarket($A31,"前日比"),"") -> -31.2 | F31: =IFERROR(_xll.RssMarket($A31,"時価総額"),"") -> 166813 | G31: =T20D35746[[#This Row],[時価総額]]/T20D35746[[#This Row],[現在値]] -> 267.5 | H31: =IFERROR(_xll.RssMarket($A31,"PER"),"") -> 14.46 | I31: =T20D35746[[#This Row],[現在値]] / IFERROR(IF(T20D35746[[#This Row],[PER]] > 0, T20D35746[[#This Row],[PER]], 15), 15) -> 43.125864 | J31: =IFERROR(_xll.RssMarket($A31,"PBR"),"") -> 4.04 | K31: =T20D35746[[#This Row],[現在値]]/T20D35746[[#This Row],[PBR]] -> 154.35644 | L31: =T20D35746[[#This Row],[EPS]]/T20D35746[[#This Row],[BPS]]*100 -> 27.939142 | M31: =IFERROR(_xll.RssMarket($A31,"配当"),"") -> 0 | N31: =T20D35746[[#This Row],[配当]]/T20D35746[[#This Row],[現在値]] -> 0 | O31: =ROUND( ((IF(OR(R31="",R31<=0),20,R31)/20) *(L31/15)) /(IFERROR(IF(H31>0,H31,15),15)/15) *100,0) -> 116 | P31: =ROUND( ((IF(OR(R31="",R31<=0),20,R31)/20) *(L31/15) *((MIN(MAX(S31,0),50)/15)+1) *(1+MIN(MAX(IFERROR(IF(W31="",0,W31),0),-30),50)/200)) /(IFERROR(IF(H31>0,H31,15),15)/15) *100,0) -> 125 | Q31: =T20D35746[[#This Row],[スコア⑤]]/T20D35746[[#This Row],[スコア③]] -> 1.0775862 | R31: 12 | T31: 236 | U31: 120 | V31: 770 | W31: =(T20D35746[[#This Row],[現金及び預金（億）]]-T20D35746[[#This Row],[負債（億）]])/T20D35746[[#This Row],[総資産]]*100 -> 15.064935
A32: 4516 | B32: =IFERROR(_xll.RssMarket($A32,"銘柄名称"),"") -> 日本新薬 | C32: =IFERROR(_xll.RssMarket($A32,"市場部略称"),"") -> 東Ｐ | D32: =IFERROR(_xll.RssMarket($A32,"現在値"),"") -> 4978 | E32: =IFERROR(_xll.RssMarket($A32,"前日比"),"") -> -26 | F32: =IFERROR(_xll.RssMarket($A32,"時価総額"),"") -> 349711 | G32: =T20D35746[[#This Row],[時価総額]]/T20D35746[[#This Row],[現在値]] -> 70.251306 | H32: =IFERROR(_xll.RssMarket($A32,"PER"),"") -> 12.75 | I32: =T20D35746[[#This Row],[現在値]] / IFERROR(IF(T20D35746[[#This Row],[PER]] > 0, T20D35746[[#This Row],[PER]], 15), 15) -> 390.43137 | J32: =IFERROR(_xll.RssMarket($A32,"PBR"),"") -> 1.29 | K32: =T20D35746[[#This Row],[現在値]]/T20D35746[[#This Row],[PBR]] -> 3858.9147 | L32: =T20D35746[[#This Row],[EPS]]/T20D35746[[#This Row],[BPS]]*100 -> 10.117647 | M32: =IFERROR(_xll.RssMarket($A32,"配当"),"") -> 124 | N32: =T20D35746[[#This Row],[配当]]/T20D35746[[#This Row],[現在値]] -> 0.024909602 | O32: =ROUND( ((IF(OR(R32="",R32<=0),20,R32)/20) *(L32/15)) /(IFERROR(IF(H32>0,H32,15),15)/15) *100,0) -> 72 | P32: =ROUND( ((IF(OR(R32="",R32<=0),20,R32)/20) *(L32/15) *((MIN(MAX(S32,0),50)/15)+1) *(1+MIN(MAX(IFERROR(IF(W32="",0,W32),0),-30),50)/200)) /(IFERROR(IF(H32>0,H32,15),15)/15) *100,0) -> 78 | Q32: =T20D35746[[#This Row],[スコア⑤]]/T20D35746[[#This Row],[スコア③]] -> 1.0833333 | R32: 18.07 | S32: -26.3 | T32: 552 | U32: 27.2 | V32: 2836 | W32: =(T20D35746[[#This Row],[現金及び預金（億）]]-T20D35746[[#This Row],[負債（億）]])/T20D35746[[#This Row],[総資産]]*100 -> 18.504937
A33: 8411 | B33: =IFERROR(_xll.RssMarket($A33,"銘柄名称"),"") -> みずほフィナンシャルＧ | C33: =IFERROR(_xll.RssMarket($A33,"市場部略称"),"") -> 東Ｐ | D33: =IFERROR(_xll.RssMarket($A33,"現在値"),"") -> 7681 | E33: =IFERROR(_xll.RssMarket($A33,"前日比"),"") -> -186 | F33: =IFERROR(_xll.RssMarket($A33,"時価総額"),"") -> 19124527 | G33: =T20D35746[[#This Row],[時価総額]]/T20D35746[[#This Row],[現在値]] -> 2489.8486 | H33: =IFERROR(_xll.RssMarket($A33,"PER"),"") -> 16.72 | I33: =T20D35746[[#This Row],[現在値]] / IFERROR(IF(T20D35746[[#This Row],[PER]] > 0, T20D35746[[#This Row],[PER]], 15), 15) -> 459.38995 | J33: =IFERROR(_xll.RssMarket($A33,"PBR"),"") -> 1.73 | K33: =T20D35746[[#This Row],[現在値]]/T20D35746[[#This Row],[PBR]] -> 4439.8844 | L33: =T20D35746[[#This Row],[EPS]]/T20D35746[[#This Row],[BPS]]*100 -> 10.34689 | M33: =IFERROR(_xll.RssMarket($A33,"配当"),"") -> 145 | N33: =T20D35746[[#This Row],[配当]]/T20D35746[[#This Row],[現在値]] -> 0.01887775 | O33: =ROUND( ((IF(OR(R33="",R33<=0),20,R33)/20) *(L33/15)) /(IFERROR(IF(H33>0,H33,15),15)/15) *100,0) -> 62 | P33: =ROUND( ((IF(OR(R33="",R33<=0),20,R33)/20) *(L33/15) *((MIN(MAX(S33,0),50)/15)+1) *(1+MIN(MAX(IFERROR(IF(W33="",0,W33),0),-30),50)/200)) /(IFERROR(IF(H33>0,H33,15),15)/15) *100,0) -> 68 | Q33: =T20D35746[[#This Row],[スコア⑤]]/T20D35746[[#This Row],[スコア③]] -> 1.0967742 | T33: 707000 | U33: 150000 | V33: 2830000 | W33: =(T20D35746[[#This Row],[現金及び預金（億）]]-T20D35746[[#This Row],[負債（億）]])/T20D35746[[#This Row],[総資産]]*100 -> 19.681979 | X33: 優良銘柄
A34: 8113 | B34: =IFERROR(_xll.RssMarket($A34,"銘柄名称"),"") -> ユニ・チヤ－ム | C34: =IFERROR(_xll.RssMarket($A34,"市場部略称"),"") -> 東Ｐ | D34: =IFERROR(_xll.RssMarket($A34,"現在値"),"") -> 1043.5 | E34: =IFERROR(_xll.RssMarket($A34,"前日比"),"") -> 78 | F34: =IFERROR(_xll.RssMarket($A34,"時価総額"),"") -> 1943521 | G34: =T20D35746[[#This Row],[時価総額]]/T20D35746[[#This Row],[現在値]] -> 1862.5022 | H34: =IFERROR(_xll.RssMarket($A34,"PER"),"") -> 27.82 | I34: =T20D35746[[#This Row],[現在値]] / IFERROR(IF(T20D35746[[#This Row],[PER]] > 0, T20D35746[[#This Row],[PER]], 15), 15) -> 37.508986 | J34: =IFERROR(_xll.RssMarket($A34,"PBR"),"") -> 2.39 | K34: =T20D35746[[#This Row],[現在値]]/T20D35746[[#This Row],[PBR]] -> 436.61088 | L34: =T20D35746[[#This Row],[EPS]]/T20D35746[[#This Row],[BPS]]*100 -> 8.5909418 | M34: =IFERROR(_xll.RssMarket($A34,"配当"),"") -> 18 | N34: =T20D35746[[#This Row],[配当]]/T20D35746[[#This Row],[現在値]] -> 0.017249641 | O34: =ROUND( ((IF(OR(R34="",R34<=0),20,R34)/20) *(L34/15)) /(IFERROR(IF(H34>0,H34,15),15)/15) *100,0) -> 19 | P34: =ROUND( ((IF(OR(R34="",R34<=0),20,R34)/20) *(L34/15) *((MIN(MAX(S34,0),50)/15)+1) *(1+MIN(MAX(IFERROR(IF(W34="",0,W34),0),-30),50)/200)) /(IFERROR(IF(H34>0,H34,15),15)/15) *100,0) -> 21 | Q34: =T20D35746[[#This Row],[スコア⑤]]/T20D35746[[#This Row],[スコア③]] -> 1.1052632 | R34: 12.32 | T34: 2611 | U34: 269 | V34: 12400 | W34: =(T20D35746[[#This Row],[現金及び預金（億）]]-T20D35746[[#This Row],[負債（億）]])/T20D35746[[#This Row],[総資産]]*100 -> 18.887097
A35: 9247 | B35: =IFERROR(_xll.RssMarket($A35,"銘柄名称"),"") -> ＴＲＥホールディングス | C35: =IFERROR(_xll.RssMarket($A35,"市場部略称"),"") -> 東Ｐ | D35: =IFERROR(_xll.RssMarket($A35,"現在値"),"") -> 1709 | E35: =IFERROR(_xll.RssMarket($A35,"前日比"),"") -> -72 | F35: =IFERROR(_xll.RssMarket($A35,"時価総額"),"") -> 89911 | G35: =T20D35746[[#This Row],[時価総額]]/T20D35746[[#This Row],[現在値]] -> 52.610298 | H35: =IFERROR(_xll.RssMarket($A35,"PER"),"") -> 6.5 | I35: =T20D35746[[#This Row],[現在値]] / IFERROR(IF(T20D35746[[#This Row],[PER]] > 0, T20D35746[[#This Row],[PER]], 15), 15) -> 262.92308 | J35: =IFERROR(_xll.RssMarket($A35,"PBR"),"") -> 1.03 | K35: =T20D35746[[#This Row],[現在値]]/T20D35746[[#This Row],[PBR]] -> 1659.2233 | L35: =T20D35746[[#This Row],[EPS]]/T20D35746[[#This Row],[BPS]]*100 -> 15.846154 | M35: =IFERROR(_xll.RssMarket($A35,"配当"),"") -> 50 | N35: =T20D35746[[#This Row],[配当]]/T20D35746[[#This Row],[現在値]] -> 0.029256875 | O35: =ROUND( ((IF(OR(R35="",R35<=0),20,R35)/20) *(L35/15)) /(IFERROR(IF(H35>0,H35,15),15)/15) *100,0) -> 191 | P35: =ROUND( ((IF(OR(R35="",R35<=0),20,R35)/20) *(L35/15) *((MIN(MAX(S35,0),50)/15)+1) *(1+MIN(MAX(IFERROR(IF(W35="",0,W35),0),-30),50)/200)) /(IFERROR(IF(H35>0,H35,15),15)/15) *100,0) -> 221 | Q35: =T20D35746[[#This Row],[スコア⑤]]/T20D35746[[#This Row],[スコア③]] -> 1.1570681 | R35: 15.66 | S35: 4.21 | T35: 299 | U35: 607 | V35: 1620 | W35: =(T20D35746[[#This Row],[現金及び預金（億）]]-T20D35746[[#This Row],[負債（億）]])/T20D35746[[#This Row],[総資産]]*100 -> -19.012346
A36: 9432 | B36: =IFERROR(_xll.RssMarket($A36,"銘柄名称"),"") -> ＮＴＴ | C36: =IFERROR(_xll.RssMarket($A36,"市場部略称"),"") -> 東Ｐ | D36: =IFERROR(_xll.RssMarket($A36,"現在値"),"") -> 154.6 | E36: =IFERROR(_xll.RssMarket($A36,"前日比"),"") -> 1.2 | F36: =IFERROR(_xll.RssMarket($A36,"時価総額"),"") -> 13999078 | G36: =T20D35746[[#This Row],[時価総額]]/T20D35746[[#This Row],[現在値]] -> 90550.31 | H36: =IFERROR(_xll.RssMarket($A36,"PER"),"") -> 13.1 | I36: =T20D35746[[#This Row],[現在値]] / IFERROR(IF(T20D35746[[#This Row],[PER]] > 0, T20D35746[[#This Row],[PER]], 15), 15) -> 11.801527 | J36: =IFERROR(_xll.RssMarket($A36,"PBR"),"") -> 1.38 | K36: =T20D35746[[#This Row],[現在値]]/T20D35746[[#This Row],[PBR]] -> 112.02899 | L36: =T20D35746[[#This Row],[EPS]]/T20D35746[[#This Row],[BPS]]*100 -> 10.534351 | M36: =IFERROR(_xll.RssMarket($A36,"配当"),"") -> 5.3 | N36: =T20D35746[[#This Row],[配当]]/T20D35746[[#This Row],[現在値]] -> 0.034282018 | O36: =ROUND( ((IF(OR(R36="",R36<=0),20,R36)/20) *(L36/15)) /(IFERROR(IF(H36>0,H36,15),15)/15) *100,0) -> 50 | P36: =ROUND( ((IF(OR(R36="",R36<=0),20,R36)/20) *(L36/15) *((MIN(MAX(S36,0),50)/15)+1) *(1+MIN(MAX(IFERROR(IF(W36="",0,W36),0),-30),50)/200)) /(IFERROR(IF(H36>0,H36,15),15)/15) *100,0) -> 58 | Q36: =T20D35746[[#This Row],[スコア⑤]]/T20D35746[[#This Row],[スコア③]] -> 1.16 | R36: 12.47 | S36: 5.35 | T36: 10000 | U36: 112000 | V36: 301000 | W36: =(T20D35746[[#This Row],[現金及び預金（億）]]-T20D35746[[#This Row],[負債（億）]])/T20D35746[[#This Row],[総資産]]*100 -> -33.887043 | X36: 優良銘柄
A37: 6777 | B37: =IFERROR(_xll.RssMarket($A37,"銘柄名称"),"") -> ＳＡＮＴＥＣＨＯＬＤＩＮＧＳ | C37: =IFERROR(_xll.RssMarket($A37,"市場部略称"),"") -> 東Ｓ | D37: =IFERROR(_xll.RssMarket($A37,"現在値"),"") -> 17670 | E37: =IFERROR(_xll.RssMarket($A37,"前日比"),"") -> 250 | F37: =IFERROR(_xll.RssMarket($A37,"時価総額"),"") -> 211352 | G37: =T20D35746[[#This Row],[時価総額]]/T20D35746[[#This Row],[現在値]] -> 11.961064 | H37: =IFERROR(_xll.RssMarket($A37,"PER"),"") -> 37.78 | I37: =T20D35746[[#This Row],[現在値]] / IFERROR(IF(T20D35746[[#This Row],[PER]] > 0, T20D35746[[#This Row],[PER]], 15), 15) -> 467.70778 | J37: =IFERROR(_xll.RssMarket($A37,"PBR"),"") -> 9.03 | K37: =T20D35746[[#This Row],[現在値]]/T20D35746[[#This Row],[PBR]] -> 1956.8106 | L37: =T20D35746[[#This Row],[EPS]]/T20D35746[[#This Row],[BPS]]*100 -> 23.901535 | M37: =IFERROR(_xll.RssMarket($A37,"配当"),"") -> 150 | N37: =T20D35746[[#This Row],[配当]]/T20D35746[[#This Row],[現在値]] -> 0.0084889643 | O37: =ROUND( ((IF(OR(R37="",R37<=0),20,R37)/20) *(L37/15)) /(IFERROR(IF(H37>0,H37,15),15)/15) *100,0) -> 90 | P37: =ROUND( ((IF(OR(R37="",R37<=0),20,R37)/20) *(L37/15) *((MIN(MAX(S37,0),50)/15)+1) *(1+MIN(MAX(IFERROR(IF(W37="",0,W37),0),-30),50)/200)) /(IFERROR(IF(H37>0,H37,15),15)/15) *100,0) -> 105 | Q37: =T20D35746[[#This Row],[スコア⑤]]/T20D35746[[#This Row],[スコア③]] -> 1.1666667 | R37: 28.46 | T37: 126 | U37: 27.2 | V37: 295 | W37: =(T20D35746[[#This Row],[現金及び預金（億）]]-T20D35746[[#This Row],[負債（億）]])/T20D35746[[#This Row],[総資産]]*100 -> 33.491525
A38: 6088 | B38: =IFERROR(_xll.RssMarket($A38,"銘柄名称"),"") -> シグマクシス・ホールディンク | C38: =IFERROR(_xll.RssMarket($A38,"市場部略称"),"") -> 東Ｐ | D38: =IFERROR(_xll.RssMarket($A38,"現在値"),"") -> 658 | E38: =IFERROR(_xll.RssMarket($A38,"前日比"),"") -> 3 | F38: =IFERROR(_xll.RssMarket($A38,"時価総額"),"") -> 56588 | G38: =T20D35746[[#This Row],[時価総額]]/T20D35746[[#This Row],[現在値]] -> 86 | H38: =IFERROR(_xll.RssMarket($A38,"PER"),"") -> 12.32 | I38: =T20D35746[[#This Row],[現在値]] / IFERROR(IF(T20D35746[[#This Row],[PER]] > 0, T20D35746[[#This Row],[PER]], 15), 15) -> 53.409091 | J38: =IFERROR(_xll.RssMarket($A38,"PBR"),"") -> 3.8 | K38: =T20D35746[[#This Row],[現在値]]/T20D35746[[#This Row],[PBR]] -> 173.15789 | L38: =T20D35746[[#This Row],[EPS]]/T20D35746[[#This Row],[BPS]]*100 -> 30.844156 | M38: =IFERROR(_xll.RssMarket($A38,"配当"),"") -> 26 | N38: =T20D35746[[#This Row],[配当]]/T20D35746[[#This Row],[現在値]] -> 0.039513678 | O38: =ROUND( ((IF(OR(R38="",R38<=0),20,R38)/20) *(L38/15)) /(IFERROR(IF(H38>0,H38,15),15)/15) *100,0) -> 290 | P38: =ROUND( ((IF(OR(R38="",R38<=0),20,R38)/20) *(L38/15) *((MIN(MAX(S38,0),50)/15)+1) *(1+MIN(MAX(IFERROR(IF(W38="",0,W38),0),-30),50)/200)) /(IFERROR(IF(H38>0,H38,15),15)/15) *100,0) -> 341 | Q38: =T20D35746[[#This Row],[スコア⑤]]/T20D35746[[#This Row],[スコア③]] -> 1.1758621 | R38: 23.17 | T38: 69.5 | U38: 0 | V38: 197 | W38: =(T20D35746[[#This Row],[現金及び預金（億）]]-T20D35746[[#This Row],[負債（億）]])/T20D35746[[#This Row],[総資産]]*100 -> 35.279188
A39: 5533 | B39: =IFERROR(_xll.RssMarket($A39,"銘柄名称"),"") -> エリッツホールディングス | C39: =IFERROR(_xll.RssMarket($A39,"市場部略称"),"") -> 東Ｓ | D39: =IFERROR(_xll.RssMarket($A39,"現在値"),"") -> 1997 | E39: =IFERROR(_xll.RssMarket($A39,"前日比"),"") -> 19 | F39: =IFERROR(_xll.RssMarket($A39,"時価総額"),"") -> 7010 | G39: =T20D35746[[#This Row],[時価総額]]/T20D35746[[#This Row],[現在値]] -> 3.5102654 | H39: =IFERROR(_xll.RssMarket($A39,"PER"),"") -> 9.73 | I39: =T20D35746[[#This Row],[現在値]] / IFERROR(IF(T20D35746[[#This Row],[PER]] > 0, T20D35746[[#This Row],[PER]], 15), 15) -> 205.24152 | J39: =IFERROR(_xll.RssMarket($A39,"PBR"),"") -> 1.3 | K39: =T20D35746[[#This Row],[現在値]]/T20D35746[[#This Row],[PBR]] -> 1536.1538 | L39: =T20D35746[[#This Row],[EPS]]/T20D35746[[#This Row],[BPS]]*100 -> 13.36074 | M39: =IFERROR(_xll.RssMarket($A39,"配当"),"") -> 70 | N39: =T20D35746[[#This Row],[配当]]/T20D35746[[#This Row],[現在値]] -> 0.035052579 | O39: =ROUND( ((IF(OR(R39="",R39<=0),20,R39)/20) *(L39/15)) /(IFERROR(IF(H39>0,H39,15),15)/15) *100,0) -> 112 | P39: =ROUND( ((IF(OR(R39="",R39<=0),20,R39)/20) *(L39/15) *((MIN(MAX(S39,0),50)/15)+1) *(1+MIN(MAX(IFERROR(IF(W39="",0,W39),0),-30),50)/200)) /(IFERROR(IF(H39>0,H39,15),15)/15) *100,0) -> 135 | Q39: =T20D35746[[#This Row],[スコア⑤]]/T20D35746[[#This Row],[スコア③]] -> 1.2053571 | R39: 16.33 | S39: 2 | T39: 45 | U39: 33.69 | V39: 95.5 | W39: =(T20D35746[[#This Row],[現金及び預金（億）]]-T20D35746[[#This Row],[負債（億）]])/T20D35746[[#This Row],[総資産]]*100 -> 11.842932
A40: 7378 | B40: =IFERROR(_xll.RssMarket($A40,"銘柄名称"),"") -> アシロ | C40: =IFERROR(_xll.RssMarket($A40,"市場部略称"),"") -> 東Ｇ | D40: =IFERROR(_xll.RssMarket($A40,"現在値"),"") -> 1763 | E40: =IFERROR(_xll.RssMarket($A40,"前日比"),"") -> -50 | F40: =IFERROR(_xll.RssMarket($A40,"時価総額"),"") -> 13011 | G40: =T20D35746[[#This Row],[時価総額]]/T20D35746[[#This Row],[現在値]] -> 7.380034 | H40: =IFERROR(_xll.RssMarket($A40,"PER"),"") -> 12.73 | I40: =T20D35746[[#This Row],[現在値]] / IFERROR(IF(T20D35746[[#This Row],[PER]] > 0, T20D35746[[#This Row],[PER]], 15), 15) -> 138.49175 | J40: =IFERROR(_xll.RssMarket($A40,"PBR"),"") -> 4.1 | K40: =T20D35746[[#This Row],[現在値]]/T20D35746[[#This Row],[PBR]] -> 430 | L40: =T20D35746[[#This Row],[EPS]]/T20D35746[[#This Row],[BPS]]*100 -> 32.207384 | M40: =IFERROR(_xll.RssMarket($A40,"配当"),"") -> 40.33 | N40: =T20D35746[[#This Row],[配当]]/T20D35746[[#This Row],[現在値]] -> 0.02287578 | O40: =ROUND( ((IF(OR(R40="",R40<=0),20,R40)/20) *(L40/15)) /(IFERROR(IF(H40>0,H40,15),15)/15) *100,0) -> 271 | P40: =ROUND( ((IF(OR(R40="",R40<=0),20,R40)/20) *(L40/15) *((MIN(MAX(S40,0),50)/15)+1) *(1+MIN(MAX(IFERROR(IF(W40="",0,W40),0),-30),50)/200)) /(IFERROR(IF(H40>0,H40,15),15)/15) *100,0) -> 328 | Q40: =T20D35746[[#This Row],[スコア⑤]]/T20D35746[[#This Row],[スコア③]] -> 1.2103321 | R40: 21.43 | S40: 0 | T40: 24.7 | U40: 4.25 | V40: 48.3 | W40: =(T20D35746[[#This Row],[現金及び預金（億）]]-T20D35746[[#This Row],[負債（億）]])/T20D35746[[#This Row],[総資産]]*100 -> 42.339545 | X40: 業務内容成長継続疑問。デイ監視にはいれない
A41: 4587 | B41: =IFERROR(_xll.RssMarket($A41,"銘柄名称"),"") -> ペプチドリーム | C41: =IFERROR(_xll.RssMarket($A41,"市場部略称"),"") -> 東Ｐ | D41: =IFERROR(_xll.RssMarket($A41,"現在値"),"") -> 1518.5 | E41: =IFERROR(_xll.RssMarket($A41,"前日比"),"") -> -21 | F41: =IFERROR(_xll.RssMarket($A41,"時価総額"),"") -> 197420 | G41: =T20D35746[[#This Row],[時価総額]]/T20D35746[[#This Row],[現在値]] -> 130.00988 | H41: =IFERROR(_xll.RssMarket($A41,"PER"),"") -> 0 | I41: =T20D35746[[#This Row],[現在値]] / IFERROR(IF(T20D35746[[#This Row],[PER]] > 0, T20D35746[[#This Row],[PER]], 15), 15) -> 101.23333 | J41: =IFERROR(_xll.RssMarket($A41,"PBR"),"") -> 3.65 | K41: =T20D35746[[#This Row],[現在値]]/T20D35746[[#This Row],[PBR]] -> 416.0274 | L41: =T20D35746[[#This Row],[EPS]]/T20D35746[[#This Row],[BPS]]*100 -> 24.333333 | M41: =IFERROR(_xll.RssMarket($A41,"配当"),"") -> 0 | N41: =T20D35746[[#This Row],[配当]]/T20D35746[[#This Row],[現在値]] -> 0 | O41: =ROUND( ((IF(OR(R41="",R41<=0),20,R41)/20) *(L41/15)) /(IFERROR(IF(H41>0,H41,15),15)/15) *100,0) -> 358 | P41: =ROUND( ((IF(OR(R41="",R41<=0),20,R41)/20) *(L41/15) *((MIN(MAX(S41,0),50)/15)+1) *(1+MIN(MAX(IFERROR(IF(W41="",0,W41),0),-30),50)/200)) /(IFERROR(IF(H41>0,H41,15),15)/15) *100,0) -> 436 | Q41: =T20D35746[[#This Row],[スコア⑤]]/T20D35746[[#This Row],[スコア③]] -> 1.2178771 | R41: 44.08 | S41: 0.87 | T41: 481 | U41: 196 | V41: 928 | W41: =(T20D35746[[#This Row],[現金及び預金（億）]]-T20D35746[[#This Row],[負債（億）]])/T20D35746[[#This Row],[総資産]]*100 -> 30.711207
A42: 8801 | B42: =IFERROR(_xll.RssMarket($A42,"銘柄名称"),"") -> 三井不動産 | C42: =IFERROR(_xll.RssMarket($A42,"市場部略称"),"") -> 東Ｐ | D42: =IFERROR(_xll.RssMarket($A42,"現在値"),"") -> 2081.5 | E42: =IFERROR(_xll.RssMarket($A42,"前日比"),"") -> -66 | F42: =IFERROR(_xll.RssMarket($A42,"時価総額"),"") -> 5791127 | G42: =T20D35746[[#This Row],[時価総額]]/T20D35746[[#This Row],[現在値]] -> 2782.1893 | H42: =IFERROR(_xll.RssMarket($A42,"PER"),"") -> 21.06 | I42: =T20D35746[[#This Row],[現在値]] / IFERROR(IF(T20D35746[[#This Row],[PER]] > 0, T20D35746[[#This Row],[PER]], 15), 15) -> 98.836657 | J42: =IFERROR(_xll.RssMarket($A42,"PBR"),"") -> 1.78 | K42: =T20D35746[[#This Row],[現在値]]/T20D35746[[#This Row],[PBR]] -> 1169.382 | L42: =T20D35746[[#This Row],[EPS]]/T20D35746[[#This Row],[BPS]]*100 -> 8.4520418 | M42: =IFERROR(_xll.RssMarket($A42,"配当"),"") -> 34 | N42: =T20D35746[[#This Row],[配当]]/T20D35746[[#This Row],[現在値]] -> 0.016334374 | O42: =ROUND( ((IF(OR(R42="",R42<=0),20,R42)/20) *(L42/15)) /(IFERROR(IF(H42>0,H42,15),15)/15) *100,0) -> 40 | P42: =ROUND( ((IF(OR(R42="",R42<=0),20,R42)/20) *(L42/15) *((MIN(MAX(S42,0),50)/15)+1) *(1+MIN(MAX(IFERROR(IF(W42="",0,W42),0),-30),50)/200)) /(IFERROR(IF(H42>0,H42,15),15)/15) *100,0) -> 49 | Q42: =T20D35746[[#This Row],[スコア⑤]]/T20D35746[[#This Row],[スコア③]] -> 1.225 | S42: 6.74 | T42: 1633 | U42: 39500 | V42: 98600 | W42: =(T20D35746[[#This Row],[現金及び預金（億）]]-T20D35746[[#This Row],[負債（億）]])/T20D35746[[#This Row],[総資産]]*100 -> -38.404665 | X42: 優良銘柄
A43: 7317 | B43: =IFERROR(_xll.RssMarket($A43,"銘柄名称"),"") -> 松屋アールアンドディ | C43: =IFERROR(_xll.RssMarket($A43,"市場部略称"),"") -> 東Ｇ | D43: =IFERROR(_xll.RssMarket($A43,"現在値"),"") -> 1090 | E43: =IFERROR(_xll.RssMarket($A43,"前日比"),"") -> -1 | F43: =IFERROR(_xll.RssMarket($A43,"時価総額"),"") -> 23336 | G43: =T20D35746[[#This Row],[時価総額]]/T20D35746[[#This Row],[現在値]] -> 21.409174 | H43: =IFERROR(_xll.RssMarket($A43,"PER"),"") -> 14.57 | I43: =T20D35746[[#This Row],[現在値]] / IFERROR(IF(T20D35746[[#This Row],[PER]] > 0, T20D35746[[#This Row],[PER]], 15), 15) -> 74.811256 | J43: =IFERROR(_xll.RssMarket($A43,"PBR"),"") -> 3.37 | K43: =T20D35746[[#This Row],[現在値]]/T20D35746[[#This Row],[PBR]] -> 323.44214 | L43: =T20D35746[[#This Row],[EPS]]/T20D35746[[#This Row],[BPS]]*100 -> 23.129719 | M43: =IFERROR(_xll.RssMarket($A43,"配当"),"") -> 0 | N43: =T20D35746[[#This Row],[配当]]/T20D35746[[#This Row],[現在値]] -> 0 | O43: =ROUND( ((IF(OR(R43="",R43<=0),20,R43)/20) *(L43/15)) /(IFERROR(IF(H43>0,H43,15),15)/15) *100,0) -> 165 | P43: =ROUND( ((IF(OR(R43="",R43<=0),20,R43)/20) *(L43/15) *((MIN(MAX(S43,0),50)/15)+1) *(1+MIN(MAX(IFERROR(IF(W43="",0,W43),0),-30),50)/200)) /(IFERROR(IF(H43>0,H43,15),15)/15) *100,0) -> 204 | Q43: =T20D35746[[#This Row],[スコア⑤]]/T20D35746[[#This Row],[スコア③]] -> 1.2363636 | R43: 20.83 | S43: 2.22 | T43: 39.8 | U43: 23.1 | V43: 109 | W43: =(T20D35746[[#This Row],[現金及び預金（億）]]-T20D35746[[#This Row],[負債（億）]])/T20D35746[[#This Row],[総資産]]*100 -> 15.321101
A44: 6194 | B44: =IFERROR(_xll.RssMarket($A44,"銘柄名称"),"") -> アトラエ | C44: =IFERROR(_xll.RssMarket($A44,"市場部略称"),"") -> 東Ｐ | D44: =IFERROR(_xll.RssMarket($A44,"現在値"),"") -> 718 | E44: =IFERROR(_xll.RssMarket($A44,"前日比"),"") -> 11 | F44: =IFERROR(_xll.RssMarket($A44,"時価総額"),"") -> 16525 | G44: =T20D35746[[#This Row],[時価総額]]/T20D35746[[#This Row],[現在値]] -> 23.01532 | H44: =IFERROR(_xll.RssMarket($A44,"PER"),"") -> 21.05 | I44: =T20D35746[[#This Row],[現在値]] / IFERROR(IF(T20D35746[[#This Row],[PER]] > 0, T20D35746[[#This Row],[PER]], 15), 15) -> 34.109264 | J44: =IFERROR(_xll.RssMarket($A44,"PBR"),"") -> 3.76 | K44: =T20D35746[[#This Row],[現在値]]/T20D35746[[#This Row],[PBR]] -> 190.95745 | L44: =T20D35746[[#This Row],[EPS]]/T20D35746[[#This Row],[BPS]]*100 -> 17.862233 | M44: =IFERROR(_xll.RssMarket($A44,"配当"),"") -> 33 | N44: =T20D35746[[#This Row],[配当]]/T20D35746[[#This Row],[現在値]] -> 0.045961003 | O44: =ROUND( ((IF(OR(R44="",R44<=0),20,R44)/20) *(L44/15)) /(IFERROR(IF(H44>0,H44,15),15)/15) *100,0) -> 73 | P44: =ROUND( ((IF(OR(R44="",R44<=0),20,R44)/20) *(L44/15) *((MIN(MAX(S44,0),50)/15)+1) *(1+MIN(MAX(IFERROR(IF(W44="",0,W44),0),-30),50)/200)) /(IFERROR(IF(H44>0,H44,15),15)/15) *100,0) -> 91 | Q44: =T20D35746[[#This Row],[スコア⑤]]/T20D35746[[#This Row],[スコア③]] -> 1.2465753 | R44: 17.11 | T44: 43.6 | U44: 5 | V44: 72.2 | W44: =(T20D35746[[#This Row],[現金及び預金（億）]]-T20D35746[[#This Row],[負債（億）]])/T20D35746[[#This Row],[総資産]]*100 -> 53.462604
A45: 6613 | B45: =IFERROR(_xll.RssMarket($A45,"銘柄名称"),"") -> ＱＤレーザ | C45: =IFERROR(_xll.RssMarket($A45,"市場部略称"),"") -> 東Ｇ | D45: =IFERROR(_xll.RssMarket($A45,"現在値"),"") -> 615 | E45: =IFERROR(_xll.RssMarket($A45,"前日比"),"") -> -20 | F45: =IFERROR(_xll.RssMarket($A45,"時価総額"),"") -> 25685 | G45: =T20D35746[[#This Row],[時価総額]]/T20D35746[[#This Row],[現在値]] -> 41.764228 | H45: =IFERROR(_xll.RssMarket($A45,"PER"),"") -> 0 | I45: =T20D35746[[#This Row],[現在値]] / IFERROR(IF(T20D35746[[#This Row],[PER]] > 0, T20D35746[[#This Row],[PER]], 15), 15) -> 41 | J45: =IFERROR(_xll.RssMarket($A45,"PBR"),"") -> 5.08 | K45: =T20D35746[[#This Row],[現在値]]/T20D35746[[#This Row],[PBR]] -> 121.06299 | L45: =T20D35746[[#This Row],[EPS]]/T20D35746[[#This Row],[BPS]]*100 -> 33.866667 | M45: =IFERROR(_xll.RssMarket($A45,"配当"),"") -> 0 | N45: =T20D35746[[#This Row],[配当]]/T20D35746[[#This Row],[現在値]] -> 0 | O45: =ROUND( ((IF(OR(R45="",R45<=0),20,R45)/20) *(L45/15)) /(IFERROR(IF(H45>0,H45,15),15)/15) *100,0) -> 226 | P45: =ROUND( ((IF(OR(R45="",R45<=0),20,R45)/20) *(L45/15) *((MIN(MAX(S45,0),50)/15)+1) *(1+MIN(MAX(IFERROR(IF(W45="",0,W45),0),-30),50)/200)) /(IFERROR(IF(H45>0,H45,15),15)/15) *100,0) -> 282 | Q45: =T20D35746[[#This Row],[スコア⑤]]/T20D35746[[#This Row],[スコア③]] -> 1.2477876 | T45: 37.5 | V45: 55.1 | W45: =(T20D35746[[#This Row],[現金及び預金（億）]]-T20D35746[[#This Row],[負債（億）]])/T20D35746[[#This Row],[総資産]]*100 -> 68.058076
A46: 202A | B46: =IFERROR(_xll.RssMarket($A46,"銘柄名称"),"") -> 豆蔵 | C46: =IFERROR(_xll.RssMarket($A46,"市場部略称"),"") -> 東Ｇ | D46: =IFERROR(_xll.RssMarket($A46,"現在値"),"") -> 3540 | E46: =IFERROR(_xll.RssMarket($A46,"前日比"),"") -> -5 | F46: =IFERROR(_xll.RssMarket($A46,"時価総額"),"") -> 56817 | G46: =T20D35746[[#This Row],[時価総額]]/T20D35746[[#This Row],[現在値]] -> 16.05 | H46: =IFERROR(_xll.RssMarket($A46,"PER"),"") -> 17.75 | I46: =T20D35746[[#This Row],[現在値]] / IFERROR(IF(T20D35746[[#This Row],[PER]] > 0, T20D35746[[#This Row],[PER]], 15), 15) -> 199.43662 | J46: =IFERROR(_xll.RssMarket($A46,"PBR"),"") -> 17.57 | K46: =T20D35746[[#This Row],[現在値]]/T20D35746[[#This Row],[PBR]] -> 201.4798 | L46: =T20D35746[[#This Row],[EPS]]/T20D35746[[#This Row],[BPS]]*100 -> 98.985915 | M46: =IFERROR(_xll.RssMarket($A46,"配当"),"") -> 61 | N46: =T20D35746[[#This Row],[配当]]/T20D35746[[#This Row],[現在値]] -> 0.017231638 | O46: =ROUND( ((IF(OR(R46="",R46<=0),20,R46)/20) *(L46/15)) /(IFERROR(IF(H46>0,H46,15),15)/15) *100,0) -> 547 | P46: =ROUND( ((IF(OR(R46="",R46<=0),20,R46)/20) *(L46/15) *((MIN(MAX(S46,0),50)/15)+1) *(1+MIN(MAX(IFERROR(IF(W46="",0,W46),0),-30),50)/200)) /(IFERROR(IF(H46>0,H46,15),15)/15) *100,0) -> 685 | Q46: =T20D35746[[#This Row],[スコア⑤]]/T20D35746[[#This Row],[スコア③]] -> 1.2522852 | R46: 19.62 | S46: 0.86 | T46: 18.3 | U46: 1 | V46: 47.1 | W46: =(T20D35746[[#This Row],[現金及び預金（億）]]-T20D35746[[#This Row],[負債（億）]])/T20D35746[[#This Row],[総資産]]*100 -> 36.730361
A47: 368A | B47: =IFERROR(_xll.RssMarket($A47,"銘柄名称"),"") -> 北里コーポレーション | C47: =IFERROR(_xll.RssMarket($A47,"市場部略称"),"") -> 東Ｐ | D47: =IFERROR(_xll.RssMarket($A47,"現在値"),"") -> 1526 | E47: =IFERROR(_xll.RssMarket($A47,"前日比"),"") -> -71 | F47: =IFERROR(_xll.RssMarket($A47,"時価総額"),"") -> 61040 | G47: =T20D35746[[#This Row],[時価総額]]/T20D35746[[#This Row],[現在値]] -> 40 | H47: =IFERROR(_xll.RssMarket($A47,"PER"),"") -> 16.26 | I47: =T20D35746[[#This Row],[現在値]] / IFERROR(IF(T20D35746[[#This Row],[PER]] > 0, T20D35746[[#This Row],[PER]], 15), 15) -> 93.849938 | J47: =IFERROR(_xll.RssMarket($A47,"PBR"),"") -> 3.31 | K47: =T20D35746[[#This Row],[現在値]]/T20D35746[[#This Row],[PBR]] -> 461.02719 | L47: =T20D35746[[#This Row],[EPS]]/T20D35746[[#This Row],[BPS]]*100 -> 20.356704 | M47: =IFERROR(_xll.RssMarket($A47,"配当"),"") -> 41 | N47: =T20D35746[[#This Row],[配当]]/T20D35746[[#This Row],[現在値]] -> 0.026867628 | O47: =ROUND( ((IF(OR(R47="",R47<=0),20,R47)/20) *(L47/15)) /(IFERROR(IF(H47>0,H47,15),15)/15) *100,0) -> 317 | P47: =ROUND( ((IF(OR(R47="",R47<=0),20,R47)/20) *(L47/15) *((MIN(MAX(S47,0),50)/15)+1) *(1+MIN(MAX(IFERROR(IF(W47="",0,W47),0),-30),50)/200)) /(IFERROR(IF(H47>0,H47,15),15)/15) *100,0) -> 397 | Q47: =T20D35746[[#This Row],[スコア⑤]]/T20D35746[[#This Row],[スコア③]] -> 1.2523659 | R47: 50.69 | T47: 115 | V47: 197 | W47: =(T20D35746[[#This Row],[現金及び預金（億）]]-T20D35746[[#This Row],[負債（億）]])/T20D35746[[#This Row],[総資産]]*100 -> 58.375635
A48: 7374 | B48: =IFERROR(_xll.RssMarket($A48,"銘柄名称"),"") -> コンフィデンス・インターワーク | C48: =IFERROR(_xll.RssMarket($A48,"市場部略称"),"") -> 東Ｇ | D48: =IFERROR(_xll.RssMarket($A48,"現在値"),"") -> 1699 | E48: =IFERROR(_xll.RssMarket($A48,"前日比"),"") -> -23 | F48: =IFERROR(_xll.RssMarket($A48,"時価総額"),"") -> 11405 | G48: =T20D35746[[#This Row],[時価総額]]/T20D35746[[#This Row],[現在値]] -> 6.7127722 | H48: =IFERROR(_xll.RssMarket($A48,"PER"),"") -> 11.29 | I48: =T20D35746[[#This Row],[現在値]] / IFERROR(IF(T20D35746[[#This Row],[PER]] > 0, T20D35746[[#This Row],[PER]], 15), 15) -> 150.48716 | J48: =IFERROR(_xll.RssMarket($A48,"PBR"),"") -> 1.74 | K48: =T20D35746[[#This Row],[現在値]]/T20D35746[[#This Row],[PBR]] -> 976.43678 | L48: =T20D35746[[#This Row],[EPS]]/T20D35746[[#This Row],[BPS]]*100 -> 15.411869 | M48: =IFERROR(_xll.RssMarket($A48,"配当"),"") -> 75 | N48: =T20D35746[[#This Row],[配当]]/T20D35746[[#This Row],[現在値]] -> 0.044143614 | O48: =ROUND( ((IF(OR(R48="",R48<=0),20,R48)/20) *(L48/15)) /(IFERROR(IF(H48>0,H48,15),15)/15) *100,0) -> 99 | P48: =ROUND( ((IF(OR(R48="",R48<=0),20,R48)/20) *(L48/15) *((MIN(MAX(S48,0),50)/15)+1) *(1+MIN(MAX(IFERROR(IF(W48="",0,W48),0),-30),50)/200)) /(IFERROR(IF(H48>0,H48,15),15)/15) *100,0) -> 124 | Q48: =T20D35746[[#This Row],[スコア⑤]]/T20D35746[[#This Row],[スコア③]] -> 1.2525253 | R48: 14.56 | T48: 39.9 | U48: 0.56 | V48: 66.1 | W48: =(T20D35746[[#This Row],[現金及び預金（億）]]-T20D35746[[#This Row],[負債（億）]])/T20D35746[[#This Row],[総資産]]*100 -> 59.515885
A49: 4833 | B49: =IFERROR(_xll.RssMarket($A49,"銘柄名称"),"") -> ＤＥＦＣＯＮＳＵＬＴＩＮＧ | C49: =IFERROR(_xll.RssMarket($A49,"市場部略称"),"") -> 東Ｇ | D49: =IFERROR(_xll.RssMarket($A49,"現在値"),"") -> 73 | E49: =IFERROR(_xll.RssMarket($A49,"前日比"),"") -> -2 | F49: =IFERROR(_xll.RssMarket($A49,"時価総額"),"") -> 4997 | G49: =T20D35746[[#This Row],[時価総額]]/T20D35746[[#This Row],[現在値]] -> 68.452055 | H49: =IFERROR(_xll.RssMarket($A49,"PER"),"") -> 0 | I49: =T20D35746[[#This Row],[現在値]] / IFERROR(IF(T20D35746[[#This Row],[PER]] > 0, T20D35746[[#This Row],[PER]], 15), 15) -> 4.8666667 | J49: =IFERROR(_xll.RssMarket($A49,"PBR"),"") -> 1.32 | K49: =T20D35746[[#This Row],[現在値]]/T20D35746[[#This Row],[PBR]] -> 55.30303 | L49: =T20D35746[[#This Row],[EPS]]/T20D35746[[#This Row],[BPS]]*100 -> 8.8 | M49: =IFERROR(_xll.RssMarket($A49,"配当"),"") -> 0 | N49: =T20D35746[[#This Row],[配当]]/T20D35746[[#This Row],[現在値]] -> 0 | O49: =ROUND( ((IF(OR(R49="",R49<=0),20,R49)/20) *(L49/15)) /(IFERROR(IF(H49>0,H49,15),15)/15) *100,0) -> 59 | P49: =ROUND( ((IF(OR(R49="",R49<=0),20,R49)/20) *(L49/15) *((MIN(MAX(S49,0),50)/15)+1) *(1+MIN(MAX(IFERROR(IF(W49="",0,W49),0),-30),50)/200)) /(IFERROR(IF(H49>0,H49,15),15)/15) *100,0) -> 76 | Q49: =T20D35746[[#This Row],[スコア⑤]]/T20D35746[[#This Row],[スコア③]] -> 1.2881356 | R49: 0 | S49: 1 | T49: 1.83 | U49: 0 | V49: 4.3 | W49: =(T20D35746[[#This Row],[現金及び預金（億）]]-T20D35746[[#This Row],[負債（億）]])/T20D35746[[#This Row],[総資産]]*100 -> 42.55814
A50: 2163 | B50: =IFERROR(_xll.RssMarket($A50,"銘柄名称"),"") -> アルトナー | C50: =IFERROR(_xll.RssMarket($A50,"市場部略称"),"") -> 東Ｐ | D50: =IFERROR(_xll.RssMarket($A50,"現在値"),"") -> 2010 | E50: =IFERROR(_xll.RssMarket($A50,"前日比"),"") -> -32 | F50: =IFERROR(_xll.RssMarket($A50,"時価総額"),"") -> 21362 | G50: =T20D35746[[#This Row],[時価総額]]/T20D35746[[#This Row],[現在値]] -> 10.627861 | H50: =IFERROR(_xll.RssMarket($A50,"PER"),"") -> 16.55 | I50: =T20D35746[[#This Row],[現在値]] / IFERROR(IF(T20D35746[[#This Row],[PER]] > 0, T20D35746[[#This Row],[PER]], 15), 15) -> 121.45015 | J50: =IFERROR(_xll.RssMarket($A50,"PBR"),"") -> 4.24 | K50: =T20D35746[[#This Row],[現在値]]/T20D35746[[#This Row],[PBR]] -> 474.0566 | L50: =T20D35746[[#This Row],[EPS]]/T20D35746[[#This Row],[BPS]]*100 -> 25.619335 | M50: =IFERROR(_xll.RssMarket($A50,"配当"),"") -> 84 | N50: =T20D35746[[#This Row],[配当]]/T20D35746[[#This Row],[現在値]] -> 0.041791045 | O50: =ROUND( ((IF(OR(R50="",R50<=0),20,R50)/20) *(L50/15)) /(IFERROR(IF(H50>0,H50,15),15)/15) *100,0) -> 124 | P50: =ROUND( ((IF(OR(R50="",R50<=0),20,R50)/20) *(L50/15) *((MIN(MAX(S50,0),50)/15)+1) *(1+MIN(MAX(IFERROR(IF(W50="",0,W50),0),-30),50)/200)) /(IFERROR(IF(H50>0,H50,15),15)/15) *100,0) -> 165 | Q50: =T20D35746[[#This Row],[スコア⑤]]/T20D35746[[#This Row],[スコア③]] -> 1.3306452 | R50: 15.99 | S50: 1 | T50: 45.9 | U50: 0 | V50: 66.9 | W50: =(T20D35746[[#This Row],[現金及び預金（億）]]-T20D35746[[#This Row],[負債（億）]])/T20D35746[[#This Row],[総資産]]*100 -> 68.609865
A51: 8802 | B51: =IFERROR(_xll.RssMarket($A51,"銘柄名称"),"") -> 三菱地所 | C51: =IFERROR(_xll.RssMarket($A51,"市場部略称"),"") -> 東Ｐ | D51: =IFERROR(_xll.RssMarket($A51,"現在値"),"") -> 4853 | E51: =IFERROR(_xll.RssMarket($A51,"前日比"),"") -> -170 | F51: =IFERROR(_xll.RssMarket($A51,"時価総額"),"") -> 5907235 | G51: =T20D35746[[#This Row],[時価総額]]/T20D35746[[#This Row],[現在値]] -> 1217.2337 | H51: =IFERROR(_xll.RssMarket($A51,"PER"),"") -> 26.75 | I51: =T20D35746[[#This Row],[現在値]] / IFERROR(IF(T20D35746[[#This Row],[PER]] > 0, T20D35746[[#This Row],[PER]], 15), 15) -> 181.42056 | J51: =IFERROR(_xll.RssMarket($A51,"PBR"),"") -> 2.37 | K51: =T20D35746[[#This Row],[現在値]]/T20D35746[[#This Row],[PBR]] -> 2047.6793 | L51: =T20D35746[[#This Row],[EPS]]/T20D35746[[#This Row],[BPS]]*100 -> 8.8598131 | M51: =IFERROR(_xll.RssMarket($A51,"配当"),"") -> 46 | N51: =T20D35746[[#This Row],[配当]]/T20D35746[[#This Row],[現在値]] -> 0.009478673 | O51: =ROUND( ((IF(OR(R51="",R51<=0),20,R51)/20) *(L51/15)) /(IFERROR(IF(H51>0,H51,15),15)/15) *100,0) -> 33 | P51: =ROUND( ((IF(OR(R51="",R51<=0),20,R51)/20) *(L51/15) *((MIN(MAX(S51,0),50)/15)+1) *(1+MIN(MAX(IFERROR(IF(W51="",0,W51),0),-30),50)/200)) /(IFERROR(IF(H51>0,H51,15),15)/15) *100,0) -> 44 | Q51: =T20D35746[[#This Row],[スコア⑤]]/T20D35746[[#This Row],[スコア③]] -> 1.3333333 | S51: 8.6 | T51: 2569 | U51: 33400 | V51: 80000 | W51: =(T20D35746[[#This Row],[現金及び預金（億）]]-T20D35746[[#This Row],[負債（億）]])/T20D35746[[#This Row],[総資産]]*100 -> -38.53875 | X51: 優良銘柄
A52: 9508 | B52: =IFERROR(_xll.RssMarket($A52,"銘柄名称"),"") -> 九州電力 | C52: =IFERROR(_xll.RssMarket($A52,"市場部略称"),"") -> 東Ｐ | D52: =IFERROR(_xll.RssMarket($A52,"現在値"),"") -> 1863 | E52: =IFERROR(_xll.RssMarket($A52,"前日比"),"") -> -17.5 | F52: =IFERROR(_xll.RssMarket($A52,"時価総額"),"") -> 883404 | G52: =T20D35746[[#This Row],[時価総額]]/T20D35746[[#This Row],[現在値]] -> 474.18357 | H52: =IFERROR(_xll.RssMarket($A52,"PER"),"") -> 6.29 | I52: =T20D35746[[#This Row],[現在値]] / IFERROR(IF(T20D35746[[#This Row],[PER]] > 0, T20D35746[[#This Row],[PER]], 15), 15) -> 296.18442 | J52: =IFERROR(_xll.RssMarket($A52,"PBR"),"") -> 0.98 | K52: =T20D35746[[#This Row],[現在値]]/T20D35746[[#This Row],[PBR]] -> 1901.0204 | L52: =T20D35746[[#This Row],[EPS]]/T20D35746[[#This Row],[BPS]]*100 -> 15.580286 | M52: =IFERROR(_xll.RssMarket($A52,"配当"),"") -> 50 | N52: =T20D35746[[#This Row],[配当]]/T20D35746[[#This Row],[現在値]] -> 0.026838433 | O52: =ROUND( ((IF(OR(R52="",R52<=0),20,R52)/20) *(L52/15)) /(IFERROR(IF(H52>0,H52,15),15)/15) *100,0) -> 116 | P52: =ROUND( ((IF(OR(R52="",R52<=0),20,R52)/20) *(L52/15) *((MIN(MAX(S52,0),50)/15)+1) *(1+MIN(MAX(IFERROR(IF(W52="",0,W52),0),-30),50)/200)) /(IFERROR(IF(H52>0,H52,15),15)/15) *100,0) -> 155 | Q52: =T20D35746[[#This Row],[スコア⑤]]/T20D35746[[#This Row],[スコア③]] -> 1.3362069 | R52: 9.33 | S52: 8.7 | T52: 3497 | U52: 33600 | V52: 57700 | W52: =(T20D35746[[#This Row],[現金及び預金（億）]]-T20D35746[[#This Row],[負債（億）]])/T20D35746[[#This Row],[総資産]]*100 -> -52.171577
A53: 3393 | B53: =IFERROR(_xll.RssMarket($A53,"銘柄名称"),"") -> スターティアホールディングス | C53: =IFERROR(_xll.RssMarket($A53,"市場部略称"),"") -> 東Ｐ | D53: =IFERROR(_xll.RssMarket($A53,"現在値"),"") -> 2674 | E53: =IFERROR(_xll.RssMarket($A53,"前日比"),"") -> -115 | F53: =IFERROR(_xll.RssMarket($A53,"時価総額"),"") -> 27382 | G53: =T20D35746[[#This Row],[時価総額]]/T20D35746[[#This Row],[現在値]] -> 10.24009 | H53: =IFERROR(_xll.RssMarket($A53,"PER"),"") -> 12.5 | I53: =T20D35746[[#This Row],[現在値]] / IFERROR(IF(T20D35746[[#This Row],[PER]] > 0, T20D35746[[#This Row],[PER]], 15), 15) -> 213.92 | J53: =IFERROR(_xll.RssMarket($A53,"PBR"),"") -> 3.32 | K53: =T20D35746[[#This Row],[現在値]]/T20D35746[[#This Row],[PBR]] -> 805.42169 | L53: =T20D35746[[#This Row],[EPS]]/T20D35746[[#This Row],[BPS]]*100 -> 26.56 | M53: =IFERROR(_xll.RssMarket($A53,"配当"),"") -> 125 | N53: =T20D35746[[#This Row],[配当]]/T20D35746[[#This Row],[現在値]] -> 0.046746447 | O53: =ROUND( ((IF(OR(R53="",R53<=0),20,R53)/20) *(L53/15)) /(IFERROR(IF(H53>0,H53,15),15)/15) *100,0) -> 132 | P53: =ROUND( ((IF(OR(R53="",R53<=0),20,R53)/20) *(L53/15) *((MIN(MAX(S53,0),50)/15)+1) *(1+MIN(MAX(IFERROR(IF(W53="",0,W53),0),-30),50)/200)) /(IFERROR(IF(H53>0,H53,15),15)/15) *100,0) -> 181 | Q53: =T20D35746[[#This Row],[スコア⑤]]/T20D35746[[#This Row],[スコア③]] -> 1.3712121 | R53: 12.45 | S53: 3.3 | T53: 65.7 | U53: 31.1 | V53: 142 | W53: =(T20D35746[[#This Row],[現金及び預金（億）]]-T20D35746[[#This Row],[負債（億）]])/T20D35746[[#This Row],[総資産]]*100 -> 24.366197
A54: 3741 | B54: =IFERROR(_xll.RssMarket($A54,"銘柄名称"),"") -> セック | C54: =IFERROR(_xll.RssMarket($A54,"市場部略称"),"") -> 東Ｐ | D54: =IFERROR(_xll.RssMarket($A54,"現在値"),"") -> 3870 | E54: =IFERROR(_xll.RssMarket($A54,"前日比"),"") -> -125 | F54: =IFERROR(_xll.RssMarket($A54,"時価総額"),"") -> 39628 | G54: =T20D35746[[#This Row],[時価総額]]/T20D35746[[#This Row],[現在値]] -> 10.239793 | H54: =IFERROR(_xll.RssMarket($A54,"PER"),"") -> 27.25 | I54: =T20D35746[[#This Row],[現在値]] / IFERROR(IF(T20D35746[[#This Row],[PER]] > 0, T20D35746[[#This Row],[PER]], 15), 15) -> 142.01835 | J54: =IFERROR(_xll.RssMarket($A54,"PBR"),"") -> 4.18 | K54: =T20D35746[[#This Row],[現在値]]/T20D35746[[#This Row],[PBR]] -> 925.83732 | L54: =T20D35746[[#This Row],[EPS]]/T20D35746[[#This Row],[BPS]]*100 -> 15.33945 | M54: =IFERROR(_xll.RssMarket($A54,"配当"),"") -> 56 | N54: =T20D35746[[#This Row],[配当]]/T20D35746[[#This Row],[現在値]] -> 0.014470284 | O54: =ROUND( ((IF(OR(R54="",R54<=0),20,R54)/20) *(L54/15)) /(IFERROR(IF(H54>0,H54,15),15)/15) *100,0) -> 48 | P54: =ROUND( ((IF(OR(R54="",R54<=0),20,R54)/20) *(L54/15) *((MIN(MAX(S54,0),50)/15)+1) *(1+MIN(MAX(IFERROR(IF(W54="",0,W54),0),-30),50)/200)) /(IFERROR(IF(H54>0,H54,15),15)/15) *100,0) -> 66 | Q54: =T20D35746[[#This Row],[スコア⑤]]/T20D35746[[#This Row],[スコア③]] -> 1.375 | R54: 17.2 | S54: 3.77 | T54: 22.3 | U54: 0.36 | V54: 118 | W54: =(T20D35746[[#This Row],[現金及び預金（億）]]-T20D35746[[#This Row],[負債（億）]])/T20D35746[[#This Row],[総資産]]*100 -> 18.59322
A55: 2428 | B55: =IFERROR(_xll.RssMarket($A55,"銘柄名称"),"") -> ウェルネット | C55: =IFERROR(_xll.RssMarket($A55,"市場部略称"),"") -> 東Ｓ | D55: =IFERROR(_xll.RssMarket($A55,"現在値"),"") -> 662 | E55: =IFERROR(_xll.RssMarket($A55,"前日比"),"") -> -10 | F55: =IFERROR(_xll.RssMarket($A55,"時価総額"),"") -> 12842 | G55: =T20D35746[[#This Row],[時価総額]]/T20D35746[[#This Row],[現在値]] -> 19.398792 | H55: =IFERROR(_xll.RssMarket($A55,"PER"),"") -> 11.41 | I55: =T20D35746[[#This Row],[現在値]] / IFERROR(IF(T20D35746[[#This Row],[PER]] > 0, T20D35746[[#This Row],[PER]], 15), 15) -> 58.019281 | J55: =IFERROR(_xll.RssMarket($A55,"PBR"),"") -> 1.42 | K55: =T20D35746[[#This Row],[現在値]]/T20D35746[[#This Row],[PBR]] -> 466.19718 | L55: =T20D35746[[#This Row],[EPS]]/T20D35746[[#This Row],[BPS]]*100 -> 12.445223 | M55: =IFERROR(_xll.RssMarket($A55,"配当"),"") -> 29.5 | N55: =T20D35746[[#This Row],[配当]]/T20D35746[[#This Row],[現在値]] -> 0.044561934 | O55: =ROUND( ((IF(OR(R55="",R55<=0),20,R55)/20) *(L55/15)) /(IFERROR(IF(H55>0,H55,15),15)/15) *100,0) -> 80 | P55: =ROUND( ((IF(OR(R55="",R55<=0),20,R55)/20) *(L55/15) *((MIN(MAX(S55,0),50)/15)+1) *(1+MIN(MAX(IFERROR(IF(W55="",0,W55),0),-30),50)/200)) /(IFERROR(IF(H55>0,H55,15),15)/15) *100,0) -> 111 | Q55: =T20D35746[[#This Row],[スコア⑤]]/T20D35746[[#This Row],[スコア③]] -> 1.3875 | R55: 14.61 | S55: 1.71 | T55: 175 | U55: 16 | V55: 293 | W55: =(T20D35746[[#This Row],[現金及び預金（億）]]-T20D35746[[#This Row],[負債（億）]])/T20D35746[[#This Row],[総資産]]*100 -> 54.266212
A56: 8934 | B56: =IFERROR(_xll.RssMarket($A56,"銘柄名称"),"") -> サンフロンティア不動産 | C56: =IFERROR(_xll.RssMarket($A56,"市場部略称"),"") -> 東Ｐ | D56: =IFERROR(_xll.RssMarket($A56,"現在値"),"") -> 2459 | E56: =IFERROR(_xll.RssMarket($A56,"前日比"),"") -> -45 | F56: =IFERROR(_xll.RssMarket($A56,"時価総額"),"") -> 119889 | G56: =T20D35746[[#This Row],[時価総額]]/T20D35746[[#This Row],[現在値]] -> 48.755185 | H56: =IFERROR(_xll.RssMarket($A56,"PER"),"") -> 7.69 | I56: =T20D35746[[#This Row],[現在値]] / IFERROR(IF(T20D35746[[#This Row],[PER]] > 0, T20D35746[[#This Row],[PER]], 15), 15) -> 319.76593 | J56: =IFERROR(_xll.RssMarket($A56,"PBR"),"") -> 1.09 | K56: =T20D35746[[#This Row],[現在値]]/T20D35746[[#This Row],[PBR]] -> 2255.9633 | L56: =T20D35746[[#This Row],[EPS]]/T20D35746[[#This Row],[BPS]]*100 -> 14.174252 | M56: =IFERROR(_xll.RssMarket($A56,"配当"),"") -> 76 | N56: =T20D35746[[#This Row],[配当]]/T20D35746[[#This Row],[現在値]] -> 0.030906873 | O56: =ROUND( ((IF(OR(R56="",R56<=0),20,R56)/20) *(L56/15)) /(IFERROR(IF(H56>0,H56,15),15)/15) *100,0) -> 188 | P56: =ROUND( ((IF(OR(R56="",R56<=0),20,R56)/20) *(L56/15) *((MIN(MAX(S56,0),50)/15)+1) *(1+MIN(MAX(IFERROR(IF(W56="",0,W56),0),-30),50)/200)) /(IFERROR(IF(H56>0,H56,15),15)/15) *100,0) -> 274 | Q56: =T20D35746[[#This Row],[スコア⑤]]/T20D35746[[#This Row],[スコア③]] -> 1.4574468 | R56: 20.38 | S56: 9.53 | T56: 448 | U56: 925 | V56: 2182 | W56: =(T20D35746[[#This Row],[現金及び預金（億）]]-T20D35746[[#This Row],[負債（億）]])/T20D35746[[#This Row],[総資産]]*100 -> -21.860678
A57: 4776 | B57: =IFERROR(_xll.RssMarket($A57,"銘柄名称"),"") -> サイボウズ | C57: =IFERROR(_xll.RssMarket($A57,"市場部略称"),"") -> 東Ｐ | D57: =IFERROR(_xll.RssMarket($A57,"現在値"),"") -> 2117 | E57: =IFERROR(_xll.RssMarket($A57,"前日比"),"") -> -94 | F57: =IFERROR(_xll.RssMarket($A57,"時価総額"),"") -> 111688 | G57: =T20D35746[[#This Row],[時価総額]]/T20D35746[[#This Row],[現在値]] -> 52.757676 | H57: =IFERROR(_xll.RssMarket($A57,"PER"),"") -> 15.54 | I57: =T20D35746[[#This Row],[現在値]] / IFERROR(IF(T20D35746[[#This Row],[PER]] > 0, T20D35746[[#This Row],[PER]], 15), 15) -> 136.22909 | J57: =IFERROR(_xll.RssMarket($A57,"PBR"),"") -> 6.84 | K57: =T20D35746[[#This Row],[現在値]]/T20D35746[[#This Row],[PBR]] -> 309.50292 | L57: =T20D35746[[#This Row],[EPS]]/T20D35746[[#This Row],[BPS]]*100 -> 44.015444 | M57: =IFERROR(_xll.RssMarket($A57,"配当"),"") -> 40 | N57: =T20D35746[[#This Row],[配当]]/T20D35746[[#This Row],[現在値]] -> 0.018894662 | O57: =ROUND( ((IF(OR(R57="",R57<=0),20,R57)/20) *(L57/15)) /(IFERROR(IF(H57>0,H57,15),15)/15) *100,0) -> 382 | P57: =ROUND( ((IF(OR(R57="",R57<=0),20,R57)/20) *(L57/15) *((MIN(MAX(S57,0),50)/15)+1) *(1+MIN(MAX(IFERROR(IF(W57="",0,W57),0),-30),50)/200)) /(IFERROR(IF(H57>0,H57,15),15)/15) *100,0) -> 580 | Q57: =T20D35746[[#This Row],[スコア⑤]]/T20D35746[[#This Row],[スコア③]] -> 1.5183246 | R57: 27 | S57: 5.1 | T57: 55.9 | V57: 211 | W57: =(T20D35746[[#This Row],[現金及び預金（億）]]-T20D35746[[#This Row],[負債（億）]])/T20D35746[[#This Row],[総資産]]*100 -> 26.492891
A58: 9433 | B58: =IFERROR(_xll.RssMarket($A58,"銘柄名称"),"") -> ＫＤＤＩ | C58: =IFERROR(_xll.RssMarket($A58,"市場部略称"),"") -> 東Ｐ | D58: =IFERROR(_xll.RssMarket($A58,"現在値"),"") -> 2694 | E58: =IFERROR(_xll.RssMarket($A58,"前日比"),"") -> 32.5 | F58: =IFERROR(_xll.RssMarket($A58,"時価総額"),"") -> 11282061 | G58: =T20D35746[[#This Row],[時価総額]]/T20D35746[[#This Row],[現在値]] -> 4187.8474 | H58: =IFERROR(_xll.RssMarket($A58,"PER"),"") -> 13.7 | I58: =T20D35746[[#This Row],[現在値]] / IFERROR(IF(T20D35746[[#This Row],[PER]] > 0, T20D35746[[#This Row],[PER]], 15), 15) -> 196.64234 | J58: =IFERROR(_xll.RssMarket($A58,"PBR"),"") -> 2.06 | K58: =T20D35746[[#This Row],[現在値]]/T20D35746[[#This Row],[PBR]] -> 1307.767 | L58: =T20D35746[[#This Row],[EPS]]/T20D35746[[#This Row],[BPS]]*100 -> 15.036496 | M58: =IFERROR(_xll.RssMarket($A58,"配当"),"") -> 80 | N58: =T20D35746[[#This Row],[配当]]/T20D35746[[#This Row],[現在値]] -> 0.02969562 | O58: =ROUND( ((IF(OR(R58="",R58<=0),20,R58)/20) *(L58/15)) /(IFERROR(IF(H58>0,H58,15),15)/15) *100,0) -> 102 | P58: =ROUND( ((IF(OR(R58="",R58<=0),20,R58)/20) *(L58/15) *((MIN(MAX(S58,0),50)/15)+1) *(1+MIN(MAX(IFERROR(IF(W58="",0,W58),0),-30),50)/200)) /(IFERROR(IF(H58>0,H58,15),15)/15) *100,0) -> 159 | Q58: =T20D35746[[#This Row],[スコア⑤]]/T20D35746[[#This Row],[スコア③]] -> 1.5588235 | R58: 18.61 | S58: 11.02 | T58: 9212 | U58: 44400 | V58: 169000 | W58: =(T20D35746[[#This Row],[現金及び預金（億）]]-T20D35746[[#This Row],[負債（億）]])/T20D35746[[#This Row],[総資産]]*100 -> -20.821302 | X58: 優良銘柄
A59: 2436 | B59: =IFERROR(_xll.RssMarket($A59,"銘柄名称"),"") -> 共同ピーアール | C59: =IFERROR(_xll.RssMarket($A59,"市場部略称"),"") -> 東Ｓ | D59: =IFERROR(_xll.RssMarket($A59,"現在値"),"") -> 1021 | E59: =IFERROR(_xll.RssMarket($A59,"前日比"),"") -> 44 | F59: =IFERROR(_xll.RssMarket($A59,"時価総額"),"") -> 9000 | G59: =T20D35746[[#This Row],[時価総額]]/T20D35746[[#This Row],[現在値]] -> 8.8148874 | H59: =IFERROR(_xll.RssMarket($A59,"PER"),"") -> 12.21 | I59: =T20D35746[[#This Row],[現在値]] / IFERROR(IF(T20D35746[[#This Row],[PER]] > 0, T20D35746[[#This Row],[PER]], 15), 15) -> 83.619984 | J59: =IFERROR(_xll.RssMarket($A59,"PBR"),"") -> 2.45 | K59: =T20D35746[[#This Row],[現在値]]/T20D35746[[#This Row],[PBR]] -> 416.73469 | L59: =T20D35746[[#This Row],[EPS]]/T20D35746[[#This Row],[BPS]]*100 -> 20.06552 | M59: =IFERROR(_xll.RssMarket($A59,"配当"),"") -> 14 | N59: =T20D35746[[#This Row],[配当]]/T20D35746[[#This Row],[現在値]] -> 0.013712047 | O59: =ROUND( ((IF(OR(R59="",R59<=0),20,R59)/20) *(L59/15)) /(IFERROR(IF(H59>0,H59,15),15)/15) *100,0) -> 131 | P59: =ROUND( ((IF(OR(R59="",R59<=0),20,R59)/20) *(L59/15) *((MIN(MAX(S59,0),50)/15)+1) *(1+MIN(MAX(IFERROR(IF(W59="",0,W59),0),-30),50)/200)) /(IFERROR(IF(H59>0,H59,15),15)/15) *100,0) -> 209 | Q59: =T20D35746[[#This Row],[スコア⑤]]/T20D35746[[#This Row],[スコア③]] -> 1.5954198 | R59: 16 | S59: 4.1 | T59: 32.3 | U59: 0.539 | V59: 58.1 | W59: =(T20D35746[[#This Row],[現金及び預金（億）]]-T20D35746[[#This Row],[負債（億）]])/T20D35746[[#This Row],[総資産]]*100 -> 54.666093
A60: 4570 | B60: =IFERROR(_xll.RssMarket($A60,"銘柄名称"),"") -> 免疫生物研究所 | C60: =IFERROR(_xll.RssMarket($A60,"市場部略称"),"") -> 東Ｇ | D60: =IFERROR(_xll.RssMarket($A60,"現在値"),"") -> 1579 | E60: =IFERROR(_xll.RssMarket($A60,"前日比"),"") -> -149 | F60: =IFERROR(_xll.RssMarket($A60,"時価総額"),"") -> 14707 | G60: =T20D35746[[#This Row],[時価総額]]/T20D35746[[#This Row],[現在値]] -> 9.3141229 | H60: =IFERROR(_xll.RssMarket($A60,"PER"),"") -> 54.44 | I60: =T20D35746[[#This Row],[現在値]] / IFERROR(IF(T20D35746[[#This Row],[PER]] > 0, T20D35746[[#This Row],[PER]], 15), 15) -> 29.004409 | J60: =IFERROR(_xll.RssMarket($A60,"PBR"),"") -> 8.88 | K60: =T20D35746[[#This Row],[現在値]]/T20D35746[[#This Row],[PBR]] -> 177.81532 | L60: =T20D35746[[#This Row],[EPS]]/T20D35746[[#This Row],[BPS]]*100 -> 16.311536 | M60: =IFERROR(_xll.RssMarket($A60,"配当"),"") -> 6 | N60: =T20D35746[[#This Row],[配当]]/T20D35746[[#This Row],[現在値]] -> 0.0037998733 | O60: =ROUND( ((IF(OR(R60="",R60<=0),20,R60)/20) *(L60/15)) /(IFERROR(IF(H60>0,H60,15),15)/15) *100,0) -> 35 | P60: =ROUND( ((IF(OR(R60="",R60<=0),20,R60)/20) *(L60/15) *((MIN(MAX(S60,0),50)/15)+1) *(1+MIN(MAX(IFERROR(IF(W60="",0,W60),0),-30),50)/200)) /(IFERROR(IF(H60>0,H60,15),15)/15) *100,0) -> 58 | Q60: =T20D35746[[#This Row],[スコア⑤]]/T20D35746[[#This Row],[スコア③]] -> 1.6571429 | R60: 23.41 | S60: 6.39 | T60: 7.71 | U60: 2.04 | V60: 18.5 | W60: =(T20D35746[[#This Row],[現金及び預金（億）]]-T20D35746[[#This Row],[負債（億）]])/T20D35746[[#This Row],[総資産]]*100 -> 30.648649
A61: 146A | B61: =IFERROR(_xll.RssMarket($A61,"銘柄名称"),"") -> コロンビア・ワークス | C61: =IFERROR(_xll.RssMarket($A61,"市場部略称"),"") -> 東Ｓ | D61: =IFERROR(_xll.RssMarket($A61,"現在値"),"") -> 4335 | E61: =IFERROR(_xll.RssMarket($A61,"前日比"),"") -> 700 | F61: =IFERROR(_xll.RssMarket($A61,"時価総額"),"") -> 33451 | G61: =T20D35746[[#This Row],[時価総額]]/T20D35746[[#This Row],[現在値]] -> 7.7164937 | H61: =IFERROR(_xll.RssMarket($A61,"PER"),"") -> 10.86 | I61: =T20D35746[[#This Row],[現在値]] / IFERROR(IF(T20D35746[[#This Row],[PER]] > 0, T20D35746[[#This Row],[PER]], 15), 15) -> 399.17127 | J61: =IFERROR(_xll.RssMarket($A61,"PBR"),"") -> 2.42 | K61: =T20D35746[[#This Row],[現在値]]/T20D35746[[#This Row],[PBR]] -> 1791.3223 | L61: =T20D35746[[#This Row],[EPS]]/T20D35746[[#This Row],[BPS]]*100 -> 22.28361 | M61: =IFERROR(_xll.RssMarket($A61,"配当"),"") -> 70 | N61: =T20D35746[[#This Row],[配当]]/T20D35746[[#This Row],[現在値]] -> 0.016147636 | O61: =ROUND( ((IF(OR(R61="",R61<=0),20,R61)/20) *(L61/15)) /(IFERROR(IF(H61>0,H61,15),15)/15) *100,0) -> 122 | P61: =ROUND( ((IF(OR(R61="",R61<=0),20,R61)/20) *(L61/15) *((MIN(MAX(S61,0),50)/15)+1) *(1+MIN(MAX(IFERROR(IF(W61="",0,W61),0),-30),50)/200)) /(IFERROR(IF(H61>0,H61,15),15)/15) *100,0) -> 204 | Q61: =T20D35746[[#This Row],[スコア⑤]]/T20D35746[[#This Row],[スコア③]] -> 1.6721311 | R61: 11.94 | S61: 14.46 | T61: 42.4 | U61: 376 | V61: 522 | W61: =(T20D35746[[#This Row],[現金及び預金（億）]]-T20D35746[[#This Row],[負債（億）]])/T20D35746[[#This Row],[総資産]]*100 -> -63.908046
A62: 6176 | B62: =IFERROR(_xll.RssMarket($A62,"銘柄名称"),"") -> ブランジスタ | C62: =IFERROR(_xll.RssMarket($A62,"市場部略称"),"") -> 東Ｓ | D62: =IFERROR(_xll.RssMarket($A62,"現在値"),"") -> 730 | E62: =IFERROR(_xll.RssMarket($A62,"前日比"),"") -> 3 | F62: =IFERROR(_xll.RssMarket($A62,"時価総額"),"") -> 10639 | G62: =T20D35746[[#This Row],[時価総額]]/T20D35746[[#This Row],[現在値]] -> 14.573973 | H62: =IFERROR(_xll.RssMarket($A62,"PER"),"") -> 12 | I62: =T20D35746[[#This Row],[現在値]] / IFERROR(IF(T20D35746[[#This Row],[PER]] > 0, T20D35746[[#This Row],[PER]], 15), 15) -> 60.833333 | J62: =IFERROR(_xll.RssMarket($A62,"PBR"),"") -> 1.56 | K62: =T20D35746[[#This Row],[現在値]]/T20D35746[[#This Row],[PBR]] -> 467.94872 | L62: =T20D35746[[#This Row],[EPS]]/T20D35746[[#This Row],[BPS]]*100 -> 13 | M62: =IFERROR(_xll.RssMarket($A62,"配当"),"") -> 15 | N62: =T20D35746[[#This Row],[配当]]/T20D35746[[#This Row],[現在値]] -> 0.020547945 | O62: =ROUND( ((IF(OR(R62="",R62<=0),20,R62)/20) *(L62/15)) /(IFERROR(IF(H62>0,H62,15),15)/15) *100,0) -> 115 | P62: =ROUND( ((IF(OR(R62="",R62<=0),20,R62)/20) *(L62/15) *((MIN(MAX(S62,0),50)/15)+1) *(1+MIN(MAX(IFERROR(IF(W62="",0,W62),0),-30),50)/200)) /(IFERROR(IF(H62>0,H62,15),15)/15) *100,0) -> 196 | Q62: =T20D35746[[#This Row],[スコア⑤]]/T20D35746[[#This Row],[スコア③]] -> 1.7043478 | R62: 21.3 | S62: 8.2 | T62: 13.9 | U62: 4.4 | V62: 49.6 | W62: =(T20D35746[[#This Row],[現金及び預金（億）]]-T20D35746[[#This Row],[負債（億）]])/T20D35746[[#This Row],[総資産]]*100 -> 19.153226
A63: 7148 | B63: =IFERROR(_xll.RssMarket($A63,"銘柄名称"),"") -> ＦＰＧ | C63: =IFERROR(_xll.RssMarket($A63,"市場部略称"),"") -> 東Ｐ | D63: =IFERROR(_xll.RssMarket($A63,"現在値"),"") -> 2038 | E63: =IFERROR(_xll.RssMarket($A63,"前日比"),"") -> -40 | F63: =IFERROR(_xll.RssMarket($A63,"時価総額"),"") -> 170791 | G63: =T20D35746[[#This Row],[時価総額]]/T20D35746[[#This Row],[現在値]] -> 83.803238 | H63: =IFERROR(_xll.RssMarket($A63,"PER"),"") -> 8.12 | I63: =T20D35746[[#This Row],[現在値]] / IFERROR(IF(T20D35746[[#This Row],[PER]] > 0, T20D35746[[#This Row],[PER]], 15), 15) -> 250.98522 | J63: =IFERROR(_xll.RssMarket($A63,"PBR"),"") -> 2.99 | K63: =T20D35746[[#This Row],[現在値]]/T20D35746[[#This Row],[PBR]] -> 681.60535 | L63: =T20D35746[[#This Row],[EPS]]/T20D35746[[#This Row],[BPS]]*100 -> 36.82266 | M63: =IFERROR(_xll.RssMarket($A63,"配当"),"") -> 125.4 | N63: =T20D35746[[#This Row],[配当]]/T20D35746[[#This Row],[現在値]] -> 0.061530913 | O63: =ROUND( ((IF(OR(R63="",R63<=0),20,R63)/20) *(L63/15)) /(IFERROR(IF(H63>0,H63,15),15)/15) *100,0) -> 528 | P63: =ROUND( ((IF(OR(R63="",R63<=0),20,R63)/20) *(L63/15) *((MIN(MAX(S63,0),50)/15)+1) *(1+MIN(MAX(IFERROR(IF(W63="",0,W63),0),-30),50)/200)) /(IFERROR(IF(H63>0,H63,15),15)/15) *100,0) -> 929 | Q63: =T20D35746[[#This Row],[スコア⑤]]/T20D35746[[#This Row],[スコア③]] -> 1.7594697 | R63: 23.29 | S63: 16 | T63: 143 | U63: 520 | V63: 1268 | W63: =(T20D35746[[#This Row],[現金及び預金（億）]]-T20D35746[[#This Row],[負債（億）]])/T20D35746[[#This Row],[総資産]]*100 -> -29.731861
A64: 3962 | B64: =IFERROR(_xll.RssMarket($A64,"銘柄名称"),"") -> チェンジホールディングス | C64: =IFERROR(_xll.RssMarket($A64,"市場部略称"),"") -> 東Ｐ | D64: =IFERROR(_xll.RssMarket($A64,"現在値"),"") -> 1000 | E64: =IFERROR(_xll.RssMarket($A64,"前日比"),"") -> -12 | F64: =IFERROR(_xll.RssMarket($A64,"時価総額"),"") -> 73852 | G64: =T20D35746[[#This Row],[時価総額]]/T20D35746[[#This Row],[現在値]] -> 73.852 | H64: =IFERROR(_xll.RssMarket($A64,"PER"),"") -> 8.81 | I64: =T20D35746[[#This Row],[現在値]] / IFERROR(IF(T20D35746[[#This Row],[PER]] > 0, T20D35746[[#This Row],[PER]], 15), 15) -> 113.50738 | J64: =IFERROR(_xll.RssMarket($A64,"PBR"),"") -> 1.65 | K64: =T20D35746[[#This Row],[現在値]]/T20D35746[[#This Row],[PBR]] -> 606.06061 | L64: =T20D35746[[#This Row],[EPS]]/T20D35746[[#This Row],[BPS]]*100 -> 18.728717 | M64: =IFERROR(_xll.RssMarket($A64,"配当"),"") -> 23 | N64: =T20D35746[[#This Row],[配当]]/T20D35746[[#This Row],[現在値]] -> 0.023 | O64: =ROUND( ((IF(OR(R64="",R64<=0),20,R64)/20) *(L64/15)) /(IFERROR(IF(H64>0,H64,15),15)/15) *100,0) -> 271 | P64: =ROUND( ((IF(OR(R64="",R64<=0),20,R64)/20) *(L64/15) *((MIN(MAX(S64,0),50)/15)+1) *(1+MIN(MAX(IFERROR(IF(W64="",0,W64),0),-30),50)/200)) /(IFERROR(IF(H64>0,H64,15),15)/15) *100,0) -> 489 | Q64: =T20D35746[[#This Row],[スコア⑤]]/T20D35746[[#This Row],[スコア③]] -> 1.804428 | R64: 25.45 | S64: 12.7 | T64: 302 | U64: 345 | V64: 1049 | W64: =(T20D35746[[#This Row],[現金及び預金（億）]]-T20D35746[[#This Row],[負債（億）]])/T20D35746[[#This Row],[総資産]]*100 -> -4.099142
A65: 4746 | B65: =IFERROR(_xll.RssMarket($A65,"銘柄名称"),"") -> 東計電算 | C65: =IFERROR(_xll.RssMarket($A65,"市場部略称"),"") -> 東Ｓ | D65: =IFERROR(_xll.RssMarket($A65,"現在値"),"") -> 4295 | E65: =IFERROR(_xll.RssMarket($A65,"前日比"),"") -> -20 | F65: =IFERROR(_xll.RssMarket($A65,"時価総額"),"") -> 80316 | G65: =T20D35746[[#This Row],[時価総額]]/T20D35746[[#This Row],[現在値]] -> 18.699884 | H65: =IFERROR(_xll.RssMarket($A65,"PER"),"") -> 14.03 | I65: =T20D35746[[#This Row],[現在値]] / IFERROR(IF(T20D35746[[#This Row],[PER]] > 0, T20D35746[[#This Row],[PER]], 15), 15) -> 306.12972 | J65: =IFERROR(_xll.RssMarket($A65,"PBR"),"") -> 1.53 | K65: =T20D35746[[#This Row],[現在値]]/T20D35746[[#This Row],[PBR]] -> 2807.1895 | L65: =T20D35746[[#This Row],[EPS]]/T20D35746[[#This Row],[BPS]]*100 -> 10.905203 | M65: =IFERROR(_xll.RssMarket($A65,"配当"),"") -> 173 | N65: =T20D35746[[#This Row],[配当]]/T20D35746[[#This Row],[現在値]] -> 0.040279395 | O65: =ROUND( ((IF(OR(R65="",R65<=0),20,R65)/20) *(L65/15)) /(IFERROR(IF(H65>0,H65,15),15)/15) *100,0) -> 117 | P65: =ROUND( ((IF(OR(R65="",R65<=0),20,R65)/20) *(L65/15) *((MIN(MAX(S65,0),50)/15)+1) *(1+MIN(MAX(IFERROR(IF(W65="",0,W65),0),-30),50)/200)) /(IFERROR(IF(H65>0,H65,15),15)/15) *100,0) -> 217 | Q65: =T20D35746[[#This Row],[スコア⑤]]/T20D35746[[#This Row],[スコア③]] -> 1.8547009 | R65: 30.08 | S65: 12.23 | T65: 22.1 | U65: 0 | V65: 497 | W65: =(T20D35746[[#This Row],[現金及び預金（億）]]-T20D35746[[#This Row],[負債（億）]])/T20D35746[[#This Row],[総資産]]*100 -> 4.4466801
A66: 4507 | B66: =IFERROR(_xll.RssMarket($A66,"銘柄名称"),"") -> 塩野義製薬 | C66: =IFERROR(_xll.RssMarket($A66,"市場部略称"),"") -> 東Ｐ | D66: =IFERROR(_xll.RssMarket($A66,"現在値"),"") -> 3536 | E66: =IFERROR(_xll.RssMarket($A66,"前日比"),"") -> 1 | F66: =IFERROR(_xll.RssMarket($A66,"時価総額"),"") -> 3145739 | G66: =T20D35746[[#This Row],[時価総額]]/T20D35746[[#This Row],[現在値]] -> 889.63207 | H66: =IFERROR(_xll.RssMarket($A66,"PER"),"") -> 16 | I66: =T20D35746[[#This Row],[現在値]] / IFERROR(IF(T20D35746[[#This Row],[PER]] > 0, T20D35746[[#This Row],[PER]], 15), 15) -> 221 | J66: =IFERROR(_xll.RssMarket($A66,"PBR"),"") -> 2.1 | K66: =T20D35746[[#This Row],[現在値]]/T20D35746[[#This Row],[PBR]] -> 1683.8095 | L66: =T20D35746[[#This Row],[EPS]]/T20D35746[[#This Row],[BPS]]*100 -> 13.125 | M66: =IFERROR(_xll.RssMarket($A66,"配当"),"") -> 66 | N66: =T20D35746[[#This Row],[配当]]/T20D35746[[#This Row],[現在値]] -> 0.018665158 | O66: =ROUND( ((IF(OR(R66="",R66<=0),20,R66)/20) *(L66/15)) /(IFERROR(IF(H66>0,H66,15),15)/15) *100,0) -> 152 | P66: =ROUND( ((IF(OR(R66="",R66<=0),20,R66)/20) *(L66/15) *((MIN(MAX(S66,0),50)/15)+1) *(1+MIN(MAX(IFERROR(IF(W66="",0,W66),0),-30),50)/200)) /(IFERROR(IF(H66>0,H66,15),15)/15) *100,0) -> 282 | Q66: =T20D35746[[#This Row],[スコア⑤]]/T20D35746[[#This Row],[スコア③]] -> 1.8552632 | R66: 37 | S66: 10 | T66: 3748 | U66: 219 | V66: 15400 | W66: =(T20D35746[[#This Row],[現金及び預金（億）]]-T20D35746[[#This Row],[負債（億）]])/T20D35746[[#This Row],[総資産]]*100 -> 22.915584
A67: 6436 | B67: =IFERROR(_xll.RssMarket($A67,"銘柄名称"),"") -> アマノ | C67: =IFERROR(_xll.RssMarket($A67,"市場部略称"),"") -> 東Ｐ | D67: =IFERROR(_xll.RssMarket($A67,"現在値"),"") -> 4004 | E67: =IFERROR(_xll.RssMarket($A67,"前日比"),"") -> -145 | F67: =IFERROR(_xll.RssMarket($A67,"時価総額"),"") -> 284708 | G67: =T20D35746[[#This Row],[時価総額]]/T20D35746[[#This Row],[現在値]] -> 71.105894 | H67: =IFERROR(_xll.RssMarket($A67,"PER"),"") -> 15.75 | I67: =T20D35746[[#This Row],[現在値]] / IFERROR(IF(T20D35746[[#This Row],[PER]] > 0, T20D35746[[#This Row],[PER]], 15), 15) -> 254.22222 | J67: =IFERROR(_xll.RssMarket($A67,"PBR"),"") -> 2.18 | K67: =T20D35746[[#This Row],[現在値]]/T20D35746[[#This Row],[PBR]] -> 1836.6972 | L67: =T20D35746[[#This Row],[EPS]]/T20D35746[[#This Row],[BPS]]*100 -> 13.84127 | M67: =IFERROR(_xll.RssMarket($A67,"配当"),"") -> 180 | N67: =T20D35746[[#This Row],[配当]]/T20D35746[[#This Row],[現在値]] -> 0.044955045 | O67: =ROUND( ((IF(OR(R67="",R67<=0),20,R67)/20) *(L67/15)) /(IFERROR(IF(H67>0,H67,15),15)/15) *100,0) -> 60 | P67: =ROUND( ((IF(OR(R67="",R67<=0),20,R67)/20) *(L67/15) *((MIN(MAX(S67,0),50)/15)+1) *(1+MIN(MAX(IFERROR(IF(W67="",0,W67),0),-30),50)/200)) /(IFERROR(IF(H67>0,H67,15),15)/15) *100,0) -> 116 | Q67: =T20D35746[[#This Row],[スコア⑤]]/T20D35746[[#This Row],[スコア③]] -> 1.9333333 | R67: 13.61 | S67: 10.5 | T67: 559 | U67: 8.71 | V67: 1943 | W67: =(T20D35746[[#This Row],[現金及び預金（億）]]-T20D35746[[#This Row],[負債（億）]])/T20D35746[[#This Row],[総資産]]*100 -> 28.321668
A68: 7095 | B68: =IFERROR(_xll.RssMarket($A68,"銘柄名称"),"") -> ＭＡＣＢＥＥＰＬＡＮＥＴ | C68: =IFERROR(_xll.RssMarket($A68,"市場部略称"),"") -> 東Ｐ | D68: =IFERROR(_xll.RssMarket($A68,"現在値"),"") -> 1435 | E68: =IFERROR(_xll.RssMarket($A68,"前日比"),"") -> -33 | F68: =IFERROR(_xll.RssMarket($A68,"時価総額"),"") -> 21028 | G68: =T20D35746[[#This Row],[時価総額]]/T20D35746[[#This Row],[現在値]] -> 14.653659 | H68: =IFERROR(_xll.RssMarket($A68,"PER"),"") -> 7.99 | I68: =T20D35746[[#This Row],[現在値]] / IFERROR(IF(T20D35746[[#This Row],[PER]] > 0, T20D35746[[#This Row],[PER]], 15), 15) -> 179.5995 | J68: =IFERROR(_xll.RssMarket($A68,"PBR"),"") -> 1.52 | K68: =T20D35746[[#This Row],[現在値]]/T20D35746[[#This Row],[PBR]] -> 944.07895 | L68: =T20D35746[[#This Row],[EPS]]/T20D35746[[#This Row],[BPS]]*100 -> 19.02378 | M68: =IFERROR(_xll.RssMarket($A68,"配当"),"") -> 55 | N68: =T20D35746[[#This Row],[配当]]/T20D35746[[#This Row],[現在値]] -> 0.038327526 | O68: =ROUND( ((IF(OR(R68="",R68<=0),20,R68)/20) *(L68/15)) /(IFERROR(IF(H68>0,H68,15),15)/15) *100,0) -> 109 | P68: =ROUND( ((IF(OR(R68="",R68<=0),20,R68)/20) *(L68/15) *((MIN(MAX(S68,0),50)/15)+1) *(1+MIN(MAX(IFERROR(IF(W68="",0,W68),0),-30),50)/200)) /(IFERROR(IF(H68>0,H68,15),15)/15) *100,0) -> 211 | Q68: =T20D35746[[#This Row],[スコア⑤]]/T20D35746[[#This Row],[スコア③]] -> 1.9357798 | R68: 9.18 | S68: 11.5 | T68: 75.1 | U68: 31.6 | V68: 231 | W68: =(T20D35746[[#This Row],[現金及び預金（億）]]-T20D35746[[#This Row],[負債（億）]])/T20D35746[[#This Row],[総資産]]*100 -> 18.831169
A69: 3031 | B69: =IFERROR(_xll.RssMarket($A69,"銘柄名称"),"") -> ラクーンホールディングス | C69: =IFERROR(_xll.RssMarket($A69,"市場部略称"),"") -> 東Ｐ | D69: =IFERROR(_xll.RssMarket($A69,"現在値"),"") -> 658 | E69: =IFERROR(_xll.RssMarket($A69,"前日比"),"") -> -7 | F69: =IFERROR(_xll.RssMarket($A69,"時価総額"),"") -> 14648 | G69: =T20D35746[[#This Row],[時価総額]]/T20D35746[[#This Row],[現在値]] -> 22.261398 | H69: =IFERROR(_xll.RssMarket($A69,"PER"),"") -> 15.55 | I69: =T20D35746[[#This Row],[現在値]] / IFERROR(IF(T20D35746[[#This Row],[PER]] > 0, T20D35746[[#This Row],[PER]], 15), 15) -> 42.315113 | J69: =IFERROR(_xll.RssMarket($A69,"PBR"),"") -> 2.97 | K69: =T20D35746[[#This Row],[現在値]]/T20D35746[[#This Row],[PBR]] -> 221.54882 | L69: =T20D35746[[#This Row],[EPS]]/T20D35746[[#This Row],[BPS]]*100 -> 19.099678 | M69: =IFERROR(_xll.RssMarket($A69,"配当"),"") -> 22 | N69: =T20D35746[[#This Row],[配当]]/T20D35746[[#This Row],[現在値]] -> 0.03343465 | O69: =ROUND( ((IF(OR(R69="",R69<=0),20,R69)/20) *(L69/15)) /(IFERROR(IF(H69>0,H69,15),15)/15) *100,0) -> 128 | P69: =ROUND( ((IF(OR(R69="",R69<=0),20,R69)/20) *(L69/15) *((MIN(MAX(S69,0),50)/15)+1) *(1+MIN(MAX(IFERROR(IF(W69="",0,W69),0),-30),50)/200)) /(IFERROR(IF(H69>0,H69,15),15)/15) *100,0) -> 251 | Q69: =T20D35746[[#This Row],[スコア⑤]]/T20D35746[[#This Row],[スコア③]] -> 1.9609375 | R69: 20.92 | S69: 11.76 | T69: 43.3 | U69: 12.3 | V69: 162 | W69: =(T20D35746[[#This Row],[現金及び預金（億）]]-T20D35746[[#This Row],[負債（億）]])/T20D35746[[#This Row],[総資産]]*100 -> 19.135802
A70: 4345 | B70: =IFERROR(_xll.RssMarket($A70,"銘柄名称"),"") -> シーティーエス | C70: =IFERROR(_xll.RssMarket($A70,"市場部略称"),"") -> 東Ｐ | D70: =IFERROR(_xll.RssMarket($A70,"現在値"),"") -> 1032 | E70: =IFERROR(_xll.RssMarket($A70,"前日比"),"") -> -18 | F70: =IFERROR(_xll.RssMarket($A70,"時価総額"),"") -> 43344 | G70: =T20D35746[[#This Row],[時価総額]]/T20D35746[[#This Row],[現在値]] -> 42 | H70: =IFERROR(_xll.RssMarket($A70,"PER"),"") -> 16.89 | I70: =T20D35746[[#This Row],[現在値]] / IFERROR(IF(T20D35746[[#This Row],[PER]] > 0, T20D35746[[#This Row],[PER]], 15), 15) -> 61.101243 | J70: =IFERROR(_xll.RssMarket($A70,"PBR"),"") -> 3 | K70: =T20D35746[[#This Row],[現在値]]/T20D35746[[#This Row],[PBR]] -> 344 | L70: =T20D35746[[#This Row],[EPS]]/T20D35746[[#This Row],[BPS]]*100 -> 17.761989 | M70: =IFERROR(_xll.RssMarket($A70,"配当"),"") -> 29 | N70: =T20D35746[[#This Row],[配当]]/T20D35746[[#This Row],[現在値]] -> 0.028100775 | O70: =ROUND( ((IF(OR(R70="",R70<=0),20,R70)/20) *(L70/15)) /(IFERROR(IF(H70>0,H70,15),15)/15) *100,0) -> 136 | P70: =ROUND( ((IF(OR(R70="",R70<=0),20,R70)/20) *(L70/15) *((MIN(MAX(S70,0),50)/15)+1) *(1+MIN(MAX(IFERROR(IF(W70="",0,W70),0),-30),50)/200)) /(IFERROR(IF(H70>0,H70,15),15)/15) *100,0) -> 272 | Q70: =T20D35746[[#This Row],[スコア⑤]]/T20D35746[[#This Row],[スコア③]] -> 2 | R70: 25.78 | S70: 11.53 | T70: 45.3 | U70: 0 | V70: 171 | W70: =(T20D35746[[#This Row],[現金及び預金（億）]]-T20D35746[[#This Row],[負債（億）]])/T20D35746[[#This Row],[総資産]]*100 -> 26.491228
A71: 8267 | B71: =IFERROR(_xll.RssMarket($A71,"銘柄名称"),"") -> イオン | C71: =IFERROR(_xll.RssMarket($A71,"市場部略称"),"") -> 東Ｐ | D71: =IFERROR(_xll.RssMarket($A71,"現在値"),"") -> 2319 | E71: =IFERROR(_xll.RssMarket($A71,"前日比"),"") -> 19 | F71: =IFERROR(_xll.RssMarket($A71,"時価総額"),"") -> 6455003 | G71: =T20D35746[[#This Row],[時価総額]]/T20D35746[[#This Row],[現在値]] -> 2783.5287 | H71: =IFERROR(_xll.RssMarket($A71,"PER"),"") -> 91.66 | I71: =T20D35746[[#This Row],[現在値]] / IFERROR(IF(T20D35746[[#This Row],[PER]] > 0, T20D35746[[#This Row],[PER]], 15), 15) -> 25.300022 | J71: =IFERROR(_xll.RssMarket($A71,"PBR"),"") -> 5.32 | K71: =T20D35746[[#This Row],[現在値]]/T20D35746[[#This Row],[PBR]] -> 435.90226 | L71: =T20D35746[[#This Row],[EPS]]/T20D35746[[#This Row],[BPS]]*100 -> 5.8040585 | M71: =IFERROR(_xll.RssMarket($A71,"配当"),"") -> 13.67 | N71: =T20D35746[[#This Row],[配当]]/T20D35746[[#This Row],[現在値]] -> 0.0058947822 | O71: =ROUND( ((IF(OR(R71="",R71<=0),20,R71)/20) *(L71/15)) /(IFERROR(IF(H71>0,H71,15),15)/15) *100,0) -> 1 | P71: =ROUND(((R71/20)*(L71/15)*(S71/15)*(1+W71/200))/(H71/15)*100,0) -> 2 | Q71: =T20D35746[[#This Row],[スコア⑤]]/T20D35746[[#This Row],[スコア③]] -> 2 | R71: 2.67 | S71: 36.8 | T71: 11700 | U71: 34400 | V71: 138000 | W71: =(T20D35746[[#This Row],[現金及び預金（億）]]-T20D35746[[#This Row],[負債（億）]])/T20D35746[[#This Row],[総資産]]*100 -> -16.449275
A72: 3486 | B72: =IFERROR(_xll.RssMarket($A72,"銘柄名称"),"") -> グロバルリンクマネジメント | C72: =IFERROR(_xll.RssMarket($A72,"市場部略称"),"") -> 東Ｐ | D72: =IFERROR(_xll.RssMarket($A72,"現在値"),"") -> 2238 | E72: =IFERROR(_xll.RssMarket($A72,"前日比"),"") -> -36 | F72: =IFERROR(_xll.RssMarket($A72,"時価総額"),"") -> 35905 | G72: =T20D35746[[#This Row],[時価総額]]/T20D35746[[#This Row],[現在値]] -> 16.043342 | H72: =IFERROR(_xll.RssMarket($A72,"PER"),"") -> 8.28 | I72: =T20D35746[[#This Row],[現在値]] / IFERROR(IF(T20D35746[[#This Row],[PER]] > 0, T20D35746[[#This Row],[PER]], 15), 15) -> 270.28986 | J72: =IFERROR(_xll.RssMarket($A72,"PBR"),"") -> 2.67 | K72: =T20D35746[[#This Row],[現在値]]/T20D35746[[#This Row],[PBR]] -> 838.20225 | L72: =T20D35746[[#This Row],[EPS]]/T20D35746[[#This Row],[BPS]]*100 -> 32.246377 | M72: =IFERROR(_xll.RssMarket($A72,"配当"),"") -> 80.5 | N72: =T20D35746[[#This Row],[配当]]/T20D35746[[#This Row],[現在値]] -> 0.035969616 | O72: =ROUND( ((IF(OR(R72="",R72<=0),20,R72)/20) *(L72/15)) /(IFERROR(IF(H72>0,H72,15),15)/15) *100,0) -> 181 | P72: =ROUND( ((IF(OR(R72="",R72<=0),20,R72)/20) *(L72/15) *((MIN(MAX(S72,0),50)/15)+1) *(1+MIN(MAX(IFERROR(IF(W72="",0,W72),0),-30),50)/200)) /(IFERROR(IF(H72>0,H72,15),15)/15) *100,0) -> 363 | Q72: =T20D35746[[#This Row],[スコア⑤]]/T20D35746[[#This Row],[スコア③]] -> 2.0055249 | R72: 9.31 | S72: 19.82 | T72: 113 | U72: 213 | V72: 364 | W72: =(T20D35746[[#This Row],[現金及び預金（億）]]-T20D35746[[#This Row],[負債（億）]])/T20D35746[[#This Row],[総資産]]*100 -> -27.472527
A73: 3932 | B73: =IFERROR(_xll.RssMarket($A73,"銘柄名称"),"") -> アカツキ | C73: =IFERROR(_xll.RssMarket($A73,"市場部略称"),"") -> 東Ｐ | D73: =IFERROR(_xll.RssMarket($A73,"現在値"),"") -> 2716 | E73: =IFERROR(_xll.RssMarket($A73,"前日比"),"") -> -62 | F73: =IFERROR(_xll.RssMarket($A73,"時価総額"),"") -> 39435 | G73: =T20D35746[[#This Row],[時価総額]]/T20D35746[[#This Row],[現在値]] -> 14.519514 | H73: =IFERROR(_xll.RssMarket($A73,"PER"),"") -> 7.83 | I73: =T20D35746[[#This Row],[現在値]] / IFERROR(IF(T20D35746[[#This Row],[PER]] > 0, T20D35746[[#This Row],[PER]], 15), 15) -> 346.87101 | J73: =IFERROR(_xll.RssMarket($A73,"PBR"),"") -> 0.91 | K73: =T20D35746[[#This Row],[現在値]]/T20D35746[[#This Row],[PBR]] -> 2984.6154 | L73: =T20D35746[[#This Row],[EPS]]/T20D35746[[#This Row],[BPS]]*100 -> 11.621967 | M73: =IFERROR(_xll.RssMarket($A73,"配当"),"") -> 110 | N73: =T20D35746[[#This Row],[配当]]/T20D35746[[#This Row],[現在値]] -> 0.040500736 | O73: =ROUND( ((IF(OR(R73="",R73<=0),20,R73)/20) *(L73/15)) /(IFERROR(IF(H73>0,H73,15),15)/15) *100,0) -> 123 | P73: =ROUND( ((IF(OR(R73="",R73<=0),20,R73)/20) *(L73/15) *((MIN(MAX(S73,0),50)/15)+1) *(1+MIN(MAX(IFERROR(IF(W73="",0,W73),0),-30),50)/200)) /(IFERROR(IF(H73>0,H73,15),15)/15) *100,0) -> 250 | Q73: =T20D35746[[#This Row],[スコア⑤]]/T20D35746[[#This Row],[スコア③]] -> 2.0325203 | R73: 16.55 | S73: 9.81 | T73: 311 | U73: 61 | V73: 546 | W73: =(T20D35746[[#This Row],[現金及び預金（億）]]-T20D35746[[#This Row],[負債（億）]])/T20D35746[[#This Row],[総資産]]*100 -> 45.787546
A74: 7047 | B74: =IFERROR(_xll.RssMarket($A74,"銘柄名称"),"") -> ポート | C74: =IFERROR(_xll.RssMarket($A74,"市場部略称"),"") -> 東Ｇ | D74: =IFERROR(_xll.RssMarket($A74,"現在値"),"") -> 2170 | E74: =IFERROR(_xll.RssMarket($A74,"前日比"),"") -> -29 | F74: =IFERROR(_xll.RssMarket($A74,"時価総額"),"") -> 30698 | G74: =T20D35746[[#This Row],[時価総額]]/T20D35746[[#This Row],[現在値]] -> 14.146544 | H74: =IFERROR(_xll.RssMarket($A74,"PER"),"") -> 11.16 | I74: =T20D35746[[#This Row],[現在値]] / IFERROR(IF(T20D35746[[#This Row],[PER]] > 0, T20D35746[[#This Row],[PER]], 15), 15) -> 194.44444 | J74: =IFERROR(_xll.RssMarket($A74,"PBR"),"") -> 3 | K74: =T20D35746[[#This Row],[現在値]]/T20D35746[[#This Row],[PBR]] -> 723.33333 | L74: =T20D35746[[#This Row],[EPS]]/T20D35746[[#This Row],[BPS]]*100 -> 26.88172 | M74: =IFERROR(_xll.RssMarket($A74,"配当"),"") -> 12 | N74: =T20D35746[[#This Row],[配当]]/T20D35746[[#This Row],[現在値]] -> 0.0055299539 | O74: =ROUND( ((IF(OR(R74="",R74<=0),20,R74)/20) *(L74/15)) /(IFERROR(IF(H74>0,H74,15),15)/15) *100,0) -> 151 | P74: =ROUND( ((IF(OR(R74="",R74<=0),20,R74)/20) *(L74/15) *((MIN(MAX(S74,0),50)/15)+1) *(1+MIN(MAX(IFERROR(IF(W74="",0,W74),0),-30),50)/200)) /(IFERROR(IF(H74>0,H74,15),15)/15) *100,0) -> 312 | Q74: =T20D35746[[#This Row],[スコア⑤]]/T20D35746[[#This Row],[スコア③]] -> 2.0662252 | R74: 12.5 | S74: 20.73 | T74: 25.4 | U74: 84.4 | V74: 227 | W74: =(T20D35746[[#This Row],[現金及び預金（億）]]-T20D35746[[#This Row],[負債（億）]])/T20D35746[[#This Row],[総資産]]*100 -> -25.991189
A75: 2354 | B75: =IFERROR(_xll.RssMarket($A75,"銘柄名称"),"") -> ＹＥＤＩＧＩＴＡＬ | C75: =IFERROR(_xll.RssMarket($A75,"市場部略称"),"") -> 東Ｓ | D75: =IFERROR(_xll.RssMarket($A75,"現在値"),"") -> 792 | E75: =IFERROR(_xll.RssMarket($A75,"前日比"),"") -> -10 | F75: =IFERROR(_xll.RssMarket($A75,"時価総額"),"") -> 14514 | G75: =T20D35746[[#This Row],[時価総額]]/T20D35746[[#This Row],[現在値]] -> 18.325758 | H75: =IFERROR(_xll.RssMarket($A75,"PER"),"") -> 12.27 | I75: =T20D35746[[#This Row],[現在値]] / IFERROR(IF(T20D35746[[#This Row],[PER]] > 0, T20D35746[[#This Row],[PER]], 15), 15) -> 64.547677 | J75: =IFERROR(_xll.RssMarket($A75,"PBR"),"") -> 2.09 | K75: =T20D35746[[#This Row],[現在値]]/T20D35746[[#This Row],[PBR]] -> 378.94737 | L75: =T20D35746[[#This Row],[EPS]]/T20D35746[[#This Row],[BPS]]*100 -> 17.033415 | M75: =IFERROR(_xll.RssMarket($A75,"配当"),"") -> 20 | N75: =T20D35746[[#This Row],[配当]]/T20D35746[[#This Row],[現在値]] -> 0.025252525 | O75: =ROUND( ((IF(OR(R75="",R75<=0),20,R75)/20) *(L75/15)) /(IFERROR(IF(H75>0,H75,15),15)/15) *100,0) -> 56 | P75: =ROUND( ((IF(OR(R75="",R75<=0),20,R75)/20) *(L75/15) *((MIN(MAX(S75,0),50)/15)+1) *(1+MIN(MAX(IFERROR(IF(W75="",0,W75),0),-30),50)/200)) /(IFERROR(IF(H75>0,H75,15),15)/15) *100,0) -> 118 | Q75: =T20D35746[[#This Row],[スコア⑤]]/T20D35746[[#This Row],[スコア③]] -> 2.1071429 | R75: 8 | S75: 13.49 | T75: 32 | U75: 0 | V75: 132 | W75: =(T20D35746[[#This Row],[現金及び預金（億）]]-T20D35746[[#This Row],[負債（億）]])/T20D35746[[#This Row],[総資産]]*100 -> 24.242424
A76: 6101 | B76: =IFERROR(_xll.RssMarket($A76,"銘柄名称"),"") -> ツガミ | C76: =IFERROR(_xll.RssMarket($A76,"市場部略称"),"") -> 東Ｐ | D76: =IFERROR(_xll.RssMarket($A76,"現在値"),"") -> 3690 | E76: =IFERROR(_xll.RssMarket($A76,"前日比"),"") -> -105 | F76: =IFERROR(_xll.RssMarket($A76,"時価総額"),"") -> 177120 | G76: =T20D35746[[#This Row],[時価総額]]/T20D35746[[#This Row],[現在値]] -> 48 | H76: =IFERROR(_xll.RssMarket($A76,"PER"),"") -> 13.78 | I76: =T20D35746[[#This Row],[現在値]] / IFERROR(IF(T20D35746[[#This Row],[PER]] > 0, T20D35746[[#This Row],[PER]], 15), 15) -> 267.77939 | J76: =IFERROR(_xll.RssMarket($A76,"PBR"),"") -> 2.54 | K76: =T20D35746[[#This Row],[現在値]]/T20D35746[[#This Row],[PBR]] -> 1452.7559 | L76: =T20D35746[[#This Row],[EPS]]/T20D35746[[#This Row],[BPS]]*100 -> 18.432511 | M76: =IFERROR(_xll.RssMarket($A76,"配当"),"") -> 72 | N76: =T20D35746[[#This Row],[配当]]/T20D35746[[#This Row],[現在値]] -> 0.019512195 | O76: =ROUND( ((IF(OR(R76="",R76<=0),20,R76)/20) *(L76/15)) /(IFERROR(IF(H76>0,H76,15),15)/15) *100,0) -> 157 | P76: =ROUND( ((IF(OR(R76="",R76<=0),20,R76)/20) *(L76/15) *((MIN(MAX(S76,0),50)/15)+1) *(1+MIN(MAX(IFERROR(IF(W76="",0,W76),0),-30),50)/200)) /(IFERROR(IF(H76>0,H76,15),15)/15) *100,0) -> 334 | Q76: =T20D35746[[#This Row],[スコア⑤]]/T20D35746[[#This Row],[スコア③]] -> 2.1273885 | R76: 23.48 | S76: 15.03 | T76: 277 | U76: 115 | V76: 1273 | W76: =(T20D35746[[#This Row],[現金及び預金（億）]]-T20D35746[[#This Row],[負債（億）]])/T20D35746[[#This Row],[総資産]]*100 -> 12.725844
A77: 3933 | B77: =IFERROR(_xll.RssMarket($A77,"銘柄名称"),"") -> チエル | C77: =IFERROR(_xll.RssMarket($A77,"市場部略称"),"") -> 東Ｓ | D77: =IFERROR(_xll.RssMarket($A77,"現在値"),"") -> 685 | E77: =IFERROR(_xll.RssMarket($A77,"前日比"),"") -> 8 | F77: =IFERROR(_xll.RssMarket($A77,"時価総額"),"") -> 5392 | G77: =T20D35746[[#This Row],[時価総額]]/T20D35746[[#This Row],[現在値]] -> 7.8715328 | H77: =IFERROR(_xll.RssMarket($A77,"PER"),"") -> 10.44 | I77: =T20D35746[[#This Row],[現在値]] / IFERROR(IF(T20D35746[[#This Row],[PER]] > 0, T20D35746[[#This Row],[PER]], 15), 15) -> 65.613027 | J77: =IFERROR(_xll.RssMarket($A77,"PBR"),"") -> 1.56 | K77: =T20D35746[[#This Row],[現在値]]/T20D35746[[#This Row],[PBR]] -> 439.10256 | L77: =T20D35746[[#This Row],[EPS]]/T20D35746[[#This Row],[BPS]]*100 -> 14.942529 | M77: =IFERROR(_xll.RssMarket($A77,"配当"),"") -> 15 | N77: =T20D35746[[#This Row],[配当]]/T20D35746[[#This Row],[現在値]] -> 0.02189781 | O77: =ROUND( ((IF(OR(R77="",R77<=0),20,R77)/20) *(L77/15)) /(IFERROR(IF(H77>0,H77,15),15)/15) *100,0) -> 54 | P77: =ROUND( ((IF(OR(R77="",R77<=0),20,R77)/20) *(L77/15) *((MIN(MAX(S77,0),50)/15)+1) *(1+MIN(MAX(IFERROR(IF(W77="",0,W77),0),-30),50)/200)) /(IFERROR(IF(H77>0,H77,15),15)/15) *100,0) -> 115 | Q77: =T20D35746[[#This Row],[スコア⑤]]/T20D35746[[#This Row],[スコア③]] -> 2.1296296 | R77: 7.5 | S77: 15.45 | T77: 31.3 | U77: 18.9 | V77: 106 | W77: =(T20D35746[[#This Row],[現金及び預金（億）]]-T20D35746[[#This Row],[負債（億）]])/T20D35746[[#This Row],[総資産]]*100 -> 11.698113
A78: 5903 | B78: =IFERROR(_xll.RssMarket($A78,"銘柄名称"),"") -> シンポ | C78: =IFERROR(_xll.RssMarket($A78,"市場部略称"),"") -> 東Ｓ | D78: =IFERROR(_xll.RssMarket($A78,"現在値"),"") -> 1196 | E78: =IFERROR(_xll.RssMarket($A78,"前日比"),"") -> -6 | F78: =IFERROR(_xll.RssMarket($A78,"時価総額"),"") -> 7344 | G78: =T20D35746[[#This Row],[時価総額]]/T20D35746[[#This Row],[現在値]] -> 6.1404682 | H78: =IFERROR(_xll.RssMarket($A78,"PER"),"") -> 9.94 | I78: =T20D35746[[#This Row],[現在値]] / IFERROR(IF(T20D35746[[#This Row],[PER]] > 0, T20D35746[[#This Row],[PER]], 15), 15) -> 120.32193 | J78: =IFERROR(_xll.RssMarket($A78,"PBR"),"") -> 0.94 | K78: =T20D35746[[#This Row],[現在値]]/T20D35746[[#This Row],[PBR]] -> 1272.3404 | L78: =T20D35746[[#This Row],[EPS]]/T20D35746[[#This Row],[BPS]]*100 -> 9.4567404 | M78: =IFERROR(_xll.RssMarket($A78,"配当"),"") -> 42 | N78: =T20D35746[[#This Row],[配当]]/T20D35746[[#This Row],[現在値]] -> 0.035117057 | O78: =ROUND( ((IF(OR(R78="",R78<=0),20,R78)/20) *(L78/15)) /(IFERROR(IF(H78>0,H78,15),15)/15) *100,0) -> 62 | P78: =ROUND( ((IF(OR(R78="",R78<=0),20,R78)/20) *(L78/15) *((MIN(MAX(S78,0),50)/15)+1) *(1+MIN(MAX(IFERROR(IF(W78="",0,W78),0),-30),50)/200)) /(IFERROR(IF(H78>0,H78,15),15)/15) *100,0) -> 133 | Q78: =T20D35746[[#This Row],[スコア⑤]]/T20D35746[[#This Row],[スコア③]] -> 2.1451613 | R78: 12.98 | S78: 14.07 | T78: 19.7 | U78: 0.502 | V78: 87 | W78: =(T20D35746[[#This Row],[現金及び預金（億）]]-T20D35746[[#This Row],[負債（億）]])/T20D35746[[#This Row],[総資産]]*100 -> 22.066667
A79: 2222 | B79: =IFERROR(_xll.RssMarket($A79,"銘柄名称"),"") -> 寿スピリッツ | C79: =IFERROR(_xll.RssMarket($A79,"市場部略称"),"") -> 東Ｐ | D79: =IFERROR(_xll.RssMarket($A79,"現在値"),"") -> 1979 | E79: =IFERROR(_xll.RssMarket($A79,"前日比"),"") -> -97 | F79: =IFERROR(_xll.RssMarket($A79,"時価総額"),"") -> 308047 | G79: =T20D35746[[#This Row],[時価総額]]/T20D35746[[#This Row],[現在値]] -> 155.65791 | H79: =IFERROR(_xll.RssMarket($A79,"PER"),"") -> 23.14 | I79: =T20D35746[[#This Row],[現在値]] / IFERROR(IF(T20D35746[[#This Row],[PER]] > 0, T20D35746[[#This Row],[PER]], 15), 15) -> 85.522904 | J79: =IFERROR(_xll.RssMarket($A79,"PBR"),"") -> 7.58 | K79: =T20D35746[[#This Row],[現在値]]/T20D35746[[#This Row],[PBR]] -> 261.08179 | L79: =T20D35746[[#This Row],[EPS]]/T20D35746[[#This Row],[BPS]]*100 -> 32.757131 | M79: =IFERROR(_xll.RssMarket($A79,"配当"),"") -> 35 | N79: =T20D35746[[#This Row],[配当]]/T20D35746[[#This Row],[現在値]] -> 0.0176857 | O79: =ROUND( ((IF(OR(R79="",R79<=0),20,R79)/20) *(L79/15)) /(IFERROR(IF(H79>0,H79,15),15)/15) *100,0) -> 175 | P79: =ROUND( ((IF(OR(R79="",R79<=0),20,R79)/20) *(L79/15) *((MIN(MAX(S79,0),50)/15)+1) *(1+MIN(MAX(IFERROR(IF(W79="",0,W79),0),-30),50)/200)) /(IFERROR(IF(H79>0,H79,15),15)/15) *100,0) -> 379 | Q79: =T20D35746[[#This Row],[スコア⑤]]/T20D35746[[#This Row],[スコア③]] -> 2.1657143 | R79: 24.66 | S79: 11.3 | T79: 251 | U79: 3 | V79: 520 | W79: =(T20D35746[[#This Row],[現金及び預金（億）]]-T20D35746[[#This Row],[負債（億）]])/T20D35746[[#This Row],[総資産]]*100 -> 47.692308
A80: 4051 | B80: =IFERROR(_xll.RssMarket($A80,"銘柄名称"),"") -> ＧＭＯフィナンシャルゲート | C80: =IFERROR(_xll.RssMarket($A80,"市場部略称"),"") -> 東Ｐ | D80: =IFERROR(_xll.RssMarket($A80,"現在値"),"") -> 5250 | E80: =IFERROR(_xll.RssMarket($A80,"前日比"),"") -> 30 | F80: =IFERROR(_xll.RssMarket($A80,"時価総額"),"") -> 43782 | G80: =T20D35746[[#This Row],[時価総額]]/T20D35746[[#This Row],[現在値]] -> 8.3394286 | H80: =IFERROR(_xll.RssMarket($A80,"PER"),"") -> 23.17 | I80: =T20D35746[[#This Row],[現在値]] / IFERROR(IF(T20D35746[[#This Row],[PER]] > 0, T20D35746[[#This Row],[PER]], 15), 15) -> 226.5861 | J80: =IFERROR(_xll.RssMarket($A80,"PBR"),"") -> 6.92 | K80: =T20D35746[[#This Row],[現在値]]/T20D35746[[#This Row],[PBR]] -> 758.67052 | L80: =T20D35746[[#This Row],[EPS]]/T20D35746[[#This Row],[BPS]]*100 -> 29.866206 | M80: =IFERROR(_xll.RssMarket($A80,"配当"),"") -> 125 | N80: =T20D35746[[#This Row],[配当]]/T20D35746[[#This Row],[現在値]] -> 0.023809524 | O80: =ROUND( ((IF(OR(R80="",R80<=0),20,R80)/20) *(L80/15)) /(IFERROR(IF(H80>0,H80,15),15)/15) *100,0) -> 91 | P80: =ROUND( ((IF(OR(R80="",R80<=0),20,R80)/20) *(L80/15) *((MIN(MAX(S80,0),50)/15)+1) *(1+MIN(MAX(IFERROR(IF(W80="",0,W80),0),-30),50)/200)) /(IFERROR(IF(H80>0,H80,15),15)/15) *100,0) -> 198 | Q80: =T20D35746[[#This Row],[スコア⑤]]/T20D35746[[#This Row],[スコア③]] -> 2.1758242 | R80: 14.19 | S80: 14.95 | T80: 42.6 | U80: 20 | V80: 138 | W80: =(T20D35746[[#This Row],[現金及び預金（億）]]-T20D35746[[#This Row],[負債（億）]])/T20D35746[[#This Row],[総資産]]*100 -> 16.376812
A81: 4054 | B81: =IFERROR(_xll.RssMarket($A81,"銘柄名称"),"") -> 日本情報クリエイト | C81: =IFERROR(_xll.RssMarket($A81,"市場部略称"),"") -> 東Ｇ | D81: =IFERROR(_xll.RssMarket($A81,"現在値"),"") -> 600 | E81: =IFERROR(_xll.RssMarket($A81,"前日比"),"") -> -6 | F81: =IFERROR(_xll.RssMarket($A81,"時価総額"),"") -> 8624 | G81: =T20D35746[[#This Row],[時価総額]]/T20D35746[[#This Row],[現在値]] -> 14.373333 | H81: =IFERROR(_xll.RssMarket($A81,"PER"),"") -> 11.27 | I81: =T20D35746[[#This Row],[現在値]] / IFERROR(IF(T20D35746[[#This Row],[PER]] > 0, T20D35746[[#This Row],[PER]], 15), 15) -> 53.238687 | J81: =IFERROR(_xll.RssMarket($A81,"PBR"),"") -> 2.13 | K81: =T20D35746[[#This Row],[現在値]]/T20D35746[[#This Row],[PBR]] -> 281.69014 | L81: =T20D35746[[#This Row],[EPS]]/T20D35746[[#This Row],[BPS]]*100 -> 18.899734 | M81: =IFERROR(_xll.RssMarket($A81,"配当"),"") -> 12 | N81: =T20D35746[[#This Row],[配当]]/T20D35746[[#This Row],[現在値]] -> 0.02 | O81: =ROUND( ((IF(OR(R81="",R81<=0),20,R81)/20) *(L81/15)) /(IFERROR(IF(H81>0,H81,15),15)/15) *100,0) -> 173 | P81: =ROUND( ((IF(OR(R81="",R81<=0),20,R81)/20) *(L81/15) *((MIN(MAX(S81,0),50)/15)+1) *(1+MIN(MAX(IFERROR(IF(W81="",0,W81),0),-30),50)/200)) /(IFERROR(IF(H81>0,H81,15),15)/15) *100,0) -> 380 | Q81: =T20D35746[[#This Row],[スコア⑤]]/T20D35746[[#This Row],[スコア③]] -> 2.1965318 | R81: 20.69 | S81: 16.31 | T81: 5.79 | U81: 0 | V81: 57.2 | W81: =(T20D35746[[#This Row],[現金及び預金（億）]]-T20D35746[[#This Row],[負債（億）]])/T20D35746[[#This Row],[総資産]]*100 -> 10.122378
A82: 4262 | B82: =IFERROR(_xll.RssMarket($A82,"銘柄名称"),"") -> ニフティライフスタイル | C82: =IFERROR(_xll.RssMarket($A82,"市場部略称"),"") -> 東Ｇ | D82: =IFERROR(_xll.RssMarket($A82,"現在値"),"") -> 1456 | E82: =IFERROR(_xll.RssMarket($A82,"前日比"),"") -> -3 | F82: =IFERROR(_xll.RssMarket($A82,"時価総額"),"") -> 9293 | G82: =T20D35746[[#This Row],[時価総額]]/T20D35746[[#This Row],[現在値]] -> 6.3825549 | H82: =IFERROR(_xll.RssMarket($A82,"PER"),"") -> 12.16 | I82: =T20D35746[[#This Row],[現在値]] / IFERROR(IF(T20D35746[[#This Row],[PER]] > 0, T20D35746[[#This Row],[PER]], 15), 15) -> 119.73684 | J82: =IFERROR(_xll.RssMarket($A82,"PBR"),"") -> 1.56 | K82: =T20D35746[[#This Row],[現在値]]/T20D35746[[#This Row],[PBR]] -> 933.33333 | L82: =T20D35746[[#This Row],[EPS]]/T20D35746[[#This Row],[BPS]]*100 -> 12.828947 | M82: =IFERROR(_xll.RssMarket($A82,"配当"),"") -> 60 | N82: =T20D35746[[#This Row],[配当]]/T20D35746[[#This Row],[現在値]] -> 0.041208791 | O82: =ROUND( ((IF(OR(R82="",R82<=0),20,R82)/20) *(L82/15)) /(IFERROR(IF(H82>0,H82,15),15)/15) *100,0) -> 106 | P82: =ROUND( ((IF(OR(R82="",R82<=0),20,R82)/20) *(L82/15) *((MIN(MAX(S82,0),50)/15)+1) *(1+MIN(MAX(IFERROR(IF(W82="",0,W82),0),-30),50)/200)) /(IFERROR(IF(H82>0,H82,15),15)/15) *100,0) -> 233 | Q82: =T20D35746[[#This Row],[スコア⑤]]/T20D35746[[#This Row],[スコア③]] -> 2.1981132 | R82: 20.14 | S82: 11.3 | T82: 41.8 | U82: 0 | V82: 70.2 | W82: =(T20D35746[[#This Row],[現金及び預金（億）]]-T20D35746[[#This Row],[負債（億）]])/T20D35746[[#This Row],[総資産]]*100 -> 59.54416
A83: 3064 | B83: =IFERROR(_xll.RssMarket($A83,"銘柄名称"),"") -> ＭｏｎｏｔａＲＯ | C83: =IFERROR(_xll.RssMarket($A83,"市場部略称"),"") -> 東Ｐ | D83: =IFERROR(_xll.RssMarket($A83,"現在値"),"") -> 2074.5 | E83: =IFERROR(_xll.RssMarket($A83,"前日比"),"") -> -94.5 | F83: =IFERROR(_xll.RssMarket($A83,"時価総額"),"") -> 1040073 | G83: =T20D35746[[#This Row],[時価総額]]/T20D35746[[#This Row],[現在値]] -> 501.36081 | H83: =IFERROR(_xll.RssMarket($A83,"PER"),"") -> 28.49 | I83: =T20D35746[[#This Row],[現在値]] / IFERROR(IF(T20D35746[[#This Row],[PER]] > 0, T20D35746[[#This Row],[PER]], 15), 15) -> 72.815023 | J83: =IFERROR(_xll.RssMarket($A83,"PBR"),"") -> 8.41 | K83: =T20D35746[[#This Row],[現在値]]/T20D35746[[#This Row],[PBR]] -> 246.67063 | L83: =T20D35746[[#This Row],[EPS]]/T20D35746[[#This Row],[BPS]]*100 -> 29.51913 | M83: =IFERROR(_xll.RssMarket($A83,"配当"),"") -> 37 | N83: =T20D35746[[#This Row],[配当]]/T20D35746[[#This Row],[現在値]] -> 0.017835623 | O83: =ROUND( ((IF(OR(R83="",R83<=0),20,R83)/20) *(L83/15)) /(IFERROR(IF(H83>0,H83,15),15)/15) *100,0) -> 68 | P83: =ROUND( ((IF(OR(R83="",R83<=0),20,R83)/20) *(L83/15) *((MIN(MAX(S83,0),50)/15)+1) *(1+MIN(MAX(IFERROR(IF(W83="",0,W83),0),-30),50)/200)) /(IFERROR(IF(H83>0,H83,15),15)/15) *100,0) -> 150 | Q83: =T20D35746[[#This Row],[スコア⑤]]/T20D35746[[#This Row],[スコア③]] -> 2.2058824 | R83: 13.1 | S83: 15 | T83: 304 | U83: 4.3 | V83: 1450 | W83: =(T20D35746[[#This Row],[現金及び預金（億）]]-T20D35746[[#This Row],[負債（億）]])/T20D35746[[#This Row],[総資産]]*100 -> 20.668966
... A92: 9984 | B92: =IFERROR(_xll.RssMarket($A92,"銘柄名称"),"") -> ソフトバンクグループ | C92: =IFERROR(_xll.RssMarket($A92,"市場部略称"),"") -> 東Ｐ | D92: =IFERROR(_xll.RssMarket($A92,"現在値"),"") -> 4390 | E92: =IFERROR(_xll.RssMarket($A92,"前日比"),"") -> -427 | F92: =IFERROR(_xll.RssMarket($A92,"時価総額"),"") -> 25075013 | G92: =T20D35746[[#This Row],[時価総額]]/T20D35746[[#This Row],[現在値]] -> 5711.8481 | H92: =IFERROR(_xll.RssMarket($A92,"PER"),"") -> 7.58 | I92: =T20D35746[[#This Row],[現在値]] / IFERROR(IF(T20D35746[[#This Row],[PER]] > 0, T20D35746[[#This Row],[PER]], 15), 15) -> 579.15567 | J92: =IFERROR(_xll.RssMarket($A92,"PBR"),"") -> 1.77 | K92: =T20D35746[[#This Row],[現在値]]/T20D35746[[#This Row],[PBR]] -> 2480.226 | L92: =T20D35746[[#This Row],[EPS]]/T20D35746[[#This Row],[BPS]]*100 -> 23.350923 | M92: =IFERROR(_xll.RssMarket($A92,"配当"),"") -> 11 | N92: =T20D35746[[#This Row],[配当]]/T20D35746[[#This Row],[現在値]] -> 0.0025056948 | O92: =ROUND( ((IF(OR(R92="",R92<=0),20,R92)/20) *(L92/15)) /(IFERROR(IF(H92>0,H92,15),15)/15) *100,0) -> 155 | P92: =ROUND( ((IF(OR(R92="",R92<=0),20,R92)/20) *(L92/15) *((MIN(MAX(S92,0),50)/15)+1) *(1+MIN(MAX(IFERROR(IF(W92="",0,W92),0),-30),50)/200)) /(IFERROR(IF(H92>0,H92,15),15)/15) *100,0) -> 396 | Q92: =T20D35746[[#This Row],[スコア⑤]]/T20D35746[[#This Row],[スコア③]] -> 2.5548387 | R92: 10.07 | S92: 30 | T92: 3.71 | U92: 180000 | V92: 450000 | W92: =(T20D35746[[#This Row],[現金及び預金（億）]]-T20D35746[[#This Row],[負債（億）]])/T20D35746[[#This Row],[総資産]]*100 -> -39.999176
A93: 3825 | B93: =IFERROR(_xll.RssMarket($A93,"銘柄名称"),"") -> リミックスポイント | C93: =IFERROR(_xll.RssMarket($A93,"市場部略称"),"") -> 東Ｓ | D93: =IFERROR(_xll.RssMarket($A93,"現在値"),"") -> 233 | E93: =IFERROR(_xll.RssMarket($A93,"前日比"),"") -> -14 | F93: =IFERROR(_xll.RssMarket($A93,"時価総額"),"") -> 34726 | G93: =T20D35746[[#This Row],[時価総額]]/T20D35746[[#This Row],[現在値]] -> 149.03863 | H93: =IFERROR(_xll.RssMarket($A93,"PER"),"") -> 16.29 | I93: =T20D35746[[#This Row],[現在値]] / IFERROR(IF(T20D35746[[#This Row],[PER]] > 0, T20D35746[[#This Row],[PER]], 15), 15) -> 14.303254 | J93: =IFERROR(_xll.RssMarket($A93,"PBR"),"") -> 1.04 | K93: =T20D35746[[#This Row],[現在値]]/T20D35746[[#This Row],[PBR]] -> 224.03846 | L93: =T20D35746[[#This Row],[EPS]]/T20D35746[[#This Row],[BPS]]*100 -> 6.3842848 | M93: =IFERROR(_xll.RssMarket($A93,"配当"),"") -> 5 | N93: =T20D35746[[#This Row],[配当]]/T20D35746[[#This Row],[現在値]] -> 0.021459227 | O93: =ROUND( ((IF(OR(R93="",R93<=0),20,R93)/20) *(L93/15)) /(IFERROR(IF(H93>0,H93,15),15)/15) *100,0) -> 51 | P93: =ROUND( ((IF(OR(R93="",R93<=0),20,R93)/20) *(L93/15) *((MIN(MAX(S93,0),50)/15)+1) *(1+MIN(MAX(IFERROR(IF(W93="",0,W93),0),-30),50)/200)) /(IFERROR(IF(H93>0,H93,15),15)/15) *100,0) -> 134 | Q93: =T20D35746[[#This Row],[スコア⑤]]/T20D35746[[#This Row],[スコア③]] -> 2.627451 | R93: 26.18 | S93: 20 | T93: 51 | U93: 3.19 | V93: 205 | W93: =(T20D35746[[#This Row],[現金及び預金（億）]]-T20D35746[[#This Row],[負債（億）]])/T20D35746[[#This Row],[総資産]]*100 -> 23.321951 | X93: 仮想通貨。1Q黒転。１Q特別利益が多い。通期予測保守的に22円で計算。評価益が売上に入る会計
A94: 4189 | B94: =IFERROR(_xll.RssMarket($A94,"銘柄名称"),"") -> ＫＨネオケム | C94: =IFERROR(_xll.RssMarket($A94,"市場部略称"),"") -> 東Ｐ | D94: =IFERROR(_xll.RssMarket($A94,"現在値"),"") -> 2989 | E94: =IFERROR(_xll.RssMarket($A94,"前日比"),"") -> -41 | F94: =IFERROR(_xll.RssMarket($A94,"時価総額"),"") -> 111039 | G94: =T20D35746[[#This Row],[時価総額]]/T20D35746[[#This Row],[現在値]] -> 37.149214 | H94: =IFERROR(_xll.RssMarket($A94,"PER"),"") -> 12.02 | I94: =T20D35746[[#This Row],[現在値]] / IFERROR(IF(T20D35746[[#This Row],[PER]] > 0, T20D35746[[#This Row],[PER]], 15), 15) -> 248.66889 | J94: =IFERROR(_xll.RssMarket($A94,"PBR"),"") -> 1.5 | K94: =T20D35746[[#This Row],[現在値]]/T20D35746[[#This Row],[PBR]] -> 1992.6667 | L94: =T20D35746[[#This Row],[EPS]]/T20D35746[[#This Row],[BPS]]*100 -> 12.479201 | M94: =IFERROR(_xll.RssMarket($A94,"配当"),"") -> 110 | N94: =T20D35746[[#This Row],[配当]]/T20D35746[[#This Row],[現在値]] -> 0.036801606 | O94: =ROUND( ((IF(OR(R94="",R94<=0),20,R94)/20) *(L94/15)) /(IFERROR(IF(H94>0,H94,15),15)/15) *100,0) -> 57 | P94: =ROUND( ((IF(OR(R94="",R94<=0),20,R94)/20) *(L94/15) *((MIN(MAX(S94,0),50)/15)+1) *(1+MIN(MAX(IFERROR(IF(W94="",0,W94),0),-30),50)/200)) /(IFERROR(IF(H94>0,H94,15),15)/15) *100,0) -> 152 | Q94: =T20D35746[[#This Row],[スコア⑤]]/T20D35746[[#This Row],[スコア③]] -> 2.6666667 | R94: 10.99 | S94: 26.5 | T94: 71.6 | U94: 177 | V94: 1315 | W94: =(T20D35746[[#This Row],[現金及び預金（億）]]-T20D35746[[#This Row],[負債（億）]])/T20D35746[[#This Row],[総資産]]*100 -> -8.0152091
A95: 8789 | B95: =IFERROR(_xll.RssMarket($A95,"銘柄名称"),"") -> フィンテックグローバル | C95: =IFERROR(_xll.RssMarket($A95,"市場部略称"),"") -> 東Ｓ | D95: =IFERROR(_xll.RssMarket($A95,"現在値"),"") -> 149 | E95: =IFERROR(_xll.RssMarket($A95,"前日比"),"") -> -9 | F95: =IFERROR(_xll.RssMarket($A95,"時価総額"),"") -> 29996 | G95: =T20D35746[[#This Row],[時価総額]]/T20D35746[[#This Row],[現在値]] -> 201.31544 | H95: =IFERROR(_xll.RssMarket($A95,"PER"),"") -> 10.64 | I95: =T20D35746[[#This Row],[現在値]] / IFERROR(IF(T20D35746[[#This Row],[PER]] > 0, T20D35746[[#This Row],[PER]], 15), 15) -> 14.003759 | J95: =IFERROR(_xll.RssMarket($A95,"PBR"),"") -> 2.63 | K95: =T20D35746[[#This Row],[現在値]]/T20D35746[[#This Row],[PBR]] -> 56.653992 | L95: =T20D35746[[#This Row],[EPS]]/T20D35746[[#This Row],[BPS]]*100 -> 24.718045 | M95: =IFERROR(_xll.RssMarket($A95,"配当"),"") -> 5 | N95: =T20D35746[[#This Row],[配当]]/T20D35746[[#This Row],[現在値]] -> 0.033557047 | O95: =ROUND( ((IF(OR(R95="",R95<=0),20,R95)/20) *(L95/15)) /(IFERROR(IF(H95>0,H95,15),15)/15) *100,0) -> 268 | P95: =ROUND( ((IF(OR(R95="",R95<=0),20,R95)/20) *(L95/15) *((MIN(MAX(S95,0),50)/15)+1) *(1+MIN(MAX(IFERROR(IF(W95="",0,W95),0),-30),50)/200)) /(IFERROR(IF(H95>0,H95,15),15)/15) *100,0) -> 717 | Q95: =T20D35746[[#This Row],[スコア⑤]]/T20D35746[[#This Row],[スコア③]] -> 2.6753731 | R95: 23.08 | S95: 28.58 | T95: 64.4 | U95: 107.12 | V95: 270 | W95: =(T20D35746[[#This Row],[現金及び預金（億）]]-T20D35746[[#This Row],[負債（億）]])/T20D35746[[#This Row],[総資産]]*100 -> -15.822222
A96: 4389 | B96: =IFERROR(_xll.RssMarket($A96,"銘柄名称"),"") -> プロパティデータバンク | C96: =IFERROR(_xll.RssMarket($A96,"市場部略称"),"") -> 東Ｇ | D96: =IFERROR(_xll.RssMarket($A96,"現在値"),"") -> 788 | E96: =IFERROR(_xll.RssMarket($A96,"前日比"),"") -> -56 | F96: =IFERROR(_xll.RssMarket($A96,"時価総額"),"") -> 9349 | G96: =T20D35746[[#This Row],[時価総額]]/T20D35746[[#This Row],[現在値]] -> 11.864213 | H96: =IFERROR(_xll.RssMarket($A96,"PER"),"") -> 12.42 | I96: =T20D35746[[#This Row],[現在値]] / IFERROR(IF(T20D35746[[#This Row],[PER]] > 0, T20D35746[[#This Row],[PER]], 15), 15) -> 63.446055 | J96: =IFERROR(_xll.RssMarket($A96,"PBR"),"") -> 2.3 | K96: =T20D35746[[#This Row],[現在値]]/T20D35746[[#This Row],[PBR]] -> 342.6087 | L96: =T20D35746[[#This Row],[EPS]]/T20D35746[[#This Row],[BPS]]*100 -> 18.518519 | M96: =IFERROR(_xll.RssMarket($A96,"配当"),"") -> 12 | N96: =T20D35746[[#This Row],[配当]]/T20D35746[[#This Row],[現在値]] -> 0.015228426 | O96: =ROUND( ((IF(OR(R96="",R96<=0),20,R96)/20) *(L96/15)) /(IFERROR(IF(H96>0,H96,15),15)/15) *100,0) -> 194 | P96: =ROUND( ((IF(OR(R96="",R96<=0),20,R96)/20) *(L96/15) *((MIN(MAX(S96,0),50)/15)+1) *(1+MIN(MAX(IFERROR(IF(W96="",0,W96),0),-30),50)/200)) /(IFERROR(IF(H96>0,H96,15),15)/15) *100,0) -> 532 | Q96: =T20D35746[[#This Row],[スコア⑤]]/T20D35746[[#This Row],[スコア③]] -> 2.742268 | R96: 26 | S96: 17.96 | T96: 26.7 | U96: 0 | V96: 48.4 | W96: =(T20D35746[[#This Row],[現金及び預金（億）]]-T20D35746[[#This Row],[負債（億）]])/T20D35746[[#This Row],[総資産]]*100 -> 55.165289
A97: 3939 | B97: =IFERROR(_xll.RssMarket($A97,"銘柄名称"),"") -> カナミックネットワーク | C97: =IFERROR(_xll.RssMarket($A97,"市場部略称"),"") -> 東Ｐ | D97: =IFERROR(_xll.RssMarket($A97,"現在値"),"") -> 518 | E97: =IFERROR(_xll.RssMarket($A97,"前日比"),"") -> -25 | F97: =IFERROR(_xll.RssMarket($A97,"時価総額"),"") -> 24932 | G97: =T20D35746[[#This Row],[時価総額]]/T20D35746[[#This Row],[現在値]] -> 48.131274 | H97: =IFERROR(_xll.RssMarket($A97,"PER"),"") -> 17.92 | I97: =T20D35746[[#This Row],[現在値]] / IFERROR(IF(T20D35746[[#This Row],[PER]] > 0, T20D35746[[#This Row],[PER]], 15), 15) -> 28.90625 | J97: =IFERROR(_xll.RssMarket($A97,"PBR"),"") -> 5.28 | K97: =T20D35746[[#This Row],[現在値]]/T20D35746[[#This Row],[PBR]] -> 98.106061 | L97: =T20D35746[[#This Row],[EPS]]/T20D35746[[#This Row],[BPS]]*100 -> 29.464286 | M97: =IFERROR(_xll.RssMarket($A97,"配当"),"") -> 9 | N97: =T20D35746[[#This Row],[配当]]/T20D35746[[#This Row],[現在値]] -> 0.017374517 | O97: =ROUND( ((IF(OR(R97="",R97<=0),20,R97)/20) *(L97/15)) /(IFERROR(IF(H97>0,H97,15),15)/15) *100,0) -> 235 | P97: =ROUND( ((IF(OR(R97="",R97<=0),20,R97)/20) *(L97/15) *((MIN(MAX(S97,0),50)/15)+1) *(1+MIN(MAX(IFERROR(IF(W97="",0,W97),0),-30),50)/200)) /(IFERROR(IF(H97>0,H97,15),15)/15) *100,0) -> 652 | Q97: =T20D35746[[#This Row],[スコア⑤]]/T20D35746[[#This Row],[スコア③]] -> 2.7744681 | R97: 28.57 | S97: 19.6 | T97: 34.3 | U97: 9.26 | V97: 61.8 | W97: =(T20D35746[[#This Row],[現金及び預金（億）]]-T20D35746[[#This Row],[負債（億）]])/T20D35746[[#This Row],[総資産]]*100 -> 40.517799
A98: 5596 | B98: =IFERROR(_xll.RssMarket($A98,"銘柄名称"),"") -> アウトルックコンサルティング | C98: =IFERROR(_xll.RssMarket($A98,"市場部略称"),"") -> 東Ｇ | D98: =IFERROR(_xll.RssMarket($A98,"現在値"),"") -> 1788 | E98: =IFERROR(_xll.RssMarket($A98,"前日比"),"") -> 1 | F98: =IFERROR(_xll.RssMarket($A98,"時価総額"),"") -> 6400 | G98: =T20D35746[[#This Row],[時価総額]]/T20D35746[[#This Row],[現在値]] -> 3.5794183 | H98: =IFERROR(_xll.RssMarket($A98,"PER"),"") -> 14.11 | I98: =T20D35746[[#This Row],[現在値]] / IFERROR(IF(T20D35746[[#This Row],[PER]] > 0, T20D35746[[#This Row],[PER]], 15), 15) -> 126.71864 | J98: =IFERROR(_xll.RssMarket($A98,"PBR"),"") -> 4.99 | K98: =T20D35746[[#This Row],[現在値]]/T20D35746[[#This Row],[PBR]] -> 358.31663 | L98: =T20D35746[[#This Row],[EPS]]/T20D35746[[#This Row],[BPS]]*100 -> 35.364989 | M98: =IFERROR(_xll.RssMarket($A98,"配当"),"") -> 17 | N98: =T20D35746[[#This Row],[配当]]/T20D35746[[#This Row],[現在値]] -> 0.00950783 | O98: =ROUND( ((IF(OR(R98="",R98<=0),20,R98)/20) *(L98/15)) /(IFERROR(IF(H98>0,H98,15),15)/15) *100,0) -> 363 | P98: =ROUND( ((IF(OR(R98="",R98<=0),20,R98)/20) *(L98/15) *((MIN(MAX(S98,0),50)/15)+1) *(1+MIN(MAX(IFERROR(IF(W98="",0,W98),0),-30),50)/200)) /(IFERROR(IF(H98>0,H98,15),15)/15) *100,0) -> 1058 | Q98: =T20D35746[[#This Row],[スコア⑤]]/T20D35746[[#This Row],[スコア③]] -> 2.9146006 | R98: 29 | S98: 19.95 | T98: 8.74 | V98: 12.3 | W98: =(T20D35746[[#This Row],[現金及び預金（億）]]-T20D35746[[#This Row],[負債（億）]])/T20D35746[[#This Row],[総資産]]*100 -> 71.056911
A99: 6071 | B99: =IFERROR(_xll.RssMarket($A99,"銘柄名称"),"") -> ＩＢＪ | C99: =IFERROR(_xll.RssMarket($A99,"市場部略称"),"") -> 東Ｐ | D99: =IFERROR(_xll.RssMarket($A99,"現在値"),"") -> 717 | E99: =IFERROR(_xll.RssMarket($A99,"前日比"),"") -> -14 | F99: =IFERROR(_xll.RssMarket($A99,"時価総額"),"") -> 30114 | G99: =T20D35746[[#This Row],[時価総額]]/T20D35746[[#This Row],[現在値]] -> 42 | H99: =IFERROR(_xll.RssMarket($A99,"PER"),"") -> 17.4 | I99: =T20D35746[[#This Row],[現在値]] / IFERROR(IF(T20D35746[[#This Row],[PER]] > 0, T20D35746[[#This Row],[PER]], 15), 15) -> 41.206897 | J99: =IFERROR(_xll.RssMarket($A99,"PBR"),"") -> 2.93 | K99: =T20D35746[[#This Row],[現在値]]/T20D35746[[#This Row],[PBR]] -> 244.7099 | L99: =T20D35746[[#This Row],[EPS]]/T20D35746[[#This Row],[BPS]]*100 -> 16.83908 | M99: =IFERROR(_xll.RssMarket($A99,"配当"),"") -> 10 | N99: =T20D35746[[#This Row],[配当]]/T20D35746[[#This Row],[現在値]] -> 0.013947001 | O99: =ROUND( ((IF(OR(R99="",R99<=0),20,R99)/20) *(L99/15)) /(IFERROR(IF(H99>0,H99,15),15)/15) *100,0) -> 78 | P99: =ROUND( ((IF(OR(R99="",R99<=0),20,R99)/20) *(L99/15) *((MIN(MAX(S99,0),50)/15)+1) *(1+MIN(MAX(IFERROR(IF(W99="",0,W99),0),-30),50)/200)) /(IFERROR(IF(H99>0,H99,15),15)/15) *100,0) -> 233 | Q99: =T20D35746[[#This Row],[スコア⑤]]/T20D35746[[#This Row],[スコア③]] -> 2.9871795 | R99: 16.1 | S99: 30.77 | T99: 43.7 | U99: 51.7 | V99: 185 | W99: =(T20D35746[[#This Row],[現金及び預金（億）]]-T20D35746[[#This Row],[負債（億）]])/T20D35746[[#This Row],[総資産]]*100 -> -4.3243243
A100: 9552 | B100: =IFERROR(_xll.RssMarket($A100,"銘柄名称"),"") -> クオンツ総研ホールディンク | C100: =IFERROR(_xll.RssMarket($A100,"市場部略称"),"") -> 東Ｐ | D100: =IFERROR(_xll.RssMarket($A100,"現在値"),"") -> 1048 | E100: =IFERROR(_xll.RssMarket($A100,"前日比"),"") -> -32 | F100: =IFERROR(_xll.RssMarket($A100,"時価総額"),"") -> 56698 | G100: =T20D35746[[#This Row],[時価総額]]/T20D35746[[#This Row],[現在値]] -> 54.101145 | H100: =IFERROR(_xll.RssMarket($A100,"PER"),"") -> 16.04 | I100: =T20D35746[[#This Row],[現在値]] / IFERROR(IF(T20D35746[[#This Row],[PER]] > 0, T20D35746[[#This Row],[PER]], 15), 15) -> 65.336658 | J100: =IFERROR(_xll.RssMarket($A100,"PBR"),"") -> 10.75 | K100: =T20D35746[[#This Row],[現在値]]/T20D35746[[#This Row],[PBR]] -> 97.488372 | L100: =T20D35746[[#This Row],[EPS]]/T20D35746[[#This Row],[BPS]]*100 -> 67.01995 | M100: =IFERROR(_xll.RssMarket($A100,"配当"),"") -> 6 | N100: =T20D35746[[#This Row],[配当]]/T20D35746[[#This Row],[現在値]] -> 0.0057251908 | O100: =ROUND( ((IF(OR(R100="",R100<=0),20,R100)/20) *(L100/15)) /(IFERROR(IF(H100>0,H100,15),15)/15) *100,0) -> 564 | P100: =ROUND( ((IF(OR(R100="",R100<=0),20,R100)/20) *(L100/15) *((MIN(MAX(S100,0),50)/15)+1) *(1+MIN(MAX(IFERROR(IF(W100="",0,W100),0),-30),50)/200)) /(IFERROR(IF(H100>0,H100,15),15)/15) *100,0) -> 1743 | Q100: =T20D35746[[#This Row],[スコア⑤]]/T20D35746[[#This Row],[スコア③]] -> 3.0904255 | R100: 27.01 | S100: 22.06 | T100: 42.2 | U100: 0.15 | V100: 72.9 | W100: =(T20D35746[[#This Row],[現金及び預金（億）]]-T20D35746[[#This Row],[負債（億）]])/T20D35746[[#This Row],[総資産]]*100 -> 57.681756
A101: 8306 | B101: =IFERROR(_xll.RssMarket($A101,"銘柄名称"),"") -> 三菱ＵＦＪフィナンシャルＧ | C101: =IFERROR(_xll.RssMarket($A101,"市場部略称"),"") -> 東Ｐ | D101: =IFERROR(_xll.RssMarket($A101,"現在値"),"") -> 3003 | E101: =IFERROR(_xll.RssMarket($A101,"前日比"),"") -> -82 | F101: =IFERROR(_xll.RssMarket($A101,"時価総額"),"") -> 35638735 | G101: =T20D35746[[#This Row],[時価総額]]/T20D35746[[#This Row],[現在値]] -> 11867.711 | H101: =IFERROR(_xll.RssMarket($A101,"PER"),"") -> 16.17 | I101: =T20D35746[[#This Row],[現在値]] / IFERROR(IF(T20D35746[[#This Row],[PER]] > 0, T20D35746[[#This Row],[PER]], 15), 15) -> 185.71429 | J101: =IFERROR(_xll.RssMarket($A101,"PBR"),"") -> 1.63 | K101: =T20D35746[[#This Row],[現在値]]/T20D35746[[#This Row],[PBR]] -> 1842.3313 | L101: =T20D35746[[#This Row],[EPS]]/T20D35746[[#This Row],[BPS]]*100 -> 10.080396 | M101: =IFERROR(_xll.RssMarket($A101,"配当"),"") -> 74 | N101: =T20D35746[[#This Row],[配当]]/T20D35746[[#This Row],[現在値]] -> 0.024642025 | O101: =ROUND( ((IF(OR(R101="",R101<=0),20,R101)/20) *(L101/15)) /(IFERROR(IF(H101>0,H101,15),15)/15) *100,0) -> 47 | P101: =ROUND( ((IF(OR(R101="",R101<=0),20,R101)/20) *(L101/15) *((MIN(MAX(S101,0),50)/15)+1) *(1+MIN(MAX(IFERROR(IF(W101="",0,W101),0),-30),50)/200)) /(IFERROR(IF(H101>0,H101,15),15)/15) *100,0) -> 150 | Q101: =T20D35746[[#This Row],[スコア⑤]]/T20D35746[[#This Row],[スコア③]] -> 3.1914894 | R101: 15 | S101: 28.37 | T101: 1090000 | U101: 175000 | V101: 4130000 | W101: =(T20D35746[[#This Row],[現金及び預金（億）]]-T20D35746[[#This Row],[負債（億）]])/T20D35746[[#This Row],[総資産]]*100 -> 22.154964 | X101: 優良銘柄
A102: 8316 | B102: =IFERROR(_xll.RssMarket($A102,"銘柄名称"),"") -> 三井住友フィナンシャルＧ | C102: =IFERROR(_xll.RssMarket($A102,"市場部略称"),"") -> 東Ｐ | D102: =IFERROR(_xll.RssMarket($A102,"現在値"),"") -> 6062 | E102: =IFERROR(_xll.RssMarket($A102,"前日比"),"") -> -142 | F102: =IFERROR(_xll.RssMarket($A102,"時価総額"),"") -> 23383605 | G102: =T20D35746[[#This Row],[時価総額]]/T20D35746[[#This Row],[現在値]] -> 3857.4076 | H102: =IFERROR(_xll.RssMarket($A102,"PER"),"") -> 15.42 | I102: =T20D35746[[#This Row],[現在値]] / IFERROR(IF(T20D35746[[#This Row],[PER]] > 0, T20D35746[[#This Row],[PER]], 15), 15) -> 393.12581 | J102: =IFERROR(_xll.RssMarket($A102,"PBR"),"") -> 1.53 | K102: =T20D35746[[#This Row],[現在値]]/T20D35746[[#This Row],[PBR]] -> 3962.0915 | L102: =T20D35746[[#This Row],[EPS]]/T20D35746[[#This Row],[BPS]]*100 -> 9.922179 | M102: =IFERROR(_xll.RssMarket($A102,"配当"),"") -> 157 | N102: =T20D35746[[#This Row],[配当]]/T20D35746[[#This Row],[現在値]] -> 0.025899043 | O102: =ROUND( ((IF(OR(R102="",R102<=0),20,R102)/20) *(L102/15)) /(IFERROR(IF(H102>0,H102,15),15)/15) *100,0) -> 64 | P102: =ROUND( ((IF(OR(R102="",R102<=0),20,R102)/20) *(L102/15) *((MIN(MAX(S102,0),50)/15)+1) *(1+MIN(MAX(IFERROR(IF(W102="",0,W102),0),-30),50)/200)) /(IFERROR(IF(H102>0,H102,15),15)/15) *100,0) -> 205 | Q102: =T20D35746[[#This Row],[スコア⑤]]/T20D35746[[#This Row],[スコア③]] -> 3.203125 | S102: 29.13 | T102: 662000 | U102: 160000 | V102: 3060000 | W102: =(T20D35746[[#This Row],[現金及び預金（億）]]-T20D35746[[#This Row],[負債（億）]])/T20D35746[[#This Row],[総資産]]*100 -> 16.405229 | X102: 優良銘柄
A103: 9416 | B103: =IFERROR(_xll.RssMarket($A103,"銘柄名称"),"") -> ビジョン | C103: =IFERROR(_xll.RssMarket($A103,"市場部略称"),"") -> 東Ｐ | D103: =IFERROR(_xll.RssMarket($A103,"現在値"),"") -> 1293 | E103: =IFERROR(_xll.RssMarket($A103,"前日比"),"") -> -18 | F103: =IFERROR(_xll.RssMarket($A103,"時価総額"),"") -> 65863 | G103: =T20D35746[[#This Row],[時価総額]]/T20D35746[[#This Row],[現在値]] -> 50.938128 | H103: =IFERROR(_xll.RssMarket($A103,"PER"),"") -> 14.87 | I103: =T20D35746[[#This Row],[現在値]] / IFERROR(IF(T20D35746[[#This Row],[PER]] > 0, T20D35746[[#This Row],[PER]], 15), 15) -> 86.953598 | J103: =IFERROR(_xll.RssMarket($A103,"PBR"),"") -> 3.32 | K103: =T20D35746[[#This Row],[現在値]]/T20D35746[[#This Row],[PBR]] -> 389.45783 | L103: =T20D35746[[#This Row],[EPS]]/T20D35746[[#This Row],[BPS]]*100 -> 22.326833 | M103: =IFERROR(_xll.RssMarket($A103,"配当"),"") -> 50 | N103: =T20D35746[[#This Row],[配当]]/T20D35746[[#This Row],[現在値]] -> 0.03866976 | O103: =ROUND( ((IF(OR(R103="",R103<=0),20,R103)/20) *(L103/15)) /(IFERROR(IF(H103>0,H103,15),15)/15) *100,0) -> 121 | P103: =ROUND( ((IF(OR(R103="",R103<=0),20,R103)/20) *(L103/15) *((MIN(MAX(S103,0),50)/15)+1) *(1+MIN(MAX(IFERROR(IF(W103="",0,W103),0),-30),50)/200)) /(IFERROR(IF(H103>0,H103,15),15)/15) *100,0) -> 424 | Q103: =T20D35746[[#This Row],[スコア⑤]]/T20D35746[[#This Row],[スコア③]] -> 3.5041322 | R103: 16.1 | S103: 28.02 | T103: 119 | U103: 6 | V103: 253 | W103: =(T20D35746[[#This Row],[現金及び預金（億）]]-T20D35746[[#This Row],[負債（億）]])/T20D35746[[#This Row],[総資産]]*100 -> 44.664032
A104: 3683 | B104: =IFERROR(_xll.RssMarket($A104,"銘柄名称"),"") -> サイバーリンクス | C104: =IFERROR(_xll.RssMarket($A104,"市場部略称"),"") -> 東Ｓ | D104: =IFERROR(_xll.RssMarket($A104,"現在値"),"") -> 1219 | E104: =IFERROR(_xll.RssMarket($A104,"前日比"),"") -> -88 | F104: =IFERROR(_xll.RssMarket($A104,"時価総額"),"") -> 13915 | G104: =T20D35746[[#This Row],[時価総額]]/T20D35746[[#This Row],[現在値]] -> 11.415094 | H104: =IFERROR(_xll.RssMarket($A104,"PER"),"") -> 11.25 | I104: =T20D35746[[#This Row],[現在値]] / IFERROR(IF(T20D35746[[#This Row],[PER]] > 0, T20D35746[[#This Row],[PER]], 15), 15) -> 108.35556 | J104: =IFERROR(_xll.RssMarket($A104,"PBR"),"") -> 1.6 | K104: =T20D35746[[#This Row],[現在値]]/T20D35746[[#This Row],[PBR]] -> 761.875 | L104: =T20D35746[[#This Row],[EPS]]/T20D35746[[#This Row],[BPS]]*100 -> 14.222222 | M104: =IFERROR(_xll.RssMarket($A104,"配当"),"") -> 30 | N104: =T20D35746[[#This Row],[配当]]/T20D35746[[#This Row],[現在値]] -> 0.024610336 | O104: =ROUND( ((IF(OR(R104="",R104<=0),20,R104)/20) *(L104/15)) /(IFERROR(IF(H104>0,H104,15),15)/15) *100,0) -> 62 | P104: =ROUND( ((IF(OR(R104="",R104<=0),20,R104)/20) *(L104/15) *((MIN(MAX(S104,0),50)/15)+1) *(1+MIN(MAX(IFERROR(IF(W104="",0,W104),0),-30),50)/200)) /(IFERROR(IF(H104>0,H104,15),15)/15) *100,0) -> 224 | Q104: =T20D35746[[#This Row],[スコア⑤]]/T20D35746[[#This Row],[スコア③]] -> 3.6129032 | R104: 9.76 | S104: 42.05 | T104: 15.3 | U104: 28 | V104: 136 | W104: =(T20D35746[[#This Row],[現金及び預金（億）]]-T20D35746[[#This Row],[負債（億）]])/T20D35746[[#This Row],[総資産]]*100 -> -9.3382353
A105: 5248 | B105: =IFERROR(_xll.RssMarket($A105,"銘柄名称"),"") -> テクノロジーズ | C105: =IFERROR(_xll.RssMarket($A105,"市場部略称"),"") -> 東Ｇ | D105: =IFERROR(_xll.RssMarket($A105,"現在値"),"") -> 523 | E105: =IFERROR(_xll.RssMarket($A105,"前日比"),"") -> -15 | F105: =IFERROR(_xll.RssMarket($A105,"時価総額"),"") -> 8850 | G105: =T20D35746[[#This Row],[時価総額]]/T20D35746[[#This Row],[現在値]] -> 16.921606 | H105: =IFERROR(_xll.RssMarket($A105,"PER"),"") -> 17.72 | I105: =T20D35746[[#This Row],[現在値]] / IFERROR(IF(T20D35746[[#This Row],[PER]] > 0, T20D35746[[#This Row],[PER]], 15), 15) -> 29.514673 | J105: =IFERROR(_xll.RssMarket($A105,"PBR"),"") -> 6.33 | K105: =T20D35746[[#This Row],[現在値]]/T20D35746[[#This Row],[PBR]] -> 82.622433 | L105: =T20D35746[[#This Row],[EPS]]/T20D35746[[#This Row],[BPS]]*100 -> 35.722348 | M105: =IFERROR(_xll.RssMarket($A105,"配当"),"") -> 0 | N105: =T20D35746[[#This Row],[配当]]/T20D35746[[#This Row],[現在値]] -> 0 | O105: =ROUND( ((IF(OR(R105="",R105<=0),20,R105)/20) *(L105/15)) /(IFERROR(IF(H105>0,H105,15),15)/15) *100,0) -> 210 | P105: =ROUND( ((IF(OR(R105="",R105<=0),20,R105)/20) *(L105/15) *((MIN(MAX(S105,0),50)/15)+1) *(1+MIN(MAX(IFERROR(IF(W105="",0,W105),0),-30),50)/200)) /(IFERROR(IF(H105>0,H105,15),15)/15) *100,0) -> 777 | Q105: =T20D35746[[#This Row],[スコア⑤]]/T20D35746[[#This Row],[スコア③]] -> 3.7 | R105: 20.84 | S105: 86.06 | T105: 17.9 | U105: 73.3 | V105: 189 | W105: =(T20D35746[[#This Row],[現金及び預金（億）]]-T20D35746[[#This Row],[負債（億）]])/T20D35746[[#This Row],[総資産]]*100 -> -29.312169 | X105: 進歩率悪い。買えない
A106: 4495 | B106: =IFERROR(_xll.RssMarket($A106,"銘柄名称"),"") -> アイキューブドシステムズ | C106: =IFERROR(_xll.RssMarket($A106,"市場部略称"),"") -> 東Ｇ | D106: =IFERROR(_xll.RssMarket($A106,"現在値"),"") -> 2408 | E106: =IFERROR(_xll.RssMarket($A106,"前日比"),"") -> -20 | F106: =IFERROR(_xll.RssMarket($A106,"時価総額"),"") -> 12788 | G106: =T20D35746[[#This Row],[時価総額]]/T20D35746[[#This Row],[現在値]] -> 5.3106312 | H106: =IFERROR(_xll.RssMarket($A106,"PER"),"") -> 16.58 | I106: =T20D35746[[#This Row],[現在値]] / IFERROR(IF(T20D35746[[#This Row],[PER]] > 0, T20D35746[[#This Row],[PER]], 15), 15) -> 145.23522 | J106: =IFERROR(_xll.RssMarket($A106,"PBR"),"") -> 4.59 | K106: =T20D35746[[#This Row],[現在値]]/T20D35746[[#This Row],[PBR]] -> 524.61874 | L106: =T20D35746[[#This Row],[EPS]]/T20D35746[[#This Row],[BPS]]*100 -> 27.683957 | M106: =IFERROR(_xll.RssMarket($A106,"配当"),"") -> 36 | N106: =T20D35746[[#This Row],[配当]]/T20D35746[[#This Row],[現在値]] -> 0.014950166 | O106: =ROUND( ((IF(OR(R106="",R106<=0),20,R106)/20) *(L106/15)) /(IFERROR(IF(H106>0,H106,15),15)/15) *100,0) -> 206 | P106: =ROUND( ((IF(OR(R106="",R106<=0),20,R106)/20) *(L106/15) *((MIN(MAX(S106,0),50)/15)+1) *(1+MIN(MAX(IFERROR(IF(W106="",0,W106),0),-30),50)/200)) /(IFERROR(IF(H106>0,H106,15),15)/15) *100,0) -> 793 | Q106: =T20D35746[[#This Row],[スコア⑤]]/T20D35746[[#This Row],[スコア③]] -> 3.8495146 | R106: 24.69 | S106: 31.16 | T106: 22.2 | V106: 44.4 | W106: =(T20D35746[[#This Row],[現金及び預金（億）]]-T20D35746[[#This Row],[負債（億）]])/T20D35746[[#This Row],[総資産]]*100 -> 50
A107: 339A | B107: =IFERROR(_xll.RssMarket($A107,"銘柄名称"),"") -> プログレス・テクノロジース | C107: =IFERROR(_xll.RssMarket($A107,"市場部略称"),"") -> 東Ｇ | D107: =IFERROR(_xll.RssMarket($A107,"現在値"),"") -> 1487 | E107: =IFERROR(_xll.RssMarket($A107,"前日比"),"") -> -55 | F107: =IFERROR(_xll.RssMarket($A107,"時価総額"),"") -> 11568 | G107: =T20D35746[[#This Row],[時価総額]]/T20D35746[[#This Row],[現在値]] -> 7.7794217 | H107: =IFERROR(_xll.RssMarket($A107,"PER"),"") -> 10.51 | I107: =T20D35746[[#This Row],[現在値]] / IFERROR(IF(T20D35746[[#This Row],[PER]] > 0, T20D35746[[#This Row],[PER]], 15), 15) -> 141.4843 | J107: =IFERROR(_xll.RssMarket($A107,"PBR"),"") -> 2.12 | K107: =T20D35746[[#This Row],[現在値]]/T20D35746[[#This Row],[PBR]] -> 701.41509 | L107: =T20D35746[[#This Row],[EPS]]/T20D35746[[#This Row],[BPS]]*100 -> 20.171265 | M107: =IFERROR(_xll.RssMarket($A107,"配当"),"") -> 30 | N107: =T20D35746[[#This Row],[配当]]/T20D35746[[#This Row],[現在値]] -> 0.020174849 | O107: =ROUND( ((IF(OR(R107="",R107<=0),20,R107)/20) *(L107/15)) /(IFERROR(IF(H107>0,H107,15),15)/15) *100,0) -> 254 | P107: =ROUND( ((IF(OR(R107="",R107<=0),20,R107)/20) *(L107/15) *((MIN(MAX(S107,0),50)/15)+1) *(1+MIN(MAX(IFERROR(IF(W107="",0,W107),0),-30),50)/200)) /(IFERROR(IF(H107>0,H107,15),15)/15) *100,0) -> 982 | Q107: =T20D35746[[#This Row],[スコア⑤]]/T20D35746[[#This Row],[スコア③]] -> 3.8661417 | R107: 26.43 | S107: 70.91 | T107: 9.05 | U107: 27.8 | V107: 88.3 | W107: =(T20D35746[[#This Row],[現金及び預金（億）]]-T20D35746[[#This Row],[負債（億）]])/T20D35746[[#This Row],[総資産]]*100 -> -21.234428
A108: 4222 | B108: =IFERROR(_xll.RssMarket($A108,"銘柄名称"),"") -> 児玉化学 | C108: =IFERROR(_xll.RssMarket($A108,"市場部略称"),"") -> 東Ｓ | D108: =IFERROR(_xll.RssMarket($A108,"現在値"),"") -> 892 | E108: =IFERROR(_xll.RssMarket($A108,"前日比"),"") -> -60 | F108: =IFERROR(_xll.RssMarket($A108,"時価総額"),"") -> 13948 | G108: =T20D35746[[#This Row],[時価総額]]/T20D35746[[#This Row],[現在値]] -> 15.636771 | H108: =IFERROR(_xll.RssMarket($A108,"PER"),"") -> 0.69 | I108: =T20D35746[[#This Row],[現在値]] / IFERROR(IF(T20D35746[[#This Row],[PER]] > 0, T20D35746[[#This Row],[PER]], 15), 15) -> 1292.7536 | J108: =IFERROR(_xll.RssMarket($A108,"PBR"),"") -> 0.52 | K108: =T20D35746[[#This Row],[現在値]]/T20D35746[[#This Row],[PBR]] -> 1715.3846 | L108: =T20D35746[[#This Row],[EPS]]/T20D35746[[#This Row],[BPS]]*100 -> 75.362319 | M108: =IFERROR(_xll.RssMarket($A108,"配当"),"") -> 0 | N108: =T20D35746[[#This Row],[配当]]/T20D35746[[#This Row],[現在値]] -> 0 | O108: =ROUND( ((IF(OR(R108="",R108<=0),20,R108)/20) *(L108/15)) /(IFERROR(IF(H108>0,H108,15),15)/15) *100,0) -> 874 | P108: =ROUND( ((IF(OR(R108="",R108<=0),20,R108)/20) *(L108/15) *((MIN(MAX(S108,0),50)/15)+1) *(1+MIN(MAX(IFERROR(IF(W108="",0,W108),0),-30),50)/200)) /(IFERROR(IF(H108>0,H108,15),15)/15) *100,0) -> 3459 | Q108: =T20D35746[[#This Row],[スコア⑤]]/T20D35746[[#This Row],[スコア③]] -> 3.9576659 | R108: 1.6 | S108: 374.68 | T108: 9.82 | U108: 34.2 | V108: 141 | W108: =(T20D35746[[#This Row],[現金及び預金（億）]]-T20D35746[[#This Row],[負債（億）]])/T20D35746[[#This Row],[総資産]]*100 -> -17.29078
...

Sheet 割安チェック  (2)
A1: コード(手入力） | B1: 銘柄名（RSS） | C1: 市場部 | D1: 現在値 | E1: 前日比 | F1: 時価総額 | G1: 株式数 （百万） | H1: PER | I1: EPS | J1: PBR | K1: BPS | L1: ROE | M1: 配当 | N1: 配当率 | O1: スコア③ | P1: スコア⑤ | Q1: Gap比 | R1: 営業利益 率（予） | S1: 成長率 | T1: 現金及び預金（億） | U1: 負債（億） | V1: 総資産 | W1: ネットキャッシュ比率 | X1: 列1
A2: 2038 | B2: =IFERROR(_xll.RssMarket($A2,"銘柄名称"),"") -> ＮＮ原油ダブル・ブル | C2: =IFERROR(_xll.RssMarket($A2,"市場部略称"),"") -> 東Ｐ | D2: =IFERROR(_xll.RssMarket($A2,"現在値"),"") -> 1551 | E2: =IFERROR(_xll.RssMarket($A2,"前日比"),"") -> -85 | F2: =IFERROR(_xll.RssMarket($A2,"時価総額"),"") -> 0 | G2: =T20D357462[[#This Row],[時価総額]]/T20D357462[[#This Row],[現在値]] -> 0 | H2: =IFERROR(_xll.RssMarket($A2,"PER"),"") -> 0 | I2: =T20D357462[[#This Row],[現在値]] / IFERROR(IF(T20D357462[[#This Row],[PER]] > 0, T20D357462[[#This Row],[PER]], 15), 15) -> 103.4 | J2: =IFERROR(_xll.RssMarket($A2,"PBR"),"") -> 0 | K2: =T20D357462[[#This Row],[現在値]]/T20D357462[[#This Row],[PBR]] -> #DIV/0! | L2: =T20D357462[[#This Row],[EPS]]/T20D357462[[#This Row],[BPS]]*100 -> #DIV/0! | M2: =IFERROR(_xll.RssMarket($A2,"配当"),"") -> 0 | N2: =T20D357462[[#This Row],[配当]]/T20D357462[[#This Row],[現在値]] -> 0 | O2: =ROUND( ((IF(OR(R2="",R2<=0),20,R2)/20) *(L2/15)) /(IFERROR(IF(H2>0,H2,15),15)/15) *100,0) -> #DIV/0! | P2: =ROUND( ((IF(OR(R2="",R2<=0),20,R2)/20) *(L2/15) *((MIN(MAX(S2,0),50)/15)+1) *(1+MIN(MAX(IFERROR(IF(W2="",0,W2),0),-30),50)/200)) /(IFERROR(IF(H2>0,H2,15),15)/15) *100,0) -> #DIV/0! | Q2: =T20D357462[[#This Row],[スコア⑤]]/T20D357462[[#This Row],[スコア③]] -> #DIV/0! | S2: 16 | T2: 143 | U2: 520 | V2: 1268 | W2: =(T20D357462[[#This Row],[現金及び預金（億）]]-T20D357462[[#This Row],[負債（億）]])/T20D357462[[#This Row],[総資産]]*100 -> -29.731861
A3: 2849 | B3: =IFERROR(_xll.RssMarket($A3,"銘柄名称"),"") -> ＧＸ高配当ＥＳＧ日株 | C3: =IFERROR(_xll.RssMarket($A3,"市場部略称"),"") -> 東Ｐ | D3: =IFERROR(_xll.RssMarket($A3,"現在値"),"") -> 5293 | E3: =IFERROR(_xll.RssMarket($A3,"前日比"),"") -> -12 | F3: =IFERROR(_xll.RssMarket($A3,"時価総額"),"") -> 0 | G3: =T20D357462[[#This Row],[時価総額]]/T20D357462[[#This Row],[現在値]] -> 0 | H3: =IFERROR(_xll.RssMarket($A3,"PER"),"") -> 0 | I3: =T20D357462[[#This Row],[現在値]] / IFERROR(IF(T20D357462[[#This Row],[PER]] > 0, T20D357462[[#This Row],[PER]], 15), 15) -> 352.86667 | J3: =IFERROR(_xll.RssMarket($A3,"PBR"),"") -> 0 | K3: =T20D357462[[#This Row],[現在値]]/T20D357462[[#This Row],[PBR]] -> #DIV/0! | L3: =T20D357462[[#This Row],[EPS]]/T20D357462[[#This Row],[BPS]]*100 -> #DIV/0! | M3: =IFERROR(_xll.RssMarket($A3,"配当"),"") -> 0 | N3: =T20D357462[[#This Row],[配当]]/T20D357462[[#This Row],[現在値]] -> 0 | O3: =ROUND( ((IF(OR(R3="",R3<=0),20,R3)/20) *(L3/15)) /(IFERROR(IF(H3>0,H3,15),15)/15) *100,0) -> #DIV/0! | P3: =ROUND( ((IF(OR(R3="",R3<=0),20,R3)/20) *(L3/15) *((MIN(MAX(S3,0),50)/15)+1) *(1+MIN(MAX(IFERROR(IF(W3="",0,W3),0),-30),50)/200)) /(IFERROR(IF(H3>0,H3,15),15)/15) *100,0) -> #DIV/0! | Q3: =T20D357462[[#This Row],[スコア⑤]]/T20D357462[[#This Row],[スコア③]] -> #DIV/0! | T3: 9212 | U3: 44400 | V3: 169000 | W3: =(T20D357462[[#This Row],[現金及び預金（億）]]-T20D357462[[#This Row],[負債（億）]])/T20D357462[[#This Row],[総資産]]*100 -> -20.821302
A4: 467A | B4: =IFERROR(_xll.RssMarket($A4,"銘柄名称"),"") -> ＧＸＵＳ適格社債Ｈ有 | C4: =IFERROR(_xll.RssMarket($A4,"市場部略称"),"") -> 東Ｐ | D4: =IFERROR(_xll.RssMarket($A4,"現在値"),"") -> 300 | E4: =IFERROR(_xll.RssMarket($A4,"前日比"),"") -> 0.7 | F4: =IFERROR(_xll.RssMarket($A4,"時価総額"),"") -> 0 | G4: =T20D357462[[#This Row],[時価総額]]/T20D357462[[#This Row],[現在値]] -> 0 | H4: =IFERROR(_xll.RssMarket($A4,"PER"),"") -> 0 | I4: =T20D357462[[#This Row],[現在値]] / IFERROR(IF(T20D357462[[#This Row],[PER]] > 0, T20D357462[[#This Row],[PER]], 15), 15) -> 20 | J4: =IFERROR(_xll.RssMarket($A4,"PBR"),"") -> 0 | K4: =T20D357462[[#This Row],[現在値]]/T20D357462[[#This Row],[PBR]] -> #DIV/0! | L4: =T20D357462[[#This Row],[EPS]]/T20D357462[[#This Row],[BPS]]*100 -> #DIV/0! | M4: =IFERROR(_xll.RssMarket($A4,"配当"),"") -> 0 | N4: =T20D357462[[#This Row],[配当]]/T20D357462[[#This Row],[現在値]] -> 0 | O4: =ROUND( ((IF(OR(R4="",R4<=0),20,R4)/20) *(L4/15)) /(IFERROR(IF(H4>0,H4,15),15)/15) *100,0) -> #DIV/0! | P4: =ROUND( ((IF(OR(R4="",R4<=0),20,R4)/20) *(L4/15) *((MIN(MAX(S4,0),50)/15)+1) *(1+MIN(MAX(IFERROR(IF(W4="",0,W4),0),-30),50)/200)) /(IFERROR(IF(H4>0,H4,15),15)/15) *100,0) -> #DIV/0! | Q4: =T20D357462[[#This Row],[スコア⑤]]/T20D357462[[#This Row],[スコア③]] -> #DIV/0! | T4: 8.06 | U4: 7.05 | V4: 31.6 | W4: =(T20D357462[[#This Row],[現金及び預金（億）]]-T20D357462[[#This Row],[負債（億）]])/T20D357462[[#This Row],[総資産]]*100 -> 3.1962025
A5: 6173 | B5: =IFERROR(_xll.RssMarket($A5,"銘柄名称"),"") -> アクアライン | C5: =IFERROR(_xll.RssMarket($A5,"市場部略称"),"") -> 東Ｇ | D5: =IFERROR(_xll.RssMarket($A5,"現在値"),"") -> 177 | E5: =IFERROR(_xll.RssMarket($A5,"前日比"),"") -> -8 | F5: =IFERROR(_xll.RssMarket($A5,"時価総額"),"") -> 1479 | G5: =T20D357462[[#This Row],[時価総額]]/T20D357462[[#This Row],[現在値]] -> 8.3559322 | H5: =IFERROR(_xll.RssMarket($A5,"PER"),"") -> 0 | I5: =T20D357462[[#This Row],[現在値]] / IFERROR(IF(T20D357462[[#This Row],[PER]] > 0, T20D357462[[#This Row],[PER]], 15), 15) -> 11.8 | J5: =IFERROR(_xll.RssMarket($A5,"PBR"),"") -> 0 | K5: =T20D357462[[#This Row],[現在値]]/T20D357462[[#This Row],[PBR]] -> #DIV/0! | L5: =T20D357462[[#This Row],[EPS]]/T20D357462[[#This Row],[BPS]]*100 -> #DIV/0! | M5: =IFERROR(_xll.RssMarket($A5,"配当"),"") -> 0 | N5: =T20D357462[[#This Row],[配当]]/T20D357462[[#This Row],[現在値]] -> 0 | O5: =ROUND( ((IF(OR(R5="",R5<=0),20,R5)/20) *(L5/15)) /(IFERROR(IF(H5>0,H5,15),15)/15) *100,0) -> #DIV/0! | P5: =ROUND( ((IF(OR(R5="",R5<=0),20,R5)/20) *(L5/15) *((MIN(MAX(S5,0),50)/15)+1) *(1+MIN(MAX(IFERROR(IF(W5="",0,W5),0),-30),50)/200)) /(IFERROR(IF(H5>0,H5,15),15)/15) *100,0) -> #DIV/0! | Q5: =T20D357462[[#This Row],[スコア⑤]]/T20D357462[[#This Row],[スコア③]] -> #DIV/0! | T5: 42.6 | U5: 20 | V5: 138 | W5: =(T20D357462[[#This Row],[現金及び預金（億）]]-T20D357462[[#This Row],[負債（億）]])/T20D357462[[#This Row],[総資産]]*100 -> 16.376812
A6: 2484 | B6: =IFERROR(_xll.RssMarket($A6,"銘柄名称"),"") -> 出前館 | C6: =IFERROR(_xll.RssMarket($A6,"市場部略称"),"") -> 東Ｓ | D6: =IFERROR(_xll.RssMarket($A6,"現在値"),"") -> 130 | E6: =IFERROR(_xll.RssMarket($A6,"前日比"),"") -> -7 | F6: =IFERROR(_xll.RssMarket($A6,"時価総額"),"") -> 14609 | G6: =T20D357462[[#This Row],[時価総額]]/T20D357462[[#This Row],[現在値]] -> 112.37692 | H6: =IFERROR(_xll.RssMarket($A6,"PER"),"") -> 0 | I6: =T20D357462[[#This Row],[現在値]] / IFERROR(IF(T20D357462[[#This Row],[PER]] > 0, T20D357462[[#This Row],[PER]], 15), 15) -> 8.6666667 | J6: =IFERROR(_xll.RssMarket($A6,"PBR"),"") -> 0.5 | K6: =T20D357462[[#This Row],[現在値]]/T20D357462[[#This Row],[PBR]] -> 260 | L6: =T20D357462[[#This Row],[EPS]]/T20D357462[[#This Row],[BPS]]*100 -> 3.3333333 | M6: =IFERROR(_xll.RssMarket($A6,"配当"),"") -> 0 | N6: =T20D357462[[#This Row],[配当]]/T20D357462[[#This Row],[現在値]] -> 0 | O6: =ROUND( ((IF(OR(R6="",R6<=0),20,R6)/20) *(L6/15)) /(IFERROR(IF(H6>0,H6,15),15)/15) *100,0) -> 22 | P6: =ROUND( ((IF(OR(R6="",R6<=0),20,R6)/20) *(L6/15) *((MIN(MAX(S6,0),50)/15)+1) *(1+MIN(MAX(IFERROR(IF(W6="",0,W6),0),-30),50)/200)) /(IFERROR(IF(H6>0,H6,15),15)/15) *100,0) -> 20 | Q6: =T20D357462[[#This Row],[スコア⑤]]/T20D357462[[#This Row],[スコア③]] -> 0.90909091 | T6: 448 | U6: 925 | V6: 2182 | W6: =(T20D357462[[#This Row],[現金及び預金（億）]]-T20D357462[[#This Row],[負債（億）]])/T20D357462[[#This Row],[総資産]]*100 -> -21.860678
A7: 1718 | B7: =IFERROR(_xll.RssMarket($A7,"銘柄名称"),"") -> 美樹工業 | C7: =IFERROR(_xll.RssMarket($A7,"市場部略称"),"") -> 東Ｓ | D7: =IFERROR(_xll.RssMarket($A7,"現在値"),"") -> 9590 | E7: =IFERROR(_xll.RssMarket($A7,"前日比"),"") -> -310 | F7: =IFERROR(_xll.RssMarket($A7,"時価総額"),"") -> 11059 | G7: =T20D357462[[#This Row],[時価総額]]/T20D357462[[#This Row],[現在値]] -> 1.1531804 | H7: =IFERROR(_xll.RssMarket($A7,"PER"),"") -> 7.48 | I7: =T20D357462[[#This Row],[現在値]] / IFERROR(IF(T20D357462[[#This Row],[PER]] > 0, T20D357462[[#This Row],[PER]], 15), 15) -> 1282.0856 | J7: =IFERROR(_xll.RssMarket($A7,"PBR"),"") -> 0.64 | K7: =T20D357462[[#This Row],[現在値]]/T20D357462[[#This Row],[PBR]] -> 14984.375 | L7: =T20D357462[[#This Row],[EPS]]/T20D357462[[#This Row],[BPS]]*100 -> 8.5561497 | M7: =IFERROR(_xll.RssMarket($A7,"配当"),"") -> 380 | N7: =T20D357462[[#This Row],[配当]]/T20D357462[[#This Row],[現在値]] -> 0.039624609 | O7: =ROUND( ((IF(OR(R7="",R7<=0),20,R7)/20) *(L7/15)) /(IFERROR(IF(H7>0,H7,15),15)/15) *100,0) -> 114 | P7: =ROUND( ((IF(OR(R7="",R7<=0),20,R7)/20) *(L7/15) *((MIN(MAX(S7,0),50)/15)+1) *(1+MIN(MAX(IFERROR(IF(W7="",0,W7),0),-30),50)/200)) /(IFERROR(IF(H7>0,H7,15),15)/15) *100,0) -> 97 | Q7: =T20D357462[[#This Row],[スコア⑤]]/T20D357462[[#This Row],[スコア③]] -> 0.85087719 | T7: 2569 | U7: 33400 | V7: 80000 | W7: =(T20D357462[[#This Row],[現金及び預金（億）]]-T20D357462[[#This Row],[負債（億）]])/T20D357462[[#This Row],[総資産]]*100 -> -38.53875
A8: 7162 | B8: =IFERROR(_xll.RssMarket($A8,"銘柄名称"),"") -> アストマックス | C8: =IFERROR(_xll.RssMarket($A8,"市場部略称"),"") -> 東Ｓ | D8: =IFERROR(_xll.RssMarket($A8,"現在値"),"") -> 213 | E8: =IFERROR(_xll.RssMarket($A8,"前日比"),"") -> -2 | F8: =IFERROR(_xll.RssMarket($A8,"時価総額"),"") -> 2803 | G8: =T20D357462[[#This Row],[時価総額]]/T20D357462[[#This Row],[現在値]] -> 13.159624 | H8: =IFERROR(_xll.RssMarket($A8,"PER"),"") -> 10.39 | I8: =T20D357462[[#This Row],[現在値]] / IFERROR(IF(T20D357462[[#This Row],[PER]] > 0, T20D357462[[#This Row],[PER]], 15), 15) -> 20.500481 | J8: =IFERROR(_xll.RssMarket($A8,"PBR"),"") -> 0.56 | K8: =T20D357462[[#This Row],[現在値]]/T20D357462[[#This Row],[PBR]] -> 380.35714 | L8: =T20D357462[[#This Row],[EPS]]/T20D357462[[#This Row],[BPS]]*100 -> 5.3897979 | M8: =IFERROR(_xll.RssMarket($A8,"配当"),"") -> 7 | N8: =T20D357462[[#This Row],[配当]]/T20D357462[[#This Row],[現在値]] -> 0.03286385 | O8: =ROUND( ((IF(OR(R8="",R8<=0),20,R8)/20) *(L8/15)) /(IFERROR(IF(H8>0,H8,15),15)/15) *100,0) -> 52 | P8: =ROUND( ((IF(OR(R8="",R8<=0),20,R8)/20) *(L8/15) *((MIN(MAX(S8,0),50)/15)+1) *(1+MIN(MAX(IFERROR(IF(W8="",0,W8),0),-30),50)/200)) /(IFERROR(IF(H8>0,H8,15),15)/15) *100,0) -> 58 | Q8: =T20D357462[[#This Row],[スコア⑤]]/T20D357462[[#This Row],[スコア③]] -> 1.1153846 | T8: 1090000 | U8: 175000 | V8: 4130000 | W8: =(T20D357462[[#This Row],[現金及び預金（億）]]-T20D357462[[#This Row],[負債（億）]])/T20D357462[[#This Row],[総資産]]*100 -> 22.154964
A9: 9478 | B9: =IFERROR(_xll.RssMarket($A9,"銘柄名称"),"") -> ＳＥホール＆インキュベ | C9: =IFERROR(_xll.RssMarket($A9,"市場部略称"),"") -> 東Ｓ | D9: =IFERROR(_xll.RssMarket($A9,"現在値"),"") -> 465 | E9: =IFERROR(_xll.RssMarket($A9,"前日比"),"") -> -1 | F9: =IFERROR(_xll.RssMarket($A9,"時価総額"),"") -> 7944 | G9: =T20D357462[[#This Row],[時価総額]]/T20D357462[[#This Row],[現在値]] -> 17.083871 | H9: =IFERROR(_xll.RssMarket($A9,"PER"),"") -> 16.08 | I9: =T20D357462[[#This Row],[現在値]] / IFERROR(IF(T20D357462[[#This Row],[PER]] > 0, T20D357462[[#This Row],[PER]], 15), 15) -> 28.91791 | J9: =IFERROR(_xll.RssMarket($A9,"PBR"),"") -> 0.73 | K9: =T20D357462[[#This Row],[現在値]]/T20D357462[[#This Row],[PBR]] -> 636.9863 | L9: =T20D357462[[#This Row],[EPS]]/T20D357462[[#This Row],[BPS]]*100 -> 4.539801 | M9: =IFERROR(_xll.RssMarket($A9,"配当"),"") -> 3.5 | N9: =T20D357462[[#This Row],[配当]]/T20D357462[[#This Row],[現在値]] -> 0.0075268817 | O9: =ROUND( ((IF(OR(R9="",R9<=0),20,R9)/20) *(L9/15)) /(IFERROR(IF(H9>0,H9,15),15)/15) *100,0) -> 28 | P9: =ROUND( ((IF(OR(R9="",R9<=0),20,R9)/20) *(L9/15) *((MIN(MAX(S9,0),50)/15)+1) *(1+MIN(MAX(IFERROR(IF(W9="",0,W9),0),-30),50)/200)) /(IFERROR(IF(H9>0,H9,15),15)/15) *100,0) -> 34 | Q9: =T20D357462[[#This Row],[スコア⑤]]/T20D357462[[#This Row],[スコア③]] -> 1.2142857 | T9: 1.83 | U9: 0 | V9: 4.3 | W9: =(T20D357462[[#This Row],[現金及び預金（億）]]-T20D357462[[#This Row],[負債（億）]])/T20D357462[[#This Row],[総資産]]*100 -> 42.55814
A10: 8006 | B10: =IFERROR(_xll.RssMarket($A10,"銘柄名称"),"") -> ユアサ・フナシヨク | C10: =IFERROR(_xll.RssMarket($A10,"市場部略称"),"") -> 東Ｓ | D10: =IFERROR(_xll.RssMarket($A10,"現在値"),"") -> 1770 | E10: =IFERROR(_xll.RssMarket($A10,"前日比"),"") -> -50 | F10: =IFERROR(_xll.RssMarket($A10,"時価総額"),"") -> 34675 | G10: =T20D357462[[#This Row],[時価総額]]/T20D357462[[#This Row],[現在値]] -> 19.590395 | H10: =IFERROR(_xll.RssMarket($A10,"PER"),"") -> 13.02 | I10: =T20D357462[[#This Row],[現在値]] / IFERROR(IF(T20D357462[[#This Row],[PER]] > 0, T20D357462[[#This Row],[PER]], 15), 15) -> 135.9447 | J10: =IFERROR(_xll.RssMarket($A10,"PBR"),"") -> 0.76 | K10: =T20D357462[[#This Row],[現在値]]/T20D357462[[#This Row],[PBR]] -> 2328.9474 | L10: =T20D357462[[#This Row],[EPS]]/T20D357462[[#This Row],[BPS]]*100 -> 5.8371736 | M10: =IFERROR(_xll.RssMarket($A10,"配当"),"") -> 30 | N10: =T20D357462[[#This Row],[配当]]/T20D357462[[#This Row],[現在値]] -> 0.016949153 | O10: =ROUND( ((IF(OR(R10="",R10<=0),20,R10)/20) *(L10/15)) /(IFERROR(IF(H10>0,H10,15),15)/15) *100,0) -> 45 | P10: =ROUND( ((IF(OR(R10="",R10<=0),20,R10)/20) *(L10/15) *((MIN(MAX(S10,0),50)/15)+1) *(1+MIN(MAX(IFERROR(IF(W10="",0,W10),0),-30),50)/200)) /(IFERROR(IF(H10>0,H10,15),15)/15) *100,0) -> 52 | Q10: =T20D357462[[#This Row],[スコア⑤]]/T20D357462[[#This Row],[スコア③]] -> 1.1555556 | T10: 126 | U10: 27.2 | V10: 295 | W10: =(T20D357462[[#This Row],[現金及び預金（億）]]-T20D357462[[#This Row],[負債（億）]])/T20D357462[[#This Row],[総資産]]*100 -> 33.491525
A11: 4365 | B11: =IFERROR(_xll.RssMarket($A11,"銘柄名称"),"") -> 松本油脂製薬 | C11: =IFERROR(_xll.RssMarket($A11,"市場部略称"),"") -> 東Ｓ | D11: =IFERROR(_xll.RssMarket($A11,"現在値"),"") -> 0 | E11: =IFERROR(_xll.RssMarket($A11,"前日比"),"") -> 0 | F11: =IFERROR(_xll.RssMarket($A11,"時価総額"),"") -> 92193 | G11: =T20D357462[[#This Row],[時価総額]]/T20D357462[[#This Row],[現在値]] -> #DIV/0! | H11: =IFERROR(_xll.RssMarket($A11,"PER"),"") -> 10.39 | I11: =T20D357462[[#This Row],[現在値]] / IFERROR(IF(T20D357462[[#This Row],[PER]] > 0, T20D357462[[#This Row],[PER]], 15), 15) -> 0 | J11: =IFERROR(_xll.RssMarket($A11,"PBR"),"") -> 0.71 | K11: =T20D357462[[#This Row],[現在値]]/T20D357462[[#This Row],[PBR]] -> 0 | L11: =T20D357462[[#This Row],[EPS]]/T20D357462[[#This Row],[BPS]]*100 -> #DIV/0! | M11: =IFERROR(_xll.RssMarket($A11,"配当"),"") -> 400 | N11: =T20D357462[[#This Row],[配当]]/T20D357462[[#This Row],[現在値]] -> #DIV/0! | O11: =ROUND( ((IF(OR(R11="",R11<=0),20,R11)/20) *(L11/15)) /(IFERROR(IF(H11>0,H11,15),15)/15) *100,0) -> #DIV/0! | P11: =ROUND( ((IF(OR(R11="",R11<=0),20,R11)/20) *(L11/15) *((MIN(MAX(S11,0),50)/15)+1) *(1+MIN(MAX(IFERROR(IF(W11="",0,W11),0),-30),50)/200)) /(IFERROR(IF(H11>0,H11,15),15)/15) *100,0) -> #DIV/0! | Q11: =T20D357462[[#This Row],[スコア⑤]]/T20D357462[[#This Row],[スコア③]] -> #DIV/0! | T11: 10800 | U11: 17300 | V11: 83700 | W11: =(T20D357462[[#This Row],[現金及び預金（億）]]-T20D357462[[#This Row],[負債（億）]])/T20D357462[[#This Row],[総資産]]*100 -> -7.7658303
A12: 9476 | B12: =IFERROR(_xll.RssMarket($A12,"銘柄名称"),"") -> 中央経済社ＨＬＤＧＳ | C12: =IFERROR(_xll.RssMarket($A12,"市場部略称"),"") -> 東Ｓ | D12: =IFERROR(_xll.RssMarket($A12,"現在値"),"") -> 887 | E12: =IFERROR(_xll.RssMarket($A12,"前日比"),"") -> -2 | F12: =IFERROR(_xll.RssMarket($A12,"時価総額"),"") -> 3901 | G12: =T20D357462[[#This Row],[時価総額]]/T20D357462[[#This Row],[現在値]] -> 4.3979707 | H12: =IFERROR(_xll.RssMarket($A12,"PER"),"") -> 26.39 | I12: =T20D357462[[#This Row],[現在値]] / IFERROR(IF(T20D357462[[#This Row],[PER]] > 0, T20D357462[[#This Row],[PER]], 15), 15) -> 33.611216 | J12: =IFERROR(_xll.RssMarket($A12,"PBR"),"") -> 0.78 | K12: =T20D357462[[#This Row],[現在値]]/T20D357462[[#This Row],[PBR]] -> 1137.1795 | L12: =T20D357462[[#This Row],[EPS]]/T20D357462[[#This Row],[BPS]]*100 -> 2.955665 | M12: =IFERROR(_xll.RssMarket($A12,"配当"),"") -> 13 | N12: =T20D357462[[#This Row],[配当]]/T20D357462[[#This Row],[現在値]] -> 0.014656144 | O12: =ROUND( ((IF(OR(R12="",R12<=0),20,R12)/20) *(L12/15)) /(IFERROR(IF(H12>0,H12,15),15)/15) *100,0) -> 11 | P12: =ROUND( ((IF(OR(R12="",R12<=0),20,R12)/20) *(L12/15) *((MIN(MAX(S12,0),50)/15)+1) *(1+MIN(MAX(IFERROR(IF(W12="",0,W12),0),-30),50)/200)) /(IFERROR(IF(H12>0,H12,15),15)/15) *100,0) -> 14 | Q12: =T20D357462[[#This Row],[スコア⑤]]/T20D357462[[#This Row],[スコア③]] -> 1.2727273 | T12: 24.7 | U12: 4.25 | V12: 48.3 | W12: =(T20D357462[[#This Row],[現金及び預金（億）]]-T20D357462[[#This Row],[負債（億）]])/T20D357462[[#This Row],[総資産]]*100 -> 42.339545
A13: 7989 | B13: =IFERROR(_xll.RssMarket($A13,"銘柄名称"),"") -> 立川ブラインド | C13: =IFERROR(_xll.RssMarket($A13,"市場部略称"),"") -> 東Ｐ | D13: =IFERROR(_xll.RssMarket($A13,"現在値"),"") -> 2518 | E13: =IFERROR(_xll.RssMarket($A13,"前日比"),"") -> -48 | F13: =IFERROR(_xll.RssMarket($A13,"時価総額"),"") -> 52282 | G13: =T20D357462[[#This Row],[時価総額]]/T20D357462[[#This Row],[現在値]] -> 20.763304 | H13: =IFERROR(_xll.RssMarket($A13,"PER"),"") -> 15.1 | I13: =T20D357462[[#This Row],[現在値]] / IFERROR(IF(T20D357462[[#This Row],[PER]] > 0, T20D357462[[#This Row],[PER]], 15), 15) -> 166.75497 | J13: =IFERROR(_xll.RssMarket($A13,"PBR"),"") -> 0.89 | K13: =T20D357462[[#This Row],[現在値]]/T20D357462[[#This Row],[PBR]] -> 2829.2135 | L13: =T20D357462[[#This Row],[EPS]]/T20D357462[[#This Row],[BPS]]*100 -> 5.8940397 | M13: =IFERROR(_xll.RssMarket($A13,"配当"),"") -> 70 | N13: =T20D357462[[#This Row],[配当]]/T20D357462[[#This Row],[現在値]] -> 0.027799841 | O13: =ROUND( ((IF(OR(R13="",R13<=0),20,R13)/20) *(L13/15)) /(IFERROR(IF(H13>0,H13,15),15)/15) *100,0) -> 39 | P13: =ROUND( ((IF(OR(R13="",R13<=0),20,R13)/20) *(L13/15) *((MIN(MAX(S13,0),50)/15)+1) *(1+MIN(MAX(IFERROR(IF(W13="",0,W13),0),-30),50)/200)) /(IFERROR(IF(H13>0,H13,15),15)/15) *100,0) -> 45 | Q13: =T20D357462[[#This Row],[スコア⑤]]/T20D357462[[#This Row],[スコア③]] -> 1.1538462 | T13: 19.7 | U13: 5.26 | V13: 45.2 | W13: =(T20D357462[[#This Row],[現金及び預金（億）]]-T20D357462[[#This Row],[負債（億）]])/T20D357462[[#This Row],[総資産]]*100 -> 31.946903
A14: 6803 | B14: =IFERROR(_xll.RssMarket($A14,"銘柄名称"),"") -> ティアック | C14: =IFERROR(_xll.RssMarket($A14,"市場部略称"),"") -> 東Ｓ | D14: =IFERROR(_xll.RssMarket($A14,"現在値"),"") -> 119 | E14: =IFERROR(_xll.RssMarket($A14,"前日比"),"") -> -3 | F14: =IFERROR(_xll.RssMarket($A14,"時価総額"),"") -> 3442 | G14: =T20D357462[[#This Row],[時価総額]]/T20D357462[[#This Row],[現在値]] -> 28.92437 | H14: =IFERROR(_xll.RssMarket($A14,"PER"),"") -> 34 | I14: =T20D357462[[#This Row],[現在値]] / IFERROR(IF(T20D357462[[#This Row],[PER]] > 0, T20D357462[[#This Row],[PER]], 15), 15) -> 3.5 | J14: =IFERROR(_xll.RssMarket($A14,"PBR"),"") -> 1.02 | K14: =T20D357462[[#This Row],[現在値]]/T20D357462[[#This Row],[PBR]] -> 116.66667 | L14: =T20D357462[[#This Row],[EPS]]/T20D357462[[#This Row],[BPS]]*100 -> 3 | M14: =IFERROR(_xll.RssMarket($A14,"配当"),"") -> 1 | N14: =T20D357462[[#This Row],[配当]]/T20D357462[[#This Row],[現在値]] -> 0.0084033613 | O14: =ROUND( ((IF(OR(R14="",R14<=0),20,R14)/20) *(L14/15)) /(IFERROR(IF(H14>0,H14,15),15)/15) *100,0) -> 9 | P14: =ROUND( ((IF(OR(R14="",R14<=0),20,R14)/20) *(L14/15) *((MIN(MAX(S14,0),50)/15)+1) *(1+MIN(MAX(IFERROR(IF(W14="",0,W14),0),-30),50)/200)) /(IFERROR(IF(H14>0,H14,15),15)/15) *100,0) -> 10 | Q14: =T20D357462[[#This Row],[スコア⑤]]/T20D357462[[#This Row],[スコア③]] -> 1.1111111 | T14: 2611 | U14: 269 | V14: 12400 | W14: =(T20D357462[[#This Row],[現金及び預金（億）]]-T20D357462[[#This Row],[負債（億）]])/T20D357462[[#This Row],[総資産]]*100 -> 18.887097
A15: 3154 | B15: =IFERROR(_xll.RssMarket($A15,"銘柄名称"),"") -> メディアスホールディングス | C15: =IFERROR(_xll.RssMarket($A15,"市場部略称"),"") -> 東Ｐ | D15: =IFERROR(_xll.RssMarket($A15,"現在値"),"") -> 836 | E15: =IFERROR(_xll.RssMarket($A15,"前日比"),"") -> -3 | F15: =IFERROR(_xll.RssMarket($A15,"時価総額"),"") -> 18591 | G15: =T20D357462[[#This Row],[時価総額]]/T20D357462[[#This Row],[現在値]] -> 22.238038 | H15: =IFERROR(_xll.RssMarket($A15,"PER"),"") -> 14.29 | I15: =T20D357462[[#This Row],[現在値]] / IFERROR(IF(T20D357462[[#This Row],[PER]] > 0, T20D357462[[#This Row],[PER]], 15), 15) -> 58.502449 | J15: =IFERROR(_xll.RssMarket($A15,"PBR"),"") -> 0.91 | K15: =T20D357462[[#This Row],[現在値]]/T20D357462[[#This Row],[PBR]] -> 918.68132 | L15: =T20D357462[[#This Row],[EPS]]/T20D357462[[#This Row],[BPS]]*100 -> 6.3680896 | M15: =IFERROR(_xll.RssMarket($A15,"配当"),"") -> 20 | N15: =T20D357462[[#This Row],[配当]]/T20D357462[[#This Row],[現在値]] -> 0.023923445 | O15: =ROUND( ((IF(OR(R15="",R15<=0),20,R15)/20) *(L15/15)) /(IFERROR(IF(H15>0,H15,15),15)/15) *100,0) -> 45 | P15: =ROUND( ((IF(OR(R15="",R15<=0),20,R15)/20) *(L15/15) *((MIN(MAX(S15,0),50)/15)+1) *(1+MIN(MAX(IFERROR(IF(W15="",0,W15),0),-30),50)/200)) /(IFERROR(IF(H15>0,H15,15),15)/15) *100,0) -> 41 | Q15: =T20D357462[[#This Row],[スコア⑤]]/T20D357462[[#This Row],[スコア③]] -> 0.91111111 | T15: 40.3 | U15: 67.2 | V15: 151 | W15: =(T20D357462[[#This Row],[現金及び預金（億）]]-T20D357462[[#This Row],[負債（億）]])/T20D357462[[#This Row],[総資産]]*100 -> -17.81457
A16: 7270 | B16: =IFERROR(_xll.RssMarket($A16,"銘柄名称"),"") -> ＳＵＢＡＲＵ | C16: =IFERROR(_xll.RssMarket($A16,"市場部略称"),"") -> 東Ｐ | D16: =IFERROR(_xll.RssMarket($A16,"現在値"),"") -> 3165 | E16: =IFERROR(_xll.RssMarket($A16,"前日比"),"") -> 19 | F16: =IFERROR(_xll.RssMarket($A16,"時価総額"),"") -> 2270366 | G16: =T20D357462[[#This Row],[時価総額]]/T20D357462[[#This Row],[現在値]] -> 717.33523 | H16: =IFERROR(_xll.RssMarket($A16,"PER"),"") -> 18.11 | I16: =T20D357462[[#This Row],[現在値]] / IFERROR(IF(T20D357462[[#This Row],[PER]] > 0, T20D357462[[#This Row],[PER]], 15), 15) -> 174.76532 | J16: =IFERROR(_xll.RssMarket($A16,"PBR"),"") -> 0.83 | K16: =T20D357462[[#This Row],[現在値]]/T20D357462[[#This Row],[PBR]] -> 3813.253 | L16: =T20D357462[[#This Row],[EPS]]/T20D357462[[#This Row],[BPS]]*100 -> 4.5831033 | M16: =IFERROR(_xll.RssMarket($A16,"配当"),"") -> 115 | N16: =T20D357462[[#This Row],[配当]]/T20D357462[[#This Row],[現在値]] -> 0.036334913 | O16: =ROUND( ((IF(OR(R16="",R16<=0),20,R16)/20) *(L16/15)) /(IFERROR(IF(H16>0,H16,15),15)/15) *100,0) -> 25 | P16: =ROUND( ((IF(OR(R16="",R16<=0),20,R16)/20) *(L16/15) *((MIN(MAX(S16,0),50)/15)+1) *(1+MIN(MAX(IFERROR(IF(W16="",0,W16),0),-30),50)/200)) /(IFERROR(IF(H16>0,H16,15),15)/15) *100,0) -> 28 | Q16: =T20D357462[[#This Row],[スコア⑤]]/T20D357462[[#This Row],[スコア③]] -> 1.12 | T16: 3748 | U16: 219 | V16: 15400 | W16: =(T20D357462[[#This Row],[現金及び預金（億）]]-T20D357462[[#This Row],[負債（億）]])/T20D357462[[#This Row],[総資産]]*100 -> 22.915584
... A18: 6769 | B18: =IFERROR(_xll.RssMarket($A18,"銘柄名称"),"") -> ザインエレクトロニクス | C18: =IFERROR(_xll.RssMarket($A18,"市場部略称"),"") -> 東Ｓ | D18: =IFERROR(_xll.RssMarket($A18,"現在値"),"") -> 827 | E18: =IFERROR(_xll.RssMarket($A18,"前日比"),"") -> -6 | F18: =IFERROR(_xll.RssMarket($A18,"時価総額"),"") -> 10205 | G18: =T20D357462[[#This Row],[時価総額]]/T20D357462[[#This Row],[現在値]] -> 12.339782 | H18: =IFERROR(_xll.RssMarket($A18,"PER"),"") -> 2756.66 | I18: =T20D357462[[#This Row],[現在値]] / IFERROR(IF(T20D357462[[#This Row],[PER]] > 0, T20D357462[[#This Row],[PER]], 15), 15) -> 0.30000073 | J18: =IFERROR(_xll.RssMarket($A18,"PBR"),"") -> 0.99 | K18: =T20D357462[[#This Row],[現在値]]/T20D357462[[#This Row],[PBR]] -> 835.35354 | L18: =T20D357462[[#This Row],[EPS]]/T20D357462[[#This Row],[BPS]]*100 -> 0.035913025 | M18: =IFERROR(_xll.RssMarket($A18,"配当"),"") -> 15 | N18: =T20D357462[[#This Row],[配当]]/T20D357462[[#This Row],[現在値]] -> 0.018137848 | O18: =ROUND( ((IF(OR(R18="",R18<=0),20,R18)/20) *(L18/15)) /(IFERROR(IF(H18>0,H18,15),15)/15) *100,0) -> 0 | P18: =ROUND( ((IF(OR(R18="",R18<=0),20,R18)/20) *(L18/15) *((MIN(MAX(S18,0),50)/15)+1) *(1+MIN(MAX(IFERROR(IF(W18="",0,W18),0),-30),50)/200)) /(IFERROR(IF(H18>0,H18,15),15)/15) *100,0) -> 0 | Q18: =T20D357462[[#This Row],[スコア⑤]]/T20D357462[[#This Row],[スコア③]] -> #DIV/0! | T18: 75.1 | U18: 31.6 | V18: 231 | W18: =(T20D357462[[#This Row],[現金及び預金（億）]]-T20D357462[[#This Row],[負債（億）]])/T20D357462[[#This Row],[総資産]]*100 -> 18.831169
A19: 9165 | B19: =IFERROR(_xll.RssMarket($A19,"銘柄名称"),"") -> クオルテック | C19: =IFERROR(_xll.RssMarket($A19,"市場部略称"),"") -> 東Ｇ | D19: =IFERROR(_xll.RssMarket($A19,"現在値"),"") -> 1600 | E19: =IFERROR(_xll.RssMarket($A19,"前日比"),"") -> 25 | F19: =IFERROR(_xll.RssMarket($A19,"時価総額"),"") -> 3760 | G19: =T20D357462[[#This Row],[時価総額]]/T20D357462[[#This Row],[現在値]] -> 2.35 | H19: =IFERROR(_xll.RssMarket($A19,"PER"),"") -> 13.92 | I19: =T20D357462[[#This Row],[現在値]] / IFERROR(IF(T20D357462[[#This Row],[PER]] > 0, T20D357462[[#This Row],[PER]], 15), 15) -> 114.94253 | J19: =IFERROR(_xll.RssMarket($A19,"PBR"),"") -> 1.14 | K19: =T20D357462[[#This Row],[現在値]]/T20D357462[[#This Row],[PBR]] -> 1403.5088 | L19: =T20D357462[[#This Row],[EPS]]/T20D357462[[#This Row],[BPS]]*100 -> 8.1896552 | M19: =IFERROR(_xll.RssMarket($A19,"配当"),"") -> 37 | N19: =T20D357462[[#This Row],[配当]]/T20D357462[[#This Row],[現在値]] -> 0.023125 | O19: =ROUND( ((IF(OR(R19="",R19<=0),20,R19)/20) *(L19/15)) /(IFERROR(IF(H19>0,H19,15),15)/15) *100,0) -> 59 | P19: =ROUND( ((IF(OR(R19="",R19<=0),20,R19)/20) *(L19/15) *((MIN(MAX(S19,0),50)/15)+1) *(1+MIN(MAX(IFERROR(IF(W19="",0,W19),0),-30),50)/200)) /(IFERROR(IF(H19>0,H19,15),15)/15) *100,0) -> 70 | Q19: =T20D357462[[#This Row],[スコア⑤]]/T20D357462[[#This Row],[スコア③]] -> 1.1864407 | T19: 19.1 | U19: 5.13 | V19: 36.7 | W19: 38.065395
A20: 7615 | B20: =IFERROR(_xll.RssMarket($A20,"銘柄名称"),"") -> 京都きもの友禅ＨＤ | C20: =IFERROR(_xll.RssMarket($A20,"市場部略称"),"") -> 東Ｓ | D20: =IFERROR(_xll.RssMarket($A20,"現在値"),"") -> 172 | E20: =IFERROR(_xll.RssMarket($A20,"前日比"),"") -> -20 | F20: =IFERROR(_xll.RssMarket($A20,"時価総額"),"") -> 3445 | G20: =T20D357462[[#This Row],[時価総額]]/T20D357462[[#This Row],[現在値]] -> 20.02907 | H20: =IFERROR(_xll.RssMarket($A20,"PER"),"") -> 10.95 | I20: =T20D357462[[#This Row],[現在値]] / IFERROR(IF(T20D357462[[#This Row],[PER]] > 0, T20D357462[[#This Row],[PER]], 15), 15) -> 15.707763 | J20: =IFERROR(_xll.RssMarket($A20,"PBR"),"") -> 1.17 | K20: =T20D357462[[#This Row],[現在値]]/T20D357462[[#This Row],[PBR]] -> 147.00855 | L20: =T20D357462[[#This Row],[EPS]]/T20D357462[[#This Row],[BPS]]*100 -> 10.684932 | M20: =IFERROR(_xll.RssMarket($A20,"配当"),"") -> 0 | N20: =T20D357462[[#This Row],[配当]]/T20D357462[[#This Row],[現在値]] -> 0 | O20: =ROUND( ((IF(OR(R20="",R20<=0),20,R20)/20) *(L20/15)) /(IFERROR(IF(H20>0,H20,15),15)/15) *100,0) -> 98 | P20: =ROUND( ((IF(OR(R20="",R20<=0),20,R20)/20) *(L20/15) *((MIN(MAX(S20,0),50)/15)+1) *(1+MIN(MAX(IFERROR(IF(W20="",0,W20),0),-30),50)/200)) /(IFERROR(IF(H20>0,H20,15),15)/15) *100,0) -> 109 | Q20: =T20D357462[[#This Row],[スコア⑤]]/T20D357462[[#This Row],[スコア③]] -> 1.1122449 | T20: 65.7 | U20: 31.1 | V20: 142 | W20: =(T20D357462[[#This Row],[現金及び預金（億）]]-T20D357462[[#This Row],[負債（億）]])/T20D357462[[#This Row],[総資産]]*100 -> 24.366197
A21: 5214 | B21: =IFERROR(_xll.RssMarket($A21,"銘柄名称"),"") -> 日本電気硝子 | C21: =IFERROR(_xll.RssMarket($A21,"市場部略称"),"") -> 東Ｐ | D21: =IFERROR(_xll.RssMarket($A21,"現在値"),"") -> 5700 | E21: =IFERROR(_xll.RssMarket($A21,"前日比"),"") -> -305 | F21: =IFERROR(_xll.RssMarket($A21,"時価総額"),"") -> 510282 | G21: =T20D357462[[#This Row],[時価総額]]/T20D357462[[#This Row],[現在値]] -> 89.523158 | H21: =IFERROR(_xll.RssMarket($A21,"PER"),"") -> 18.64 | I21: =T20D357462[[#This Row],[現在値]] / IFERROR(IF(T20D357462[[#This Row],[PER]] > 0, T20D357462[[#This Row],[PER]], 15), 15) -> 305.79399 | J21: =IFERROR(_xll.RssMarket($A21,"PBR"),"") -> 0.87 | K21: =T20D357462[[#This Row],[現在値]]/T20D357462[[#This Row],[PBR]] -> 6551.7241 | L21: =T20D357462[[#This Row],[EPS]]/T20D357462[[#This Row],[BPS]]*100 -> 4.667382 | M21: =IFERROR(_xll.RssMarket($A21,"配当"),"") -> 160 | N21: =T20D357462[[#This Row],[配当]]/T20D357462[[#This Row],[現在値]] -> 0.028070175 | O21: =ROUND( ((IF(OR(R21="",R21<=0),20,R21)/20) *(L21/15)) /(IFERROR(IF(H21>0,H21,15),15)/15) *100,0) -> 25 | P21: =ROUND( ((IF(OR(R21="",R21<=0),20,R21)/20) *(L21/15) *((MIN(MAX(S21,0),50)/15)+1) *(1+MIN(MAX(IFERROR(IF(W21="",0,W21),0),-30),50)/200)) /(IFERROR(IF(H21>0,H21,15),15)/15) *100,0) -> 26 | Q21: =T20D357462[[#This Row],[スコア⑤]]/T20D357462[[#This Row],[スコア③]] -> 1.04 | T21: 44300 | U21: 0 | V21: 568000 | W21: =(T20D357462[[#This Row],[現金及び預金（億）]]-T20D357462[[#This Row],[負債（億）]])/T20D357462[[#This Row],[総資産]]*100 -> 7.7992958
A22: 7062 | B22: =IFERROR(_xll.RssMarket($A22,"銘柄名称"),"") -> フレアス | C22: =IFERROR(_xll.RssMarket($A22,"市場部略称"),"") -> 東Ｇ | D22: =IFERROR(_xll.RssMarket($A22,"現在値"),"") -> 823 | E22: =IFERROR(_xll.RssMarket($A22,"前日比"),"") -> -10 | F22: =IFERROR(_xll.RssMarket($A22,"時価総額"),"") -> 2146 | G22: =T20D357462[[#This Row],[時価総額]]/T20D357462[[#This Row],[現在値]] -> 2.6075334 | H22: =IFERROR(_xll.RssMarket($A22,"PER"),"") -> 5.5 | I22: =T20D357462[[#This Row],[現在値]] / IFERROR(IF(T20D357462[[#This Row],[PER]] > 0, T20D357462[[#This Row],[PER]], 15), 15) -> 149.63636 | J22: =IFERROR(_xll.RssMarket($A22,"PBR"),"") -> 1.1 | K22: =T20D357462[[#This Row],[現在値]]/T20D357462[[#This Row],[PBR]] -> 748.18182 | L22: =T20D357462[[#This Row],[EPS]]/T20D357462[[#This Row],[BPS]]*100 -> 20 | M22: =IFERROR(_xll.RssMarket($A22,"配当"),"") -> 0 | N22: =T20D357462[[#This Row],[配当]]/T20D357462[[#This Row],[現在値]] -> 0 | O22: =ROUND( ((IF(OR(R22="",R22<=0),20,R22)/20) *(L22/15)) /(IFERROR(IF(H22>0,H22,15),15)/15) *100,0) -> 364 | P22: =ROUND( ((IF(OR(R22="",R22<=0),20,R22)/20) *(L22/15) *((MIN(MAX(S22,0),50)/15)+1) *(1+MIN(MAX(IFERROR(IF(W22="",0,W22),0),-30),50)/200)) /(IFERROR(IF(H22>0,H22,15),15)/15) *100,0) -> 399 | Q22: =T20D357462[[#This Row],[スコア⑤]]/T20D357462[[#This Row],[スコア③]] -> 1.0961538 | T22: 707000 | U22: 150000 | V22: 2830000 | W22: =(T20D357462[[#This Row],[現金及び預金（億）]]-T20D357462[[#This Row],[負債（億）]])/T20D357462[[#This Row],[総資産]]*100 -> 19.681979
A23: 6633 | B23: =IFERROR(_xll.RssMarket($A23,"銘柄名称"),"") -> ＣＧＳホールディングス | C23: =IFERROR(_xll.RssMarket($A23,"市場部略称"),"") -> 東Ｓ | D23: =IFERROR(_xll.RssMarket($A23,"現在値"),"") -> 411 | E23: =IFERROR(_xll.RssMarket($A23,"前日比"),"") -> 0 | F23: =IFERROR(_xll.RssMarket($A23,"時価総額"),"") -> 4028 | G23: =T20D357462[[#This Row],[時価総額]]/T20D357462[[#This Row],[現在値]] -> 9.8004866 | H23: =IFERROR(_xll.RssMarket($A23,"PER"),"") -> 13.93 | I23: =T20D357462[[#This Row],[現在値]] / IFERROR(IF(T20D357462[[#This Row],[PER]] > 0, T20D357462[[#This Row],[PER]], 15), 15) -> 29.504666 | J23: =IFERROR(_xll.RssMarket($A23,"PBR"),"") -> 1.21 | K23: =T20D357462[[#This Row],[現在値]]/T20D357462[[#This Row],[PBR]] -> 339.66942 | L23: =T20D357462[[#This Row],[EPS]]/T20D357462[[#This Row],[BPS]]*100 -> 8.6862886 | M23: =IFERROR(_xll.RssMarket($A23,"配当"),"") -> 10 | N23: =T20D357462[[#This Row],[配当]]/T20D357462[[#This Row],[現在値]] -> 0.0243309 | O23: =ROUND( ((IF(OR(R23="",R23<=0),20,R23)/20) *(L23/15)) /(IFERROR(IF(H23>0,H23,15),15)/15) *100,0) -> 62 | P23: =ROUND( ((IF(OR(R23="",R23<=0),20,R23)/20) *(L23/15) *((MIN(MAX(S23,0),50)/15)+1) *(1+MIN(MAX(IFERROR(IF(W23="",0,W23),0),-30),50)/200)) /(IFERROR(IF(H23>0,H23,15),15)/15) *100,0) -> 68 | Q23: =T20D357462[[#This Row],[スコア⑤]]/T20D357462[[#This Row],[スコア③]] -> 1.0967742 | T23: 552 | U23: 27.2 | V23: 2836 | W23: =(T20D357462[[#This Row],[現金及び預金（億）]]-T20D357462[[#This Row],[負債（億）]])/T20D357462[[#This Row],[総資産]]*100 -> 18.504937
